Workbook
Name AICPA: #REF!
Name AICPA: #REF!
Name Automated: #REF!
Name Automated: #REF!
Name CBInspection10a: 'Control Activity-1 - v2016'!$A$57
Name CBInspection10a: 'Control Activity-2 - v2016'!$A$57
Name CBInspection10a: 'Master Control Activity v2016'!$A$57
Name CBInspection10b: 'Control Activity-1 - v2016'!$H$57
Name CBInspection10b: 'Control Activity-2 - v2016'!$H$57
Name CBInspection10b: 'Master Control Activity v2016'!$H$57
Name CBInspection20a: 'Control Activity-1 - v2016'!$A$58
Name CBInspection20a: 'Control Activity-2 - v2016'!$A$58
Name CBInspection20a: 'Master Control Activity v2016'!$A$58
Name CBInspection20b: 'Control Activity-1 - v2016'!$H$58
Name CBInspection20b: 'Control Activity-2 - v2016'!$H$58
Name CBInspection20b: 'Master Control Activity v2016'!$H$58
Name CBInspection30a: 'Control Activity-1 - v2016'!$A$59
Name CBInspection30a: 'Control Activity-2 - v2016'!$A$59
Name CBInspection30a: 'Master Control Activity v2016'!$A$59
Name CBInspection30b: 'Control Activity-1 - v2016'!$H$59
Name CBInspection30b: 'Control Activity-2 - v2016'!$H$59
Name CBInspection30b: 'Master Control Activity v2016'!$H$59
Name CBInspection40a: 'Control Activity-1 - v2016'!$A$60
Name CBInspection40a: 'Control Activity-2 - v2016'!$A$60
Name CBInspection40a: 'Master Control Activity v2016'!$A$60
Name CBInspection40b: 'Control Activity-1 - v2016'!$H$60
Name CBInspection40b: 'Control Activity-2 - v2016'!$H$60
Name CBInspection40b: 'Master Control Activity v2016'!$H$60
Name CBInspection50a: 'Control Activity-1 - v2016'!$A$61
Name CBInspection50a: 'Control Activity-2 - v2016'!$A$61
Name CBInspection50a: 'Master Control Activity v2016'!$A$61
Name CBInspection50b: 'Control Activity-1 - v2016'!$H$61
Name CBInspection50b: 'Control Activity-2 - v2016'!$H$61
Name CBInspection50b: 'Master Control Activity v2016'!$H$61
Name CBInspection60a: 'Control Activity-1 - v2016'!$A$62
Name CBInspection60a: 'Control Activity-2 - v2016'!$A$62
Name CBInspection60a: 'Master Control Activity v2016'!$A$62
Name CBInspection60b: 'Control Activity-1 - v2016'!$H$62
Name CBInspection60b: 'Control Activity-2 - v2016'!$H$62
Name CBInspection60b: 'Master Control Activity v2016'!$H$62
Name CBInspection70a: 'Control Activity-1 - v2016'!$A$63
Name CBInspection70a: 'Control Activity-2 - v2016'!$A$63
Name CBInspection70a: 'Master Control Activity v2016'!$A$63
Name CBInspection70b: 'Control Activity-1 - v2016'!$H$63
Name CBInspection70b: 'Control Activity-2 - v2016'!$H$63
Name CBInspection70b: 'Master Control Activity v2016'!$H$63
Name ControlDesignStarter: 'Master Control Design'!$A$11
Name ControlType: #REF!
Name ControlType: #REF!
Name Debug: 'Drop down'!$C$16
Name DesignEvaluationRow: DataSheet!$B$14:$R$14
Name DesiredEvidence: 'Drop down'!$I$6:$I$9
Name DesiredEvidence: 'Drop down'!$I$6:$I$9
Name DoNotUncheckBoxes123456: 'Control Activity-1 - v2016'!$A$2
Name DoNotUncheckBoxes123456: 'Control Activity-2 - v2016'!$A$2
Name DoNotUncheckBoxes123456: 'Master Control Activity v2016'!$A$2
Name DoNotUncheckBoxes123456: 'Master Control Design'!$A$2
Name DoNotUncheckBoxes123456: 'Master Procedures (1)'!$A$2
Name DoNotUncheckBoxes123456: 'Master Procedures (10)'!$A$2
Name DoNotUncheckBoxes123456: 'Master Procedures (11)'!$A$2

Sheet Master Procedures (51)
B1: Prior year control testing documentation rolled forward for reference purposes.
B2: Perform testing using inquiry, observation, inspection and reperformance
B3: When more than one preparer was involved in the completion of this EGA, document the names of the team members involved and the procedures performed. | G3: [Document the initials or names of team members and procedures performed (e.g., Jane Doe performed step a) below)]
B6: Intrusion prevention/detection and monitoring (PCAOB engagements)
B7: Procedures | G7: Results | L7: Links
B8: a) | C8: Verify whether there have been changes to the design of the control. | H8: Verified whether there have been changes to the design of the control, and
I9: No changes were noted in the design of the control, or
I10: Changes were noted in the design of the control.
H11: [Document procedures performed and changes, as necessary]
B13: b) | C13: Inquiry Inquire of personnel knowledgeable of the control to test the various aspects of the control. | H13: Not applicable. Additional inquiry not performed. | N13: TRUE
G14: OR
H15: Inquired and documented in a related EGA addressing the understanding and evaluation of entity's ITGCs or in a related EGA addressing the understanding and evaluation of entity's internal control.
C17: Note: One Cyber resources are available to assist US engagement teams with the completion of this EGA. For non-US teams consider engaging similar specialist support available in your territory.
H18: [provide link]
G20: OR
H21: Inquired of personnel knowledgeable of the control considering the various aspects of the control (including any automated control components):
H23: - | I23: Policies and/or procedures related to the entity's security incident monitoring program.
I24: - | J24: Whether an in-house group (e.g., Security Operation Center) is used to manage the security incident management program, or whether the program (or aspects thereof) are outsourced to a third party service organization (i.e. Managed Security Service Provider).
I27: - | J27: The mechanisms used by the entity to monitor its security incident monitoring program, such as a dedicated tool, or through an embedded security function (e.g. next generation firewall system).
I30: - | J30: How management ensures that all networks and technology assets related to financially significant systems are considered in the security incident monitoring program.
H32: - | I32: An understanding of how the entity has architected its network, including:
I33: - | J33: How the entity segments its network across all systems and areas of operation, as well as how access between network segments (i.e., between Virtual Local Area Networks or “VLANs”) are restricted.
I36: - | J36: How the entity protects its network through firewalls, demilitarized zones (“DMZs”) and other security incident protection measures.
J39: A demilitarized zone or "DMZ" is a segment of a Company's network carved off and isolated from the rest of its network. A firewall is used to restrict and monitor traffic between the DMZ and trusted and untrusted sources that the DMZ is exposed to, such as a separate DMZ or the internet. A Company may choose to use a combination of DMZs and firewalls to protect its IT environment
H45: - | I45: Whether logs are configured to identify potential security incidents, and
I46: - | J46: Whether an alerting mechanism is in place to notify relevant personnel of potential security incidents.
I48: - | J48: Whether access to the logs is restricted to appropriate personnel.
I49: - | J49: How the logs are analyzed to identify potential security incidents warranting further investigation.
I51: - | J51: Whether the logs are complete and inclusive of all potential security incidents identified in the environment.
H53: - | I53: Whether a process is in place to assess, risk categorize and address identified security incidents.
H54: - | I54: How the security incident monitoring program is used to assess, risk categorize and address identified security incidents.
I56: - | J56: The framework and criteria used by the entity to assess and risk categorize identified security incidents.
I58: - | J58: Whether a root cause analysis is performed for identified security incidents.
I59: - | J59: Whether defined service level objectives are in place for addressing identified security incidents based on risk categorization.
I61: - | J61: How evidence of investigation and remediation of identified security incidents is retained (e.g. a dedicated case management system).
I63: - | J63: How relevant stakeholders are made aware of security incidents.
I64: - | J64: Whether documented playbooks are in place for addressing common or frequently identified security incidents.
I66: - | J66: Whether there is a documented incident response plan and whether the incident plan is periodically tested.
H68: - | I68: Whether periodic network penetration tests are performed.
I69: - | J69: How frequently the tests are performed.
I70: - | J70: How relevant stakeholders are notified of network penetration test results.
H71: - | I71: The period for which the control has been in operation and the frequency of its operation.
H72: - | I72: The appropriateness of the person(s) performing the control(s).
H74: [document the various aspects of the control considered]
H75: [document details, name and date of inquiry]
B77: c) | C77: Observation During the normal course of processing, observe the control operator performing the control. | H77: Not applicable. Observation not performed. | N77: TRUE
G78: OR
H79: Observed and documented in a related EGA addressing the understanding and evaluation of entity's ITGCs or in a related EGA addressing the understanding and evaluation of entity's internal control.
H82: [provide link]
G83: OR
H84: Observed the control operator performing the control.
H85: [document date and details of observation]
B87: d) | C87: Inspection Inspect a sample of evidence of the control performance during the relevant period to determine whether the control has been performed as designed and that exceptions are investigated and resolved on a timely basis. | H87: Not applicable. Inspection not performed. | N87: TRUE
G88: OR
H89: Inspected a sample of evidence of the control performance during the relevant period to determine whether the control has been performed as designed and that exceptions are investigated and resolved on a timely basis. Testing in tab 'ToC Template' or provided link.
G93: OR
H94: Inspected evidence that the status of the entity's intrusion prevention/detection program (security incident monitoring) is periodically monitored and relevant stakeholders (e.g. technology leadership) are updated on the status of the program (e.g. metrics and qualitative information related to identified security incidents)
H98: [document details of inspection]
B100: e) | C100: Reperformance | H100: Not applicable. Reperformance is typically not applicable to the control type chosen | N100: TRUE
B102: f) | C102: Automated control | H102: Not applicable. The control is not automated. | N102: TRUE
C103: Confirm that evidence has been obtained for each of the following: | G103: OR
H104: Tested that ITGCs support continued reliable operation of the automated control by:
C105: i) | D105: ITGCs support continued reliable operation of the automated control; and | I105: Testing the ITGCs, or
I106: [provide link]
C107: ii) | D107: There are no changes in the automated control during the period. | I107: Other [specify]
G108: AND
H109: Tested that the automated control did not change during the period by:
I110: Inspecting/examining the documentation around all of the program changes that impacted the automated control, or
I112: [document details of inspection]
I113: Inspecting/examining the configuration setting in the application, or
I114: [document details of inspection]
I115: Inspecting/examining the system date stamp of last change, or
I116: [document details of inspection]
I117: Other [specify]
G118: AND
H119: No exceptions noted, evidence has been obtained for each item, or
H120: Exceptions noted for at least one item.
H121: [document details and impact on audit plan (e.g., additional testing on the operating effectiveness)]
B126: Guidance (click + to expand):
B128: AUDIT GUIDE
B129: US PwC Audit 3302 - Understand and evaluate the design of ITGCs
B130: US PwC Audit 1206 - Audit evidence
B131: US PwC Audit 5400 - Determine nature, timing and extent of controls testing to be performed
B133: GUIDANCE
B134: ● | C134: Inquiry alone will not provide sufficient evidence to support a conclusion about the effectiveness of a specific control. Consider the need to get further support by examining reports, manuals or other documents used in or generated by the performance of the control.
B136: ● | C136: The control being observed might not be performed in the same manner when the auditors are not present. In addition, observation is pertinent only at a point in time. Consider performing observation of multiple instances of the control, or combining observation with additional testing methods, such as detailed inquiry or inspection of documentation, to gain further evidence about the operation of the control over the period.
B139: ● | C139: When inspecting or reperforming the control at a point in time, consider how to obtain sufficient evidence that a control is operating effectively throughout the audit period (e.g., ITGCs, other evidence of no change, etc.).
B141: ● | C141: Observation, inspection and reperformance may not be possible in all system environments; in such instances, consider alternative testing procedures to address such aspects.
B142: ● | C142: When reperforming a control in a test environment, obtain sufficient evidence to be satisfied that the test instance substantially mirrors the current production environment at the time of testing.
B144: ● | C144: If transactions are not processed uniformly (i.e., if the control operates in a different manner for each type of transaction), testing regarding each transaction type may be appropriate.
B145: ● | C145: Evaluation of the operating effectiveness of an automated control is generally limited to seeing all important aspects of the control operate once (often referred to as a "test of one"). An imperative in the "test of one" concept is that we test all critical attributes or iterations of the control. For each iteration, define conditions that would indicate performance of the control as designed, and what constitutes an exception.
B148: ● | C148: The actions of the control may be determined by a technically complex set of system configurations. Consider whether the use of a specialist in accounting/auditing field is appropriate given the nature and complexity of the application and its processing environment.
B150: ● | C150: Consider whether the control operates at an appropriate level of precision (i.e., threshold used) to address the control objective.
B151: ● | C151: Consider whether the information used in the execution of the control is accurate and reliable. To the extent necessary, consider additional procedures to obtain evidence of the reliability of the data (i.e. completeness, accuracy and validity).
B153: ● | C153: When using sampling techniques for testing:
C154: - | D154: understand the population from which the items will be selected. Consider if the population provides an appropriate base for which to evaluate if the control operated and consider whether the population is complete,
C156: - | D156: consider if the population subject to testing is sufficiently homogeneous to permit it to be treated as one population and, therefore, permit the results of our testing to be appropriately projected to the entire population,
C158: - | D158: consider the frequency of the control and the number of instances of the control,
C159: - | D159: define conditions that would indicate performance of the control as designed, and what constitutes an exception (Note: the absence of documentation evidencing the operation of a control does not in and of itself create the presumption of ineffectiveness of the control. Rather, the auditor must be satisfied that the control actually operated through other corroborating evidence that is sufficiently persuasive).
B162: ● | C162: When exceptions are identified, make inquiries to understand their potential consequences and determine whether:
...

Sheet Master Procedures (52)
B1: Prior year control testing documentation rolled forward for reference purposes.
B2: Perform testing using inquiry, observation, inspection and reperformance
B3: When more than one preparer was involved in the completion of this EGA, document the names of the team members involved and the procedures performed. | G3: [Document the initials or names of team members and procedures performed (e.g., Jane Doe performed step a) below)]
B6: Patch management (PCAOB engagements)
B7: Procedures | G7: Results | L7: Links
B8: a) | C8: Verify whether there have been changes to the design of the control. | H8: Verified whether there have been changes to the design of the control, and
I9: No changes were noted in the design of the control, or
I10: Changes were noted in the design of the control.
H11: [Document procedures performed and changes, as necessary]
B13: b) | C13: Inquiry Inquire of personnel knowledgeable of the control to test the various aspects of the control. | H13: Not applicable. Additional inquiry not performed. | N13: TRUE
G14: OR
H15: Inquired and documented in a related EGA addressing the understanding and evaluation of entity's ITGCs or in a related EGA addressing the understanding and evaluation of entity's internal control.
H18: [provide link]
G19: OR
H20: Inquired of personnel knowledgeable of the control considering the various aspects of the control (including any automated control components):
C21: Note: An organization may structure their patch management process as a component of the overall vulnerability management program. Therefore, in gaining an understanding of an organization's policies and/or procedures related to patch management, it may be necessary to gain a broader understanding of the organization's vulnerability management program, including the policies and/or procedures related to how vulnerabilities are identified, evaluated, and addressed.
H22: - | I22: Obtain an understanding of the entity's patch management program including:
I23: - | J23: Policies and/or procedures related to the entity's patch management program.
I24: - | J24: How the entity is notified of patches by external vendors (e.g., Microsoft for Windows patches).
I26: - | J26: Whether patches are installed automatically or manually, and whether a defined schedule is used to install patches for various technologies, including network devices (e.g., firewalls and virtual private networks), operating systems, applications, and databases.
I29: - | J29: Whether a tool is used to monitor for and deploy patches.
I30: - | J30: Whether documented service level objectives are defined based on the inherent nature of a missing/unapplied patch and/or the type of technology asset (e.g., the service level objective for an internet-facing technology asset may vary from the service level objective for an asset that is not exposed to the internet).
I34: - | J34: The process by which patches are tested prior to being deployed to the production environment.
I36: - | J36: Whether there is a separately defined process for emergency or high priority patches.
I37: - | J37: How management ensures that all technologies, including network devices (e.g., firewalls and virtual private networks), operating systems, applications, and databases, are considered in the patch management program.
I40: - | J40: Whether the services of third parties are used in the entity's patch management program, including responsibilities for patching of externally hosted applications or software used in a Software as a Service (“SaaS”) model.
I43: - | J43: Whether separate patch management processes are in place for different technology platforms (e.g., Windows vs. Unix platforms).
H45: - | I45: How appropriate personnel are periodically informed of the status of the patch management program, including the adoption and effectiveness of patches across the environment.
I47: - | J47: The mechanism and frequency of notification (e.g., quarterly risk committee meetings).
I48: - | J48: The level of detail provided (e.g., metrics related to patch adoption and effectiveness).
I49: - | J49: Whether appropriate personnel (e.g., CIO, CTO, CISO, operational risk, technology risk) are informed of the status of patch management program.
H51: - | I51: How management addresses vulnerabilities attributable to missed/unapplied patches.
I52: - | J52: Whether periodic scans are performed to identify potential vulnerabilities attributable to missed/unapplied security patches.
I54: - | J54: Whether an exemption or risk acceptance process is in place for patches that cannot be deployed due to system limitations and/or business constraints.
H56: - | I56: The period for which the control has been in operation and the frequency of its operation.
H57: - | I57: The appropriateness of the person(s) performing the control(s).
H59: [document the various aspects of the control considered]
H60: [document details, name and date of inquiry]
B62: c) | C62: Observation During the normal course of processing, observe the control operator performing the control. | H62: Not applicable. Observation not performed. | N62: TRUE
G63: OR
H64: Observed and documented in a related EGA addressing the understanding and evaluation of entity's ITGCs or in a related EGA addressing the understanding and evaluation of entity's internal control.
H67: [provide link]
G68: OR
H69: Observed the control operator performing the control.
H70: [document date and details of observation]
B72: d) | C72: Inspection Inspect a sample of evidence of the control performance during the relevant period to determine whether the control has been performed as designed and that exceptions are investigated and resolved on a timely basis. | H72: Not applicable. Inspection not performed. | N72: TRUE
G73: OR
H74: Inspected a sample of evidence of the control performance during the relevant period to determine whether the control has been performed as designed and that exceptions are investigated and resolved on a timely basis. Testing in tab 'ToC Template' or provided link.
G77: OR
H78: Performed one or more of the following (checked those that apply):
I79: Inspected evidence that the status of the entity's patch management program is periodically monitored and relevant stakeholders (e.g., technology leadership) are updated on the status of the patch management program (e.g., monthly technology risk committee meetings during which metrics related to the adoption and effectiveness of patches across the IT environment and/or identified high risk and critical vulnerabilities attributable to missed/unapplied patches are discussed).
I85: [document details of inspection]
I87: Inspected a sample of months (or other unit of frequency based on the design of management’s process and related control related to the vendor patch release schedule) during the relevant period to verify each of the following:
I90: - | J90: Existence of supporting evidence that patch releases have been applied in accordance with the entity's policies and/or procedures.
I92: - | J92: Existence of supporting evidence that critical patches communicated outside of the normal patch release schedule have been applied in accordance with the entity's policies/procedures and/or critical patches not applied have been appropriately approved.
I95: [document details of inspection]
I97: Inspected a sample of results from vulnerability scans run during the relevant period to verify evidence that vulnerabilities attributable to missed/unapplied patches identified are being addressed on a timely basis in accordance with the company’s policies and/or procedures.
I100: [document details of inspection]
B102: e) | C102: Reperformance | H102: Not applicable. Reperformance is typically not applicable to the control type chosen. | N102: TRUE
B104: f) | C104: Automated control | H104: Not applicable. The control is not automated. | N104: TRUE
C105: Confirm that evidence has been obtained for each of the following: | G105: OR
H106: Tested that ITGCs support continued reliable operation of the automated control by:
C107: i) | D107: ITGCs support continued reliable operation of the automated control; and | I107: Testing the ITGCs, or
I108: [provide link]
C109: ii) | D109: There are no changes in the automated control during the period. | I109: Other [specify]
G110: AND
H111: Tested that the automated control did not change during the period by:
I112: Inspecting/examining the documentation around all of the program changes that impacted the automated control, or
I114: [document details of inspection]
I115: Inspecting/examining the configuration setting in the application, or
I116: [document details of inspection]
I117: Inspecting/examining the system date stamp of last change, or
I118: [document details of inspection]
I119: Other [specify]
G120: AND
H121: No exceptions noted, evidence has been obtained for each item, or
H122: Exceptions noted for at least one item.
H123: [document details and impact on audit plan (e.g., additional testing on the operating effectiveness)]
B128: Guidance (click + to expand):
B130: AUDIT GUIDE
B131: US PwC Audit 3302 - Understand and evaluate the design of ITGCs
B132: US PwC Audit 1206 - Audit evidence
B133: US PwC Audit 5400 - Determine nature, timing and extent of controls testing to be performed
B135: GUIDANCE
B136: ● | C136: Inquiry alone will not provide sufficient evidence to support a conclusion about the effectiveness of a specific control. Consider the need to get further support by examining reports, manuals or other documents used in or generated by the performance of the control.
B138: ● | C138: The control being observed might not be performed in the same manner when the auditors are not present. In addition, observation is pertinent only at a point in time. Consider performing observation of multiple instances of the control, or combining observation with additional testing methods, such as detailed inquiry or inspection of documentation, to gain further evidence about the operation of the control over the period.
B141: ● | C141: When inspecting or reperforming the control at a point in time, consider how to obtain sufficient evidence that a control is operating effectively throughout the audit period (e.g., ITGCs, other evidence of no change, etc.).
B143: ● | C143: Observation, inspection and reperformance may not be possible in all system environments; in such instances, consider alternative testing procedures to address such aspects.
B144: ● | C144: When reperforming a control in a test environment, obtain sufficient evidence to be satisfied that the test instance substantially mirrors the current production environment at the time of testing.
B146: ● | C146: If transactions are not processed uniformly (i.e., if the control operates in a different manner for each type of transaction), testing regarding each transaction type may be appropriate.
B147: ● | C147: Evaluation of the operating effectiveness of an automated control is generally limited to seeing all important aspects of the control operate once (often referred to as a "test of one"). An imperative in the "test of one" concept is that we test all critical attributes or iterations of the control. For each iteration, define conditions that would indicate performance of the control as designed, and what constitutes an exception.
B150: ● | C150: The actions of the control may be determined by a technically complex set of system configurations. Consider whether the use of a specialist in accounting/auditing field is appropriate given the nature and complexity of the application and its processing environment.
B152: ● | C152: Consider whether the control operates at an appropriate level of precision (i.e., threshold used) to address the control objective.
B153: ● | C153: Consider whether the information used in the execution of the control is accurate and reliable. To the extent necessary, consider additional procedures to obtain evidence of the reliability of the data (i.e. completeness, accuracy and validity).
B155: ● | C155: When using sampling techniques for testing:
C156: - | D156: understand the population from which the items will be selected. Consider if the population provides an appropriate base for which to evaluate if the control operated and consider whether the population is complete,
C158: - | D158: consider if the population subject to testing is sufficiently homogeneous to permit it to be treated as one population and, therefore, permit the results of our testing to be appropriately projected to the entire population,
C160: - | D160: consider the frequency of the control and the number of instances of the control,
C161: - | D161: define conditions that would indicate performance of the control as designed, and what constitutes an exception (Note: the absence of documentation evidencing the operation of a control does not in and of itself create the presumption of ineffectiveness of the control. Rather, the auditor must be satisfied that the control actually operated through other corroborating evidence that is sufficiently persuasive).
B164: ● | C164: When exceptions are identified, make inquiries to understand their potential consequences and determine whether:
...

Sheet Master Procedures (53)
B1: Prior year control testing documentation rolled forward for reference purposes.
B2: Perform testing using inquiry, observation and inspection
B3: When more than one preparer was involved in the completion of this EGA, document the names of the team members involved and the procedures performed. | G3: [Document the initials or names of team members and procedures performed (e.g., Jane Doe performed step a) below)]
B6: Comp. operations - Data is appropriately backed up and recoverable (PCAOB engagements)
B7: Procedures | G7: Results | L7: Links
B8: a) | C8: Inquiry | H8: Not applicable. Additional Inquiry not performed. | N8: TRUE
C9: Inquire of personnel knowledgeable of the control (including any automated components) to test the various aspects of the control. | G9: OR
H10: Inquired and documented in a related EGA addressing the understanding and evaluation of entity's ITGCs or in a related EGA addressing the understanding and evaluation of entity's internal control.
C13: Note: Consider the entity's ability to backup and recover systems and/or data to report its quarterly (if applicable) and annual financials in a timely manner. | H13: [provide link]
G14: OR
H15: Inquired of personnel knowledgeable of the control considering the various aspects of the control (including any automated control components):
H17: - | I17: Policies and/or procedures related to the entities backup and recovery process(es).
H18: - | I18: Whether third parties are used to perform services related to backup and recovery (e.g., cloud providers).
H20: - | I20: How the control operator determines which types of data are included and the frequency of the backup cycle.
H22: - | I22: How changes to the backup configuration(s) and/or schedule(s) are managed.
H23: - | I23: How the control operator monitors backups for successful completion.
H24: - | I24: How the control operator resolves errors encountered during the backup process(es).
H25: - | I25: How the control operator ensures that backup media would be available in the event of an emergency (e.g., off-site rotation of media, replication of data to hot/cold site, cloud, etc.).
H27: - | I27: Whether data is stored on premise, off premise, direct-to-cloud, etc.
H28: - | I28: Has management established a recovery time objective (RTO) (i.e., amount of time allotted for the recovery of a business function or resource after an incident occurs) for financially significant applications and related infrastructure.
H31: - | I31: Has management established a recovery point objective (RPO) (i.e., amount of the data that can be lost before a material impact to financial reporting occurs) for financially significant applications and related infrastructure.
H34: - | I34: How the system has been configured to back up financially significant data on a scheduled (e.g., partial, incremental, full backups) or real-time basis.
H36: - | I36: How the control operator periodically tests backups for recoverability against the entity's defined RTO and RPO (e.g., scheduled testing, throughout the period when recovering from processing problems, etc.).
... H44: - | I44: The appropriateness of the person(s) performing the control(s).
H46: [document the various aspects of the control considered]
H47: [document details, name and date of inquiry]
B49: b) | C49: Observation During the normal course of processing, observe the control operator performing the control in accordance with agreed upon policies and/or procedures, including any considerations for automated components in the process. | H49: Not applicable. Observation not performed. | N49: TRUE
G50: OR
H51: Observed and documented in a related EGA addressing the understanding and evaluation of entity's ITGCs or in a related EGA addressing the understanding and evaluation of entity's internal control.
H54: [provide link]
G55: OR
H56: Observed the control operator performing the control, may include the following:
H57: - | I57: Initiating a backup, and
H58: - | I58: Monitoring backup for successful completion, and
H59: - | I59: Resolving errors encountered during backup, and
H60: - | I60: Recovering from a backup, and
H61: - | I61: Following up on exceptions noted during testing of backup and recoverability
H62: [document details of observation, name and date of observation]
B64: c) | C64: Inspection Inspect the following: | H64: Not applicable. Inspection not performed. | N64: TRUE
G65: OR
C66: i) | D66: A sample of recovery tests performed during the relevant period. | H66: Inspected a sample of recovery tests performed during the relevant period to verify that the test was successfully completed in a timely manner in accordance with the entity's established recovery time objective and recovery point objective and follow-ups were resolved (e.g., a signature or initials on the document, written explanations, checkmarks, or other indications of follow up, such as an email etc.). Testing in tab 'ToC Template' or provided link.
C68: ii) | D68: Backup schedule and configuration.
C69: iii) | D69: A sample of backups during the relevant period.
C70: iv) | D70: Evidence of recoverability during the relevant period.
G71: AND
H72: Inspected the backup schedule and/or real-time configuration (on-line or using a report) that shows what data is backed up, how backup is performed, and the frequency of the backup. Testing in tab 'ToC Template' or provided link.
G75: AND
H76: Inspected a sample of backups during the relevant period to verify each of the following. Testing in tab 'ToC Template' or provided link.
H78: - | I78: Financially significant data was successfully backed up based on an appropriate frequency (e.g., system generated log report, real-time reporting, or other indications of follow ups such as an email etc.), and
H81: - | I81: Follow ups were completed to resolve exceptions noted during the backup process, if applicable (e.g., incident ticket resolution, successful subsequent execution, or other indications of follow up such as an email etc.).
G84: AND
H85: Inspected evidence of recoverability during the relevant period (e.g. results of failover testing, results of data restoration, results of disaster recovery testing, etc.)
H87: [document details of inspection]
B89: d) | C89: Reperformance | H89: Not applicable. Reperformance is typically not applicable to the control type chosen. | N89: TRUE
B91: e) | C91: Automated control | H91: Not applicable. The control is not automated. | N91: TRUE
C92: Confirm that evidence has been obtained that there are no changes in the automated control during the period. | G92: OR
H93: Tested that the automated control did not change during the period by:
I94: Inspecting/examining the documentation around all of the program changes that impacted the automated control, or
I96: [document details of inspection]
I97: Inspecting/examining the configuration setting in the application, or
I98: [document details of inspection]
I99: Inspecting/examining the system date stamp of last change, or
I100: [document details of inspection]
I101: Other [specify]
G102: AND
H103: No exceptions noted, evidence has been obtained, or
H104: Exceptions noted.
H105: [document details and impact on audit plan (e.g., additional testing on the operating effectiveness)]
B110: Guidance (click + to expand):
B112: AUDIT GUIDE
B113: US PwC Audit 3302 - Understand and evaluate the design of ITGCs
B114: US PwC Audit 1206 - Audit evidence
B115: US PwC Audit 5400 - Determine nature, timing and extent of controls testing to be performed
B117: GUIDANCE
B118: ● | C118: Where the various elements of the control represent different populations, the tabs 'ToC Template' and 'Testing Table' are to be copied one at the time in order to utilize one instance of the tabs for each population.
B120: ● | C120: Activities in computer operations often present operational risk, not ICFR risk, depending on the client's specific circumstances. Elements of computer operations may be relevant to ICFR, particularly when they serve not only as ITGCs, but also as application controls that directly support relevant financial statement assertions. Examples could be as follows:
C122: - | D122: Job scheduling is an IT activity that could directly impact the completeness and accuracy of financial data if it were to break down.
C123: - | D123: Backup and recovery procedures may be important to the risk of financial misstatement if data recoveries are frequent, such as when systems are unstable.
B124: ● | C124: Inquiry alone will not provide sufficient evidence to support a conclusion about the effectiveness of a specific control. Consider the need to get further support by examining reports, manuals or other documents used in or generated by the performance of the control.
B126: ● | C126: The control being observed might not be performed in the same manner when the auditors are not present. In addition, observation is pertinent only at a point in time. Consider performing observation of multiple instances of the control, or combining observation with additional testing methods, such as detailed inquiry or inspection of documentation, to gain further evidence about the operation of the control over the period.
B129: ● | C129: When inspecting the control at a point in time, consider how to obtain sufficient evidence that a control is operating effectively throughout the audit period (e.g., ITGCs, other evidence of no change, etc.).
B131: ● | C131: Observation and inspection may not be possible in all system environments; in such instances, consider alternative testing procedures to address such aspects.
B132: ● | C132: If transactions are not processed uniformly (i.e., if the control operates in a different manner for each type of transaction), testing regarding each transaction type may be appropriate.
B133: ● | C133: Evaluation of the operating effectiveness of an automated control is generally limited to seeing all important aspects of the control operate once (often referred to as a "test of one"). An imperative in the "test of one" concept is that we test all critical attributes or iterations of the control. For each iteration, define conditions that would indicate performance of the control as designed, and what constitutes an exception.
B136: ● | C136: The actions of the control may be determined by a technically complex set of system configurations. Consider whether the use of a specialist in accounting/auditing field is appropriate given the nature and complexity of the application and its processing environment.
B138: ● | C138: Consider whether the control operates at an appropriate level of precision (i.e., threshold used) to address the control objective.
B139: ● | C139: Consider whether the information used in the execution of the control is accurate and reliable. To the extent necessary, consider additional procedures to obtain evidence of the reliability of the data (i.e. completeness, accuracy and validity).
B141: ● | C141: When using sampling techniques for testing:
C142: - | D142: understand the population from which the items will be selected. Consider if the population provides an appropriate base for which to evaluate if the control operated and consider whether the population is complete. If the system does not maintain an internal system audit record of user accounts that were added and/or modified during the period to draw upon as a population for selecting our sample; consider picking the sample from relevant human resource records to understand those individuals that have joined or changed roles within the organization during the period,
C146: - | D146: consider if the population subject to testing is sufficiently homogeneous to permit it to be treated as one population and, therefore, permit the results of our testing to be appropriately projected to the entire population,
C148: - | D148: consider the frequency of the control and the number of instances of the control,
C149: - | D149: define conditions that would indicate performance of the control as designed, and what constitutes an exception (Note: the absence of documentation evidencing the operation of a control does not in and of itself create the presumption of ineffectiveness of the control. Rather, the auditor must be satisfied that the control actually operated through other corroborating evidence that is sufficiently persuasive).
B152: ● | C152: When exceptions are identified, make inquiries to understand their potential consequences and determine whether:
C153: - | D153: the tests of controls that have been performed provide an appropriate basis for reliance on the controls,
C154: - | D154: additional tests of controls are necessary,
C155: - | D155: risks of misstatement need to be addressed using alternative procedures,
C156: - | D156: exceptions represent a significant deficiency (as well as material weakness under US GAAS) in internal control (that should be documented as a Significant matter).

Sheet Master Control Design
B1: Prior year control testing documentation rolled forward for reference purposes.
B2: Review 통제 - 설계 평가 Review control - design evaluation
B3: Note: 동 template은 감사팀의 review control 설계에 대한 평가를 문서화하는 업무흐름도(해당하는 경우) 및 "추적조사" template을 보완하기 위한 목적임. Note: This template is meant to complement a flowchart (if applicable) and “walkthrough” template for documenting our evaluation of the design of review controls.
B4: 통제 번호 Control number
B5: 통제/프로그램의 내용 Description of the control/program
B6: 평가대상 통제의 대상 부문 Component(s) of the entity covered by the control being evaluated
B7: 통제 대상이 되는 부문의 계정(또는, 재무제표 전반) Account(s) at the component(s) covered by the control, or pervasive | H7: 설계의 효과성 및 실행 여부에 대한 평가 Evaluation of design effectiveness and implementation | N7: 정보의 질 Quality of Information | R7: 설계 효과성에 대한 결론 Conclusion of design effectiveness
B8: 세부 통제 활동 # Detailed Control Activity # | C8: 해당 통제 활동과 관련있는 잠재적 왜곡표시의 가능한 원천('LSPM')은 무엇인가? (Aura 내 "Risk Strategy" view에서 복사하여 붙여넣기) Which LSPM(s) is relevant for this control activity (copy and paste from the "Risk Strategy" view within Aura)? | D8: 해당 통제 활동의 목적은 무엇인가? (즉, 통제 운영자가 동 통제 활동을 통해 달성하고자 하는 것이 무엇인가) What is the objective of the control activity (i.e., what is the control operator expected to accomplish for this control activity)? | E8: 질문 일자 및 질문 대상자를 문서화 (다른 곳에서 이미 문서화하지 않은 경우) Document date of inquiry, with whom discussed if not already documented. | F8: 통제 활동 운영자 Control activity operator | G8: 통제 운영자가 효과적으로 통제를 수행하기 위해 필요한 권한 및 능력을 갖추고 있는가? Does the control operator possess the necessary authority and competence to perform the control effectively? | H8: 통제 운영자가 통제 활동의 목적을 어떻게 달성하는가? How does the control operator accomplish the objective of this control activity? | N8: (해당사항이 있는 경우)이 통제 활동의 효과적인 운영에 중요하게 사용되는 정보(예, key report)에 대한 설명 Describe the information (e.g., key report) determined to be used in and important to the effective execution of this control activity, if any | O8: 이러한 정보의 원천 Describe the source of this information | P8: 이 통제 활동의 운영에 중요하게 사용되는 정보의 신뢰성(즉, 완전성 및 정확성)에 대한 확신을 얻기 위하여, 경영진이 의존하는 통제 또는 통제 활동의 내용 For information determined to be used in and important to the operation of this control activity, describe the control or control activities management is relying on to provide assurance regarding the reliability (i.e., it is complete and accurate) of such information. | Q8: Review control이 추정의 합리성에 대한 평가와 관련된 경우, 관련된 유의적 가정을 뒷받침하는 충분한 세부내역이 통제 운영자에게 제공되는지 설명. 그렇지 않다면, 어떻게 충분히 정확한 검토가 달성되는지 설명. If the review involves an assessment of the reasonableness of an estimate, describe whether the control operator is provided with sufficient details in support of underlying significant assumptions. If not, describe how a sufficiently precise review is achieved. | R8: 통제 활동이 명시된 목적을 달성할 수 있도록 효과적으로 설계되었는가? 그렇지 않다면, 근거, SAD에 대한 참조번호 및 감사 계획에 미치는 영향을 문서화. Describe whether the control activity is designed effectively to meet the stated objective. If "No", document rationale, reference to the SAD and impact to audit plan.
H9: 각 통제 활동 내에서 통제 운영자가 정확하게 무엇을 수행하는지 세부적으로 기재. Describe in detail what exactly the control operator does in performing each control activity. | I9: 정밀함의 수준? At what level of precision? | M9: 통제 운영자가 실제로 통제 활동을 수행하였음을 입증하는, 입수된 감사증거(관련 문서 포함)의 성격 및 형태 Describe the nature and form of evidence, including documentation, obtained that demonstrates the control operator actually performed the control activity
I10: 세분화 수준 (비고: 보다 세분화/분산된 수준에서 수행되는 통제 활동이 상위 수준에서 수행되는 활동보다 더 정확함) Review control의 대상이 되는 정보를 고려하고, 이러한 정보가 효과적인 review control이 이루어질 수 있도록(즉, 중요한 왜곡표시를 적시에 식별하고 수정할 수 있도록) 충분히 세부적인 수준으로 제공되는지 여부를 평가한다. Describe the level of aggregation(Note: A control activity that is performed at a more granular/disaggregated level is more precise than one performed at a higher level) Include consideration of the information subject to the review control and address whether such information is provided at a sufficiently detailed level to allow for an effective review (i.e, timely identification and correction of material misstatements). | J10: 통제 활동의 빈도(예, 매분기, 매주), 정기적으로 혹은 비반복적으로 운영되는지 여부, 통제 활동의 수행에 사용되는 정보의 일관성, 통제 활동을 수행하는 인원의 일관성 및 통제 활동이 수행되는 방법의 일관성. Describe the frequency of the control activity (e.g., quarterly, weekly), whether it operates routinely or on a non-recurring basis, the consistency of the information used in the operation of the control activity, the consistency of the individuals who perform the control activity, and the consistency of the method by which the control activity is executed. | K10: Investigation을 수행하는 기준 (Investigation을 수행하는 기준이 되는 양적 threshold를 일관성있게 적용하고 있는가? 그러한 threshold가 존재하지 않는 경우, investigation이 필요한 사항을 결정하기 위해 일관성있게 적용되는 기준을 설명.) Describe the criteria for investigation (Is there a quantitative threshold at which investigation would consistently be performed? If not, describe the criteria used to determine matters that would be investigated consistently.) | L10: 예상치의 예측가능성 (통제활동의 효과성이 얼마나 정확한 예측치를 도출할 수 있는지 여부에 의존하는 경우, 계정의 성격 및 이용가능한 정보를 근거로 그러한 예측치가 얼마나 예측가능한지 고려.) Describe the predictability of expectations (If the effectiveness of the control activity depends on being able to develop sufficiently precise expectations, consider how predictable they can be based on the nature of the account and information available.)
A11: 1
A12: 2

Sheet Control Activity-1 - v2016
B1: Prior year control testing documentation rolled forward for reference purposes.
B2: 운영 효과성에 대한 테스트 - 통제 활동 1 Operating Effectiveness Testing - Control Activity-1
B3: Note: 각 통제 활동에 대하여 별도의 테스트 탭을 생성하여야 함 Note: A separate testing tab should be created for each control activity
B4: 동 review control activity와 관련된 LSPM은 무엇인가? (개별 통제 활동의 목적 및 설계에 대한 세부적인 이해에 근거하여 이 review control에 대한 설계 평가에 대한 결론을 내릴 때, 통제 활동이 관련 LSPM(Aura v6의 Risk Strategy view 및 설계 평가에 문서화된 바와 같이)에 대응하는지 재확인하여야 함) What LSPMs are relevant for this review control activity? (In finalizing the assessment of the design of this review control (based on a detailed understanding of the objective and design of individual control activities), we should reconfirm the control activity is responsive to the LSPMs to which is it linked (in the Risk Strategy view of Aura v6 and as documented in the design evaluation))
B5: 통제 활동의 내용 [어떻게 통제 운영자가 통제 활동의 목적을 달성하는지(즉, 통제 운영자가 정확하게 무엇을, 얼마나 정밀한 수준으로 수행하는지)?] Control Activity Description [How does the control operator accomplish the objective of this control activity (i.e., what exactly does the control operator do and at what level of precision)?]
B7: 1) 테스트 모집단을 결정 1) Determine the population(s) for testing | I7: 2) 통제 활동의 빈도 및 계획한 감사증거 수준에 따라 테스트할 기간의 개수 결정 2) Determine the number of periods to test based on the frequency of the control activity and the desired level of evidence
B8: 샘플을 선정하고 결론을 도출할 모집단을 식별 Note: 샘플을 선정하고 결론을 도출할 모집단은 사람, 프로세스, 연관 시스템, 공동의 ELC, 공동의 관리/감독, 공동의 실패 위험 등의 요소들을 고려하였을 때 하나의 모집단으로 테스트할 수 있을 만큼 충분히 동질적이어야 함. 추가적인 지침은 US PwC Audit 5400(US PwC Audit (NP) 5400)을 참조. Identify the population from which to select the sample and about which to draw conclusions Note: the population from which to select a sample and draw conclusions should be sufficiently homogenous to test as one population based on consideration of factors such as the people, processes, and systems involved, commonality of ELCs, commonality of supervisory oversight, common risks of failure, etc. Refer to US PwC Audit 5400 (US PwC Audit (NP) 5400) for further guidance. | I8: 통제 활동의 빈도 (예, 연간, 분기별, 월별, 주별, 일별, 1일 수시) Frequency of control activity (e.g., annual, quarterly, monthly, weekly, daily, multiple times per day)
B9: 모집단 완전성을 판단하기 위하여 수행한 절차 Procedures performed to determine the population is complete | I9: 통제 활동의 빈도 및 계획한 감사증거 수준에 따른 테스트 대상 기간 수(추가적인 지침은 US PwC Audit 5400 (US PwC Audit (NP) 5400)을 참조) Number of periods to test based on the frequency of the control activity and the desired level of evidence (Refer to US PwC Audit 5400 (US PwC Audit (NP) 5400) for further guidance)
B11: 3) 각 기간에 대하여 테스트할 통제 활동의 instance 개수 결정 3) Determine the number of instances of the control activity to test for each period | I11: 4a) 경영진이 사용한 정보가 의도된 목적(그러한 절차의 결과를 문서화하는 것을 포함하여) 상 신뢰성이 있는지(즉, 완전하고 정확한지) 확인하기 위해, 이 통제 활동의 운영에 중요하게 사용되는 정보에 대한 통제를 테스트 4a) Test the control(s) over information used in and important to the operation of this control activity used by management to ensure such information is reliable (i.e., is complete and accurate) for its intended purpose, including documenting the results of those procedures
B12: 각 모집단의 각 기간에 수행되는 통제 활동의 instance 개수 Note: 모집단 내에서 각 기간에 통제 활동이 1회를 초과하여 일어나는 경우, 통제 활동이 설계대로 일관성있게 운영되었음을 입증하기 위하여 필요한 감사증거의 범위를 결정하기 위하여 각 기간에 대하여 테스트할 통제 활동의 instance 개수를 결정함. 이러한 결정은 통제 활동과 연관된 위험, 이용가능한 감사증거 및 과거 경험에 근거한 전문가적 판단의 문제이다. 추가적인 지침은 US PwC Audit 5400 (US PwC Audit (NP) 5400)을 참조. Number of instances the control activity operates during each period for each population Note: In situations where a control activity occurs more than once per period within a population, determine the number of instances of the control activity to test for each period to determine the extent of evidence needed to be persuaded the control activity is operating consistently as designed. This determination is a matter of professional judgment and is based on the risk associated with the control activity, available evidence, and prior experience. Refer to US PwC Audit 5400 (US PwC Audit (NP) 5400) for further guidance. | I12: 통제 활동의 운영에 중요하게 사용되는 정보에 대하여, 그러한 정보의 신뢰성(즉, 완전하고 정확함)과 관련한 확신을 제공하기 위하여 경영진이 의존한 통제의 내용 For information determined to be used in and important to the operation of this control activity, describe the control(s) management is relying on to provide assurance regarding the reliability (i.e., it is complete and accurate) of such information. | L12: =IF('Master Control Design'!P12 = "", "", 'Master Control Design'!P12)
I13: 경영진의 통제 절차에 대한 통제 테스트의 결과를 기재하거나, 테스트 절차가 수행된 조서에 대한 링크를 첨부 Note: 통합감사의 경우, 이 통제 활동 운영에 사용된 정보의 신뢰성에 대한 우리의 독립적인 테스트와는 별개로 이러한 정보에 대한 경영진의 통제를 테스트하여야 함. Include the results of the control(s) testing over management's control procedures or reference to where the testing procedures are performed. Note: Our own independent testing over the reliability of the information used in the operation of this control activity would not substitute for our requirement to test management's controls over such information in an integrated audit.
B15: 4b) 선택한 통제 활동의 instance를 테스트 4b) Test the control activity instances selected
B16: 해당되는 모든 항목에 체크: Check all that apply:
A18: FALSE | B18: 질문 절차 - (질문만으로는 운영 효과성과 관련된 결론을 뒷받침하기에 충분하지 않음에 유의) Inquiry Procedures - (Reminder - inquiry alone is not sufficient to support conclusion regarding operating effectiveness)
B20: 테스트 계획 Test Plan | I20: 통제 활동에 investigation 기준이나 thresholds가 포함되는 경우, 테스트 계획에 확인할 후속조치의 개수에 대한 고려 뿐만 아니라 경영진이 통제 활동의 설계와 일관성있게 후속조치 및 investigation 항목을 모두 적절히 식별하였는지 여부를 판단하기 위한 절차가 포함되었는지 확인. 'Review' 통제 활동의 설계, 성격 및 빈도에 따라서, "Management Follow-up Items" 및 "Detailed Testing Table" 탭이 필요할 수 있음. In situations where the control activity includes criteria and/or thresholds for items being investigated, ensure the plan includes consideration for the number of follow-ups to corroborate as well as procedures to determine whether management appropriately identified all items for follow up and investigation consistent with the design of the control activity. The tabs “management Follow-up Items” and “Detailed Testing Table” may be needed based upon the design, nature and frequency of the ‘review’ control activity.
B21: 이 통제 활동과 관련된 질문 절차 수행 계획을 세부적으로 기재 (질문만으로는 운영 효과성과 관련된 결론을 뒷받침하기에 충분하지 않음에 유의) Describe in detail the plan to perform inquiry procedures related to this control activity (Reminder - inquiry alone is not sufficient to support conclusion regarding operating effectiveness)
B24: [대상기간 기재]에 대한 테스트 결과 Testing Results for [insert period] | I24: [대상기간 기재]에 대한 테스트 결과 Testing Results for [insert period]
A25: 1 | B25: 문서화 항목 Documentation Prompt | D25: 감사 증거 Evidence | G25: 예외사항 Exception(s) | I25: 문서화 항목 Documentation Prompt | K25: 감사 증거 Evidence | N25: 예외사항 Exception(s)
B26: 누구에게 질문이 수행되었는가? With whom were inquiries performed? | I26: 누구에게 질문이 수행되었는가? With whom were inquiries performed?
B27: 질문 수행 일자 Date inquiries were performed | I27: 질문 수행 일자 Date inquiries were performed
B28: 통제 활동 운영과 관련하여 통제 운영자에게 질문한 내용(보충 질문의 경우, 검토대상 업무의 수행자 또는 기타의 인원) Question asked of the control operator related to the operation of the control activity (or preparer or others if these are corroborative inquiries) | I28: 통제 활동 운영과 관련하여 통제 운영자에게 질문한 내용(보충 질문의 경우, 검토대상 업무의 수행자 또는 기타의 인원) Question asked of the control operator related to the operation of the control activity (or preparer or others if these are corroborative inquiries)
B29: 답변 Response provided | I29: 답변 Response provided
A32: FALSE | B32: 관찰 절차 Observation Procedures
B34: 테스트 계획 Test Plan | I34: 통제 활동에 investigation 기준이나 thresholds가 포함되는 경우, 테스트 계획에 확인할 후속조치의 개수에 대한 고려 뿐만 아니라 경영진이 통제 활동의 설계와 일관성있게 후속조치 및 investigation 항목을 모두 적절히 식별하였는지 여부를 판단하기 위한 절차가 포함되었는지 확인. 'Review' 통제 활동의 설계, 성격 및 빈도에 따라서, "Management Follow-up Items" 및 "Detailed Testing Table" 탭이 필요할 수 있음. In situations where the control activity includes criteria and/or thresholds for items being investigated, ensure the plan includes consideration for the number of follow-ups to corroborate as well as procedures to determine whether management appropriately identified all items for follow up and investigation consistent with the design of the control activity. The tabs “management Follow-up Items” and “Detailed Testing Table” may be needed based upon the design, nature and frequency of the ‘review’ control activity.
B35: 관찰 절차 수행 계획 및 입수할 감사증거의 세부 내역을 기재(각 기간의 테스트 항목 개수, 관련된 선정 기준 포함) Describe in detail the plan to perform observation procedures and the expected evidence to be obtained, including the number of items to be tested for each period and the related basis of selection
B38: [대상기간 기재]에 대한 테스트 결과 Testing Results for [insert period] | I38: [대상기간 기재]에 대한 테스트 결과 Testing Results for [insert period]
B39: 문서화 항목 Documentation Prompt | D39: 감사 증거 Evidence | G39: 예외사항 Exception(s) | I39: 문서화 항목 Documentation Prompt | K39: 감사 증거 Evidence | N39: 예외사항 Exception(s)
B40: 회의 또는 토론 일자 Meeting or discussion date | I40: 회의 또는 토론 일자 Meeting or discussion date
B41: 참석자 및 역할 (감사팀 및 기타 인원) Attendees and roles (Engagement team and others) | I41: 참석자 및 역할 (감사팀 및 기타 인원) Attendees and roles (Engagement team and others)
B42: 통제 운영자가 요청한 특정 조치 또는 통제운영자가 제기한 질문, 회의 또는 토론에서 논의된 사항들 Specific actions requested or questions raised by the control operator(s) and items discussed in the meeting or discussion | I42: 통제 운영자가 요청한 특정 조치 또는 통제운영자가 제기한 질문, 회의 또는 토론에서 논의된 사항들 Specific actions requested or questions raised by the control operator(s) and items discussed in the meeting or discussion
B43: 논의의 완전성에 대한 감사 증거(토론에서 다루어진 특정 내용이 설계평가 상 통제 활동의 정밀함의 수준을 뒷받침하는지의 여부를 포함) Evidence of completeness of the discussions, including whether specific matters addressed supported the designed precision level of the control activity | I43: 논의의 완전성에 대한 감사 증거(토론에서 다루어진 특정 내용이 설계평가 상 통제 활동의 정밀함의 수준을 뒷받침하는지의 여부를 포함) Evidence of completeness of the discussions, including whether specific matters addressed supported the designed precision level of the control activity
B44: Review의 정확성 및 효과성에 대한 증거를 제공하는, 토론의 결과로 도출된 후속조치 항목이나 변동 사항을 설명 Describe any follow-up items or changes resulting from the discussion that provide evidence of the precision and effectiveness of the review | I44: Review의 정확성 및 효과성에 대한 증거를 제공하는, 토론의 결과로 도출된 후속조치 항목이나 변동 사항을 설명 Describe any follow-up items or changes resulting from the discussion that provide evidence of the precision and effectiveness of the review
B45: 통제 운영자가 그에 필요한 지식 및 경험을 보여주는가? 그렇다면, 어떻게? Did the control operator demonstrate the requisite knowledge and experience? If so, how? | I45: 통제 운영자가 그에 필요한 지식 및 경험을 보여주는가? 그렇다면, 어떻게? Did the control operator demonstrate the requisite knowledge and experience? If so, how?
B46: 상기의 고려사항들이 전반적인 review의 범위 및 정확성에 관한 우리의 결론을 뒷받침하는가? 그렇다면, 어떻게? Did the considerations above support our conclusion regarding the overall scope and precision of the review? If so, how? | I46: 상기의 고려사항들이 전반적인 review의 범위 및 정확성에 관한 우리의 결론을 뒷받침하는가? 그렇다면, 어떻게? Did the considerations above support our conclusion regarding the overall scope and precision of the review? If so, how?
A48: FALSE | B48: 문서검사 절차 Inspection Procedures
B50: 테스트 계획 Test Plan | I50: 통제 활동에 investigation 기준이나 thresholds가 포함되는 경우, 테스트 계획에 확인할 후속조치의 개수에 대한 고려 뿐만 아니라 경영진이 통제 활동의 설계와 일관성있게 후속조치 및 investigation 항목을 모두 적절히 식별하였는지 여부를 판단하기 위한 절차가 포함되었는지 확인. 'Review' 통제 활동의 설계, 성격 및 빈도에 따라서, "Management Follow-up Items" 및 "Detailed Testing Table" 탭이 필요할 수 있음. In situations where the control activity includes criteria and/or thresholds for items being investigated, ensure the plan includes consideration for the number of follow-ups to corroborate as well as procedures to determine whether management appropriately identified all items for follow up and investigation consistent with the design of the control activity. The tabs “management Follow-up Items” and “Detailed Testing Table” may be needed based upon the design, nature and frequency of the ‘review’ control activity.
B51: 문서검사 절차 수행 계획 및 입수할 감사증거의 세부 내역을 기재(각 기간의 테스트 항목 개수, 관련된 선정 기준 포함) Describe in detail the plan to perform inspection procedures and the expected evidence to be obtained, including the number of items to be tested for each period and the related basis of selection
B54: [대상기간 기재]에 대한 테스트 결과 Testing Results for [insert period] | I54: [대상기간 기재]에 대한 테스트 결과 Testing Results for [insert period]
B55: 문서화 항목 Documentation Prompt | D55: 감사 증거 Evidence | G55: 예외사항 Exception(s) | I55: 문서화 항목 Documentation Prompt | K55: 감사 증거 Evidence | N55: 예외사항 Exception(s)
B56: 검사한 통제 활동 문서에 대한 감사 증거(해당 항목에 체크): (비고: 아래의 내역이 모두 포함되어야 하거나, 나열된 항목이 모두 요구되는 것은 아님. 추가적인 지침은 PwC Audit 4165.12를 참조.) Evidence of control activity documentation inspected (check those that apply): (Note: the list below is not all-inclusive and not all items listed below are required. Refer to PwC Audit 4165.12 for further guidance.) | I56: 검사한 통제 활동 문서에 대한 감사 증거(해당 항목에 체크): (비고: 아래의 내역이 모두 포함되어야 하거나, 나열된 항목이 모두 요구되는 것은 아님. 추가적인 지침은 PwC Audit 4165.12를 참조.) Evidence of control activity documentation inspected (check those that apply): (Note: the list below is not all-inclusive and not all items listed below are required. Refer to PwC Audit 4165.12 for further guidance.)
A57: FALSE | B57: 서명(승인) Sign-offs | H57: FALSE | I57: 서명(승인) Sign-offs
A58: FALSE | B58: 회의 안건 Meeting agendas | H58: FALSE | I58: 회의 안건 Meeting agendas
A59: FALSE | B59: 고려사항, 근거 및 결론이 기재된 상세한 회의 자료 Detailed memorandum that outline the considerations, rationale and conclusions reached | H59: FALSE | I59: 고려사항, 근거 및 결론이 기재된 상세한 회의 자료 Detailed memorandum that outline the considerations, rationale and conclusions reached
A60: FALSE | B60: 기준/thresholds에 해당하는 사항에 대한 후속조치 이행 및 해결을 입증하는 통제 운영자와의(to/from) 이메일 기록 Email correspondence to/from the control operator demonstrating follow up and resolution of items that meet the criteria/thresholds | H60: FALSE | I60: 기준/thresholds에 해당하는 사항에 대한 후속조치 이행 및 해결을 입증하는 통제 운영자와의(to/from) 이메일 기록 Email correspondence to/from the control operator demonstrating follow up and resolution of items that meet the criteria/thresholds
A61: FALSE | B61: 실질적으로 검토가 실행되었음을 입증하는, 서식/문서 또는 분석에 기재된 표시 Notations on forms, documents or analysis that demonstrate the substance of the execution of the review | H61: FALSE | I61: 실질적으로 검토가 실행되었음을 입증하는, 서식/문서 또는 분석에 기재된 표시 Notations on forms, documents or analysis that demonstrate the substance of the execution of the review
A62: FALSE | B62: 상세한 회의록 (고려사항, 근거, 결론 및 결론이 어떻게 도출되었는지에 대한 내용 포함) Detailed meeting minutes, that include the considerations, rationale, conclusions, as well as how those were arrived | H62: FALSE | I62: 상세한 회의록 (고려사항, 근거, 결론 및 결론이 어떻게 도출되었는지에 대한 내용 포함) Detailed meeting minutes, that include the considerations, rationale, conclusions, as well as how those were arrived
A63: FALSE | B63: 기타. 설명: Other. Describe: | H63: FALSE | I63: 기타. 설명: Other. Describe:
A65: FALSE | B65: 재수행 절차 (비고: 재수행 테스트 절차를 통제 및 실증 테스트 모두를 목적으로 수행하려는 경우, 테스트 계획 및 입수할 감사 증거가 통제 활동의 수행 여부 및 실증 테스트 목적 달성 여부 둘 다에 구체적으로 관련성이 있는지 확인. 통제의 효과성에 대하여 직접적인 증거를 제공하지 않는 감사 증거는 dual purpose test에 대한 증거를 제공하지 않음.) Reperformance Procedures (Note: If reperformance testing procedures are intended to provide both controls and substantive testing evidence, confirm the test plan and evidence obtained is specific with respect to BOTH the control activities performed as well as the achievement of substantive testing objectives. Audit evidence that does not provide direct evidence regarding control effectivness does not provide dual purpose evidence.)
B67: 테스트 계획 Test Plan | I67: 통제 활동에 investigation 기준이나 thresholds가 포함되는 경우, 테스트 계획에 확인할 후속조치의 개수에 대한 고려 뿐만 아니라 경영진이 통제 활동의 설계와 일관성있게 후속조치 및 investigation 항목을 모두 적절히 식별하였는지 여부를 판단하기 위한 절차가 포함되었는지 확인. 'Review' 통제 활동의 설계, 성격 및 빈도에 따라서, "Management Follow-up Items" 및 "Detailed Testing Table" 탭이 필요할 수 있음. In situations where the control activity includes criteria and/or thresholds for items being investigated, ensure the plan includes consideration for the number of follow-ups to corroborate as well as procedures to determine whether management appropriately identified all items for follow up and investigation consistent with the design of the control activity. The tabs “management Follow-up Items” and “Detailed Testing Table” may be needed based upon the design, nature and frequency of the ‘review’ control activity.
B68: 통제활동에 대한 재수행 계획 및 입수할 감사증거의 세부 내역을 기재(각 기간의 테스트 항목 개수, 관련된 선정 기준 포함) Describe in detail the plan to reperform the control activity and the expected evidence to be obtained, including the number of items to be tested for each period and the related basis of selection
B71: [대상기간 기재]에 대한 테스트 결과 Testing Results for [insert period] | I71: [대상기간 기재]에 대한 테스트 결과 Testing Results for [insert period]
A72: 1 | B72: 문서화 항목 Documentation Prompt | C72: 감사 증거 Evidence | D72: 문서화 항목 Documentation Prompt | E72: 감사 증거 Evidence | F72: 예외사항 Exception(s) | I72: 문서화 항목 Documentation Prompt | J72: 감사 증거 Evidence | K72: 문서화 항목 Documentation Prompt | L72: 감사 증거 Evidence | M72: 예외사항 Exception(s)
B73: 통제 운영자의 활동 1 Control Operator(s) Action 1 | D73: 감사팀의 활동 Engagement Team Action | I73: 통제 운영자의 조치 1 Control Operator(s) Action 1 | K73: 감사팀의 조치 Engagement Team Action
B74: 통제 운영자가 정확하게 어떤 일을 수행하였고, 통제 운영자가 명시된 절차를 실제로 수행하였는지를 확인하기 위하여 감사팀이 입수한 증거는 무엇인가? What exactly did the control operator(s) do and what evidence was obtained by the engagement team to ascertain the control operator(s) actually performed the procedures described? Note: 입수한 증거는 질문(보충 질문 포함), 관찰, 조사, 재수행이나 이들의 결합을 통해 수집됨. Note: the evidence obtained is gathered through inquiries (including corroborative inquiries), observation, inspection, reperformance or a combination thereof. (감사팀은 통제 운영자가 정확하게 무엇을 실시하였는지에 대하여 "Review Control Design" 탭 내 I열의 일관성을 검토하여야 함. 감사팀은, 통제 운영자가 기재된 절차를 실제로 수행하였음을 확인하기 위하여, "Review Control Design" 탭 내 O 열 및 상기의 질문, 관찰 및 조사에서 문서화한 감사 증거와의 일관성을 검토하여야 함.) (Engagement team should verify consistency with row I of the "Review Control Design" tab regarding what exactly the control operator(s) did. Engagement teams should verify consistency with row O of the "Review Control Design" tab and/or the evidence gathered as documented above in Inquiry, Observation and/or Inpsection regarding the evidence obtained to ascertain the control operator(s) actually performed the procedures described) | D74: 통제 운영자의 활동을 재수행하기 위하여 감사팀이 무엇을 수행하였는지 세부적으로 기재. What exactly did the engagement team do to reperform the control operator(s)'s action? (Reminder : 감사팀의 절차는 통제 운영자가 수행한 활동과 일관되어야 함에 유의. 감사팀은 통제가 수행되었는지 여부를 테스트하며, 거래나 잔액에 대한 실증테스트에서 통제 효과성을 추론하지 않음.) (Reminder: engagement team procedures should be consistent with the actions performed by the control operator(s)) - it is the performance of the control that we are testing and NOT a substantive test of a transaction or balance from which we can infer control effectiveness | I74: 통제 운영자가 정확하게 어떤 일을 수행하였고, 통제 운영자가 명시된 절차를 실제로 수행하였는지를 확인하기 위하여 감사팀이 입수한 증거는 무엇인가? What exactly did the control operator(s) do and what evidence was obtained by the engagement team to ascertain the control operator(s) actually performed the procedures described? Note: 입수한 증거는 질문(보충 질문 포함), 관찰, 조사, 재수행이나 이들의 결합을 통해 수집됨. Note: the evidence obtained is gathered through inquiries (including corroborative inquiries), observation, inspection, reperformance or a combination thereof. (감사팀은 통제 운영자가 정확하게 무엇을 실시하였는지에 대하여 "Review Control Design" 탭 내 I열의 일관성을 검토하여야 함. 감사팀은, 통제 운영자가 기재된 절차를 실제로 수행하였음을 확인하기 위하여, "Review Control Design" 탭 내 O 열 및 상기의 질문, 관찰 및 조사에서 문서화한 감사 증거와의 일관성을 검토하여야 함.) (Engagement team should verify consistency with row I of the "Review Control Design" tab regarding what exactly the control operator(s) did. Engagement teams should verify consistency with row O of the "Review Control Design" tab and/or the evidence gathered as documented above in Inquiry, Observation and/or Inpsection regarding the evidence obtained to ascertain the control operator(s) actually performed the procedures described) | K74: 통제 운영자의 활동을 재수행하기 위하여 감사팀이 무엇을 수행하였는지 세부적으로 기재. What exactly did the engagement team do to reperform the control operator(s)'s action? (Reminder : 감사팀의 절차는 통제 운영자가 수행한 활동과 일관되어야 함에 유의. 감사팀은 통제가 수행되었는지 여부를 테스트하며, 거래나 잔액에 대한 실증테스트에서 통제 효과성을 추론하지 않음.) (Reminder: engagement team procedures should be consistent with the actions performed by the control operator(s)) - it is the performance of the control that we are testing and NOT a substantive test of a transaction or balance from which we can infer control effectiveness
B77: 5) 통제 활동이 효과적으로 운영되었음을 반영하는 기타의 감사 증거가 있다면, 이를 어떻게 고려하였는지 문서화 (예를 들어, 분기 검토 중 잠재적인 왜곡표시나 예외사항이 통제 활동에 의해 적절히 발견되고 적시에 수정되었다는 증거가 존재하는지?) 5) Document consideration of other evidence, if any, that reflects positively on the operating effectiveness of the control activity (For example, during a quarterly review, is there evidence that potential misstatements or exceptions were appropriately detected by the control activity and timely corrected?)
B80: 6) 통제 활동이 효과적으로 운영되지 않음을 반영되는 기타의 감사 증거가 있다면, 이를 어떻게 고려하였는지 문서화 (예를 들어, 통제 활동에 의하여 적발되고 해결되어야 하는 왜곡표시나 예외사항(기간 외 조정 포함)이 존재하는지?) 6) Document consideration of evidence, if any, that reflects negatively on the operating effectiveness of the control activity (For example, have there been misstatements or other exceptions, including out of period adjustments, that should have been detected and resolved by the control activity but were not?)

Sheet Control Activity-2 - v2016
B1: Prior year control testing documentation rolled forward for reference purposes.
B2: 운영효과성에 대한 테스트 - 통제활동 2 Operating Effectiveness Testing - Control Activity-2
B3: Note: 각 통제 활동에 대하여 별도의 테스트 탭을 생성하여야 함 Note: A separate testing tab should be created for each control activity
B4: 동 review control activity와 관련된 LSPM은 무엇인가? (개별 통제 활동의 목적 및 설계에 대한 세부적인 이해에 근거하여 이 review control에 대한 설계 평가에 대한 결론을 내릴 때, 통제 활동이 관련 LSPM(Aura v6의 Risk Strategy view 및 설계 평가에 문서화된 바와 같이)에 대응하는지 재확인하여야 함) What LSPMs are relevant for this review control activity? (In finalizing the assessment of the design of this review control (based on a detailed understanding of the objective and design of individual control activities), we should reconfirm the control activity is responsive to the LSPMs to which is it linked (in the Risk Strategy view of Aura v6 and as documented in the design evaluation))
B5: 통제 활동의 내용 [어떻게 통제 운영자가 통제 활동의 목적을 달성하는지(즉, 통제 운영자가 정확하게 무엇을, 얼마나 정밀한 수준으로 수행하는지)?] Control Activity Description [How does the control operator accomplish the objective of this control activity (i.e., what exactly does the control operator do and at what level of precision)?]
B7: 1) 테스트 모집단을 결정 1) Determine the population(s) for testing | I7: 2) 통제 활동의 빈도 및 계획한 감사증거 수준에 따라 테스트할 기간의 개수 결정 2) Determine the number of periods to test based on the frequency of the control activity and the desired level of evidence
B8: 샘플을 선정하고 결론을 도출할 모집단을 식별 Note: 샘플을 선정하고 결론을 도출할 모집단은 사람, 프로세스, 연관 시스템, 공동의 ELC, 공동의 관리/감독, 공동의 실패 위험 등의 요소들을 고려하였을 때 하나의 모집단으로 테스트할 수 있을 만큼 충분히 동질적이어야 함. 추가적인 지침은 US PwC Audit 5400(US PwC Audit (NP) 5400)을 참조. Identify the population from which to select the sample and about which to draw conclusions Note: the population from which to select a sample and draw conclusions should be sufficiently homogenous to test as one population based on consideration of factors such as the people, processes, and systems involved, commonality of ELCs, commonality of supervisory oversight, common risks of failure, etc. Refer to US PwC Audit 5400 (US PwC Audit (NP) 5400) for further guidance. | I8: 통제 활동의 빈도 (예, 연간, 분기별, 월별, 주별, 일별, 1일 수시) Frequency of control activity (e.g., annual, quarterly, monthly, weekly, daily, multiple times per day)
B9: 모집단 완전성을 판단하기 위하여 수행한 절차 Procedures performed to determine the population is complete | I9: 통제 활동의 빈도 및 계획한 감사증거 수준에 따른 테스트 대상 기간 수(추가적인 지침은 US PwC Audit 5400 (US PwC Audit (NP) 5400)을 참조) Number of periods to test based on the frequency of the control activity and the desired level of evidence (Refer to US PwC Audit 5400 (US PwC Audit (NP) 5400) for further guidance)
B11: 3) 각 기간에 대하여 테스트할 통제 활동의 instance 개수 결정 3) Determine the number of instances of the control activity to test for each period | I11: 4a) 경영진이 사용한 정보가 의도된 목적(그러한 절차의 결과를 문서화하는 것을 포함하여) 상 신뢰성이 있는지(즉, 완전하고 정확한지) 확인하기 위해, 이 통제 활동의 운영에 중요하게 사용되는 정보에 대한 통제를 테스트 4a) Test the control(s) over information used in and important to the operation of this control activity used by management to ensure such information is reliable (i.e., is complete and accurate) for its intended purpose, including documenting the results of those procedures
B12: 각 모집단의 각 기간에 수행되는 통제 활동의 instance 개수 Note: 모집단 내에서 각 기간에 통제 활동이 1회를 초과하여 일어나는 경우, 통제 활동이 설계대로 일관성있게 운영되었음을 입증하기 위하여 필요한 감사증거의 범위를 결정하기 위하여 각 기간에 대하여 테스트할 통제 활동의 instance 개수를 결정함. 이러한 결정은 통제 활동과 연관된 위험, 이용가능한 감사증거 및 과거 경험에 근거한 전문가적 판단의 문제이다. 추가적인 지침은 US PwC Audit 5400 (US PwC Audit (NP) 5400)을 참조. Number of instances the control activity operates during each period for each population Note: In situations where a control activity occurs more than once per period within a population, determine the number of instances of the control activity to test for each period to determine the extent of evidence needed to be persuaded the control activity is operating consistently as designed. This determination is a matter of professional judgment and is based on the risk associated with the control activity, available evidence, and prior experience. Refer to US PwC Audit 5400 (US PwC Audit (NP) 5400) for further guidance. | I12: 통제 활동의 운영에 중요하게 사용되는 정보에 대하여, 그러한 정보의 신뢰성(즉, 완전하고 정확함)과 관련한 확신을 제공하기 위하여 경영진이 의존한 통제의 내용 For information determined to be used in and important to the operation of this control activity, describe the control(s) management is relying on to provide assurance regarding the reliability (i.e., it is complete and accurate) of such information. | L12: =IF('Master Control Design'!P12 = "", "", 'Master Control Design'!P12)
I13: 경영진의 통제 절차에 대한 통제 테스트의 결과를 기재하거나, 테스트 절차가 수행된 조서에 대한 링크를 첨부 Note: 통합감사의 경우, 이 통제 활동 운영에 사용된 정보의 신뢰성에 대한 우리의 독립적인 테스트와는 별개로 이러한 정보에 대한 경영진의 통제를 테스트하여야 함. Include the results of the control(s) testing over management's control procedures or reference to where the testing procedures are performed. Note: Our own independent testing over the reliability of the information used in the operation of this control activity would not substitute for our requirement to test management's controls over such information in an integrated audit.
B15: 4b) 선택한 통제 활동의 instance를 테스트 4b) Test the control activity instances selected
B16: 해당되는 모든 항목에 체크: Check all that apply:
A18: FALSE | B18: 질문 절차 - (질문만으로는 운영 효과성과 관련된 결론을 뒷받침하기에 충분하지 않음에 유의) Inquiry Procedures - (Reminder - inquiry alone is not sufficient to support conclusion regarding operating effectiveness)
B20: 테스트 계획 Test Plan | I20: 통제 활동이 조사될 항목에 대한 기준/threshold을 포함하고 있는 경우, 동 계획이 확증을 위한 후속조치의 건수뿐만 아니라 경영진이 통제 활동 설계와 일치하는 후속조치 및 조사를 위한 모든 항목을 적절하게 식별했는지의 여부를 결정하는 절차에 대한 고려를 포함하여야 한다. 'Review' 통제 활동의 설계, 성격 및 빈도에 따라 "Management Follow-up Items" 및 "Detailed Testing Table" 탭이 필요할 수 있다. In situations where the control activity includes criteria and/or thresholds for items being investigated, ensure the plan includes consideration for the number of follow-ups to corroborate as well as procedures to determine whether management appropriately identified all items for follow up and investigation consistent with the design of the control activity. The tabs “management Follow-up Items” and “Detailed Testing Table” may be needed based upon the design, nature and frequency of the ‘review’ control activity.
B21: 이 통제 활동과 관련된 질문 절차 수행 계획을 세부적으로 기재 (질문만으로는 운영 효과성과 관련된 결론을 뒷받침하기에 충분하지 않음에 유의) Describe in detail the plan to perform inquiry procedures related to this control activity (Reminder - inquiry alone is not sufficient to support conclusion regarding operating effectiveness)
B24: [대상기간 기재]에 대한 테스트 결과 Testing Results for [insert period] | I24: [대상기간 기재]에 대한 테스트 결과 Testing Results for [insert period]
A25: 1 | B25: 문서화 항목 Documentation Prompt | D25: 감사 증거 Evidence | G25: 예외사항 Exception(s) | I25: 문서화 항목 Documentation Prompt | K25: 감사 증거 Evidence | N25: 예외사항 Exception(s)
B26: 누구에게 질문이 수행되었는가? With whom were inquiries performed? | I26: 누구에게 질문이 수행되었는가? With whom were inquiries performed?
B27: 질문 수행 일자 Date inquiries were performed | I27: 질문 수행 일자 Date inquiries were performed
B28: 통제 활동 운영과 관련하여 통제 운영자에게 질문한 내용(보충 질문의 경우, 검토대상 업무의 수행자 또는 기타의 인원) Question asked of the control operator related to the operation of the control activity (or preparer or others if these are corroborative inquiries) | I28: 통제 활동 운영과 관련하여 통제 운영자에게 질문한 내용(보충 질문의 경우, 검토대상 업무의 수행자 또는 기타의 인원) Question asked of the control operator related to the operation of the control activity (or preparer or others if these are corroborative inquiries)
B29: 답변 Response provided | I29: 답변 Response provided
A32: FALSE | B32: 관찰 절차 Observation Procedures
B34: 테스트 계획 Test Plan | I34: 통제 활동에 investigation 기준이나 thresholds가 포함되는 경우, 테스트 계획에 확인할 후속조치의 개수에 대한 고려 뿐만 아니라 경영진이 통제 활동의 설계와 일관성있게 후속조치 및 investigation 항목을 모두 적절히 식별하였는지 여부를 판단하기 위한 절차가 포함되었는지 확인. 'Review' 통제 활동의 설계, 성격 및 빈도에 따라서, "Management Follow-up Items" 및 "Detailed Testing Table" 탭이 필요할 수 있음. In situations where the control activity includes criteria and/or thresholds for items being investigated, ensure the plan includes consideration for the number of follow-ups to corroborate as well as procedures to determine whether management appropriately identified all items for follow up and investigation consistent with the design of the control activity. The tabs “management Follow-up Items” and “Detailed Testing Table” may be needed based upon the design, nature and frequency of the ‘review’ control activity.
B35: 관찰 절차 수행 계획 및 입수할 감사증거의 세부 내역을 기재(각 기간의 테스트 항목 개수, 관련된 선정 기준 포함) Describe in detail the plan to perform observation procedures and the expected evidence to be obtained, including the number of items to be tested for each period and the related basis of selection
B38: [대상기간 기재]에 대한 테스트 결과 Testing Results for [insert period] | I38: [대상기간 기재]에 대한 테스트 결과 Testing Results for [insert period]
B39: 문서화 항목 Documentation Prompt | D39: 감사 증거 Evidence | G39: 예외사항 Exception(s) | I39: 문서화 항목 Documentation Prompt | K39: 감사 증거 Evidence | N39: 예외사항 Exception(s)
B40: 회의 또는 토론 일자 Meeting or discussion date | I40: 회의 또는 토론 일자 Meeting or discussion date
B41: 참석자 및 역할 (감사팀 및 기타 인원) Attendees and roles (Engagement team and others) | I41: 참석자 및 역할 (감사팀 및 기타 인원) Attendees and roles (Engagement team and others)
B42: 통제 운영자가 요구한 특정 행동이나 제기한 질문 및 회의나 토론에서 다루어진 항목 Specific actions requested or questions raised by the control operator(s) and items discussed in the meeting or discussion | I42: 통제 운영자가 요구한 특정 행동이나 제기한 질문 및 회의나 토론에서 다루어진 항목 Specific actions requested or questions raised by the control operator(s) and items discussed in the meeting or discussion
B43: 토론에서 다루어진 특정 사항이 통제 활동의 계획된 정확도 수준을 뒷받침하는지의 여부 등과 같이 토론의 완전성에 대한 증거 Evidence of completeness of the discussions, including whether specific matters addressed supported the designed precision level of the control activity | I43: 토론에서 다루어진 특정 사항이 통제 활동의 계획된 정확도 수준을 뒷받침하는지의 여부 등과 같이 토론의 완전성에 대한 증거 Evidence of completeness of the discussions, including whether specific matters addressed supported the designed precision level of the control activity
B44: 검토의 정확성 및 효과성에 대한 증거를 제시한 토론에서 나온 후속조치 항목이나 변동사항을 설명한다 Describe any follow-up items or changes resulting from the discussion that provide evidence of the precision and effectiveness of the review | I44: 검토의 정확성 및 효과성에 대한 증거를 제시한 토론에서 나온 후속조치 항목이나 변동사항을 설명한다 Describe any follow-up items or changes resulting from the discussion that provide evidence of the precision and effectiveness of the review
B45: 통제 운영자가 필수 지식 및 경험을 발휘하였는가? 그렇다면, 어떻게 발휘하였는가? Did the control operator demonstrate the requisite knowledge and experience? If so, how? | I45: 통제 운영자가 필수 지식 및 경험을 발휘하였는가? 그렇다면, 어떻게 발휘하였는가? Did the control operator demonstrate the requisite knowledge and experience? If so, how?
B46: 상기의 고려사항들이 검토의 전반적인 범위 및 정확성에 관한 우리의 결론을 뒷받침해주는가? 그렇다면, 어떻게 뒷받침해주는가? Did the considerations above support our conclusion regarding the overall scope and precision of the review? If so, how? | I46: 상기의 고려사항들이 검토의 전반적인 범위 및 정확성에 관한 우리의 결론을 뒷받침해주는가? 그렇다면, 어떻게 뒷받침해주는가? Did the considerations above support our conclusion regarding the overall scope and precision of the review? If so, how?
A48: FALSE | B48: 문서검사 절차 Inspection Procedures
B50: 테스트 계획 Test Plan | I50: 통제 활동에 investigation 기준이나 thresholds가 포함되는 경우, 테스트 계획에 확인할 후속조치의 개수에 대한 고려 뿐만 아니라 경영진이 통제 활동의 설계와 일관성있게 후속조치 및 investigation 항목을 모두 적절히 식별하였는지 여부를 판단하기 위한 절차가 포함되었는지 확인. 'Review' 통제 활동의 설계, 성격 및 빈도에 따라서, "Management Follow-up Items" 및 "Detailed Testing Table" 탭이 필요할 수 있음. In situations where the control activity includes criteria and/or thresholds for items being investigated, ensure the plan includes consideration for the number of follow-ups to corroborate as well as procedures to determine whether management appropriately identified all items for follow up and investigation consistent with the design of the control activity. The tabs “management Follow-up Items” and “Detailed Testing Table” may be needed based upon the design, nature and frequency of the ‘review’ control activity.
B51: 문서검사 절차 수행 계획 및 입수할 감사증거의 세부 내역을 기재(각 기간의 테스트 항목 개수, 관련된 선정 기준 포함) Describe in detail the plan to perform inspection procedures and the expected evidence to be obtained, including the number of items to be tested for each period and the related basis of selection
B54: [대상기간 기재]에 대한 테스트 결과 Testing Results for [insert period] | I54: [대상기간 기재]에 대한 테스트 결과 Testing Results for [insert period]
B55: 문서화 항목 Documentation Prompt | D55: 감사 증거 Evidence | G55: 예외사항 Exception(s) | I55: 문서화 항목 Documentation Prompt | K55: 감사 증거 Evidence | N55: 예외사항 Exception(s)
B56: 검사한 통제 활동 문서에 대한 감사 증거(해당 항목에 체크): (비고: 아래의 내역이 모두 포함되어야 하거나, 나열된 항목이 모두 요구되는 것은 아님. 추가적인 지침은 PwC Audit 4165.12를 참조.) Evidence of control activity documentation inspected (check those that apply): (Note: the list below is not all-inclusive and not all items listed below are required. Refer to PwC Audit 4165.12 for further guidance.) | I56: 검사한 통제 활동 문서에 대한 감사 증거(해당 항목에 체크): (비고: 아래의 내역이 모두 포함되어야 하거나, 나열된 항목이 모두 요구되는 것은 아님. 추가적인 지침은 PwC Audit 4165.12를 참조.) Evidence of control activity documentation inspected (check those that apply): (Note: the list below is not all-inclusive and not all items listed below are required. Refer to PwC Audit 4165.12 for further guidance.)
A57: FALSE | B57: 서명(승인) Sign-offs | H57: FALSE | I57: 서명(승인) Sign-offs
A58: FALSE | B58: 회의 안건 Meeting agendas | H58: FALSE | I58: 회의 안건 Meeting agendas
A59: FALSE | B59: 고려사항, 근거 및 결론이 기재된 상세한 회의 자료 Detailed memorandum that outline the considerations, rationale and conclusions reached | H59: FALSE | I59: 고려사항, 근거 및 결론이 기재된 상세한 회의 자료 Detailed memorandum that outline the considerations, rationale and conclusions reached
A60: FALSE | B60: 기준/thresholds에 해당하는 사항에 대한 후속조치 이행 및 해결을 입증하는 통제 운영자와의(to/from) 이메일 기록 서신 Email correspondence to/from the control operator demonstrating follow up and resolution of items that meet the criteria/thresholds | H60: FALSE | I60: 기준/thresholds에 해당하는 사항에 대한 후속조치 이행 및 해결을 입증하는 통제 운영자와의(to/from) 이메일 기록 서신 Email correspondence to/from the control operator demonstrating follow up and resolution of items that meet the criteria/thresholds
A61: FALSE | B61: 실질적으로 검토가 실행되었음을 입증하는, 서식/문서 또는 분석에 기재된 표시 Notations on forms, documents or analysis that demonstrate the substance of the execution of the review | H61: FALSE | I61: 실질적으로 검토가 실행되었음을 입증하는, 서식/문서 또는 분석에 기재된 표시 Notations on forms, documents or analysis that demonstrate the substance of the execution of the review
A62: FALSE | B62: 상세한 회의록 (고려사항, 근거, 결론 및 결론이 어떻게 도출되었는지에 대한 내용 포함) Detailed meeting minutes, that include the considerations, rationale, conclusions, as well as how those were arrived | H62: FALSE | I62: 상세한 회의록 (고려사항, 근거, 결론 및 결론이 어떻게 도출되었는지에 대한 내용 포함) Detailed meeting minutes, that include the considerations, rationale, conclusions, as well as how those were arrived
A63: FALSE | B63: 기타. 설명: Other. Describe: | H63: FALSE | I63: 기타. 설명: Other. Describe:
A65: FALSE | B65: 재수행 절차 (비고: 재수행 테스트 절차를 통제 및 실증 테스트 모두를 목적으로 수행하려는 경우, 테스트 계획 및 입수할 감사 증거가 통제 활동의 수행 여부 및 실증 테스트 목적 달성 여부 둘 다에 구체적으로 관련성이 있는지 확인. 통제의 효과성에 대하여 직접적인 증거를 제공하지 않는 감사 증거는 dual purpose test에 대한 증거를 제공하지 않음.) Reperformance Procedures (Note: If reperformance testing procedures are intended to provide both controls and substantive testing evidence, confirm the test plan and evidence obtained is specific with respect to BOTH the control activities performed as well as the achievement of substantive testing objectives. Audit evidence that does not provide direct evidence regarding control effectivness does not provide dual purpose evidence.)
B67: 테스트 계획 Test Plan | I67: 통제 활동이 조사될 항목에 대한 기준/threshold을 포함하고 있는 경우, 동 계획이 확증을 위한 후속조치의 건수뿐만 아니라 경영진이 통제 활동 설계와 일치하는 후속조치 및 조사를 위한 모든 항목을 적절하게 식별했는지의 여부를 결정하는 절차에 대한 고려를 포함하여야 한다. 'Review' 통제 활동의 설계, 성격 및 빈도에 따라 "Management Follow-up Items" 및 "Detailed Testing Table" 탭이 필요할 수 있다. In situations where the control activity includes criteria and/or thresholds for items being investigated, ensure the plan includes consideration for the number of follow-ups to corroborate as well as procedures to determine whether management appropriately identified all items for follow up and investigation consistent with the design of the control activity. The tabs “management Follow-up Items” and “Detailed Testing Table” may be needed based upon the design, nature and frequency of the ‘review’ control activity.
B68: 통제활동에 대한 재수행 계획 및 입수할 감사증거의 세부 내역을 기재(각 기간의 테스트 항목 개수, 관련된 선정 기준 포함) Describe in detail the plan to reperform the control activity and the expected evidence to be obtained, including the number of items to be tested for each period and the related basis of selection
B71: [대상기간 기재]에 대한 테스트 결과 Testing Results for [insert period] | I71: [대상기간 기재]에 대한 테스트 결과 Testing Results for [insert period]
A72: 1 | B72: 문서화 항목 Documentation Prompt | C72: 감사 증거 Evidence | D72: 문서화 항목 Documentation Prompt | E72: 감사 증거 Evidence | F72: 예외사항 Exception(s) | I72: 문서화 항목 Documentation Prompt | J72: 감사 증거 Evidence | K72: 문서화 항목 Documentation Prompt | L72: 감사 증거 Evidence | M72: 예외사항 Exception(s)
B73: 통제 운영자의 활동 1 Control Operator(s) Action 1 | D73: 감사팀의 활동 Engagement Team Action | I73: 통제 운영자의 활동 1 Control Operator(s) Action 1 | K73: 감사팀의 활동 Engagement Team Action
B74: 통제 운영자가 정확하게 어떤 일을 수행하였고, 통제 운영자가 명시된 절차를 실제로 수행하였는지를 확인하기 위하여 감사팀이 입수한 증거는 무엇인가? What exactly did the control operator(s) do and what evidence was obtained by the engagement team to ascertain the control operator(s) actually performed the procedures described? Note: 입수한 증거는 질문(보충 질문 포함), 관찰, 조사, 재수행이나 이들의 결합을 통해 수집됨. Note: the evidence obtained is gathered through inquiries (including corroborative inquiries), observation, inspection, reperformance or a combination thereof. (감사팀은 통제 운영자가 정확하게 무엇을 실시하였는지에 대하여 "Review Control Design" 탭 내 I열의 일관성을 검토하여야 함. 감사팀은, 통제 운영자가 기재된 절차를 실제로 수행하였음을 확인하기 위하여, "Review Control Design" 탭 내 O 열 및 상기의 질문, 관찰 및 조사에서 문서화한 감사 증거와의 일관성을 검토하여야 함.) (Engagement team should verify consistency with row I of the "Review Control Design" tab regarding what exactly the control operator(s) did. Engagement teams should verify consistency with row O of the "Review Control Design" tab and/or the evidence gathered as documented above in Inquiry, Observation and/or Inpsection regarding the evidence obtained to ascertain the control operator(s) actually performed the procedures described) | D74: 통제 운영자의 활동을 재수행하기 위하여 감사팀이 무엇을 수행하였는지 세부적으로 기재. What exactly did the engagement team do to reperform the control operator(s)'s action? (Reminder : 감사팀의 절차는 통제 운영자가 수행한 활동과 일관되어야 함에 유의. 감사팀은 통제가 수행되었는지 여부를 테스트하며, 거래나 잔액에 대한 실증테스트에서 통제 효과성을 추론하지 않음.) (Reminder: engagement team procedures should be consistent with the actions performed by the control operator(s)) - it is the performance of the control that we are testing and NOT a substantive test of a transaction or balance from which we can infer control effectiveness | I74: 통제 운영자가 정확하게 어떤 일을 수행하였고, 통제 운영자가 명시된 절차를 실제로 수행하였는지를 확인하기 위하여 감사팀이 입수한 증거는 무엇인가? What exactly did the control operator(s) do and what evidence was obtained by the engagement team to ascertain the control operator(s) actually performed the procedures described? Note: 입수한 증거는 질문(보충 질문 포함), 관찰, 조사, 재수행이나 이들의 결합을 통해 수집됨. Note: the evidence obtained is gathered through inquiries (including corroborative inquiries), observation, inspection, reperformance or a combination thereof. (감사팀은 통제 운영자가 정확하게 무엇을 실시하였는지에 대하여 "Review Control Design" 탭 내 I열의 일관성을 검토하여야 함. 감사팀은, 통제 운영자가 기재된 절차를 실제로 수행하였음을 확인하기 위하여, "Review Control Design" 탭 내 O 열 및 상기의 질문, 관찰 및 조사에서 문서화한 감사 증거와의 일관성을 검토하여야 함.) (Engagement team should verify consistency with row I of the "Review Control Design" tab regarding what exactly the control operator(s) did. Engagement teams should verify consistency with row O of the "Review Control Design" tab and/or the evidence gathered as documented above in Inquiry, Observation and/or Inpsection regarding the evidence obtained to ascertain the control operator(s) actually performed the procedures described) | K74: 통제 운영자의 활동을 재수행하기 위하여 감사팀이 무엇을 수행하였는지 세부적으로 기재. What exactly did the engagement team do to reperform the control operator(s)'s action? (Reminder : 감사팀의 절차는 통제 운영자가 수행한 활동과 일관되어야 함에 유의. 감사팀은 통제가 수행되었는지 여부를 테스트하며, 거래나 잔액에 대한 실증테스트에서 통제 효과성을 추론하지 않음.) (Reminder: engagement team procedures should be consistent with the actions performed by the control operator(s)) - it is the performance of the control that we are testing and NOT a substantive test of a transaction or balance from which we can infer control effectiveness
B77: 5) 통제 활동이 효과적으로 운영되었음을 반영하는 기타의 감사 증거가 있다면, 이를 어떻게 고려하였는지 문서화 (예를 들어, 분기 검토 중 잠재적인 왜곡표시나 예외사항이 통제 활동에 의해 적절히 발견되고 적시에 수정되었다는 증거가 존재하는지?) 5) Document consideration of other evidence, if any, that reflects positively on the operating effectiveness of the control activity (For example, during a quarterly review, is there evidence that potential misstatements or exceptions were appropriately detected by the control activity and timely corrected?)
B80: 6) 통제 활동이 효과적으로 운영되지 않음을 반영되는 기타의 감사 증거가 있다면, 이를 어떻게 고려하였는지 문서화 (예를 들어, 통제 활동에 의하여 적발되고 해결되었어야 하나 그러지 않은 왜곡표시나 예외사항(기간 외 조정 포함)이 존재하는지?) 6) Document consideration of evidence, if any, that reflects negatively on the operating effectiveness of the control activity (For example, have there been misstatements or other exceptions, including out of period adjustments, that should have been detected and resolved by the control activity but were not?)

Sheet Master Control Activity v2016
B1: Prior year control testing documentation rolled forward for reference purposes.
B2: 운영효과성에 대한 테스트 - 통제활동- Operating Effectiveness Testing - Control Activity-
B3: Note: 각 통제 활동에 대하여 별도의 테스트 탭을 생성하여야 함 Note: A separate testing tab should be created for each control activity
B4: 동 review control activity와 관련된 LSPM은 무엇인가? (개별 통제 활동의 목적 및 설계에 대한 세부적인 이해에 근거하여 이 review control에 대한 설계 평가에 대한 결론을 내릴 때, 통제 활동이 관련 LSPM(Aura v6의 Risk Strategy view 및 설계 평가에 문서화된 바와 같이)에 대응하는지 재확인하여야 함) What LSPMs are relevant for this review control activity? (In finalizing the assessment of the design of this review control (based on a detailed understanding of the objective and design of individual control activities), we should reconfirm the control activity is responsive to the LSPMs to which is it linked (in the Risk Strategy view of Aura v6 and as documented in the design evaluation))
B5: 통제 활동의 내용 [어떻게 통제 운영자가 통제 활동의 목적을 달성하는지(즉, 통제 운영자가 정확하게 무엇을, 얼마나 정밀한 수준으로 수행하는지)?] Control Activity Description [How does the control operator accomplish the objective of this control activity (i.e., what exactly does the control operator do and at what level of precision)?]
B7: 1) 테스트 모집단을 결정 1) Determine the population(s) for testing | I7: 2) 통제 활동의 빈도 및 계획한 감사증거 수준에 따라 테스트할 기간의 개수 결정 2) Determine the number of periods to test based on the frequency of the control activity and the desired level of evidence
B8: 샘플을 선정하고 결론을 도출할 모집단을 식별 Note: 샘플을 선정하고 결론을 도출할 모집단은 사람, 프로세스, 연관 시스템, 공동의 ELC, 공동의 관리/감독, 공동의 실패 위험 등의 요소들을 고려하였을 때 하나의 모집단으로 테스트할 수 있을 만큼 충분히 동질적이어야 함. 추가적인 지침은 US PwC Audit 5400(US PwC Audit (NP) 5400)을 참조. Identify the population from which to select the sample and about which to draw conclusions Note: the population from which to select a sample and draw conclusions should be sufficiently homogenous to test as one population based on consideration of factors such as the people, processes, and systems involved, commonality of ELCs, commonality of supervisory oversight, common risks of failure, etc. Refer to US PwC Audit 5400 (US PwC Audit (NP) 5400) for further guidance. | I8: 통제 활동의 빈도 (예, 연간, 분기별, 월별, 주별, 일별, 1일 수시) Frequency of control activity (e.g., annual, quarterly, monthly, weekly, daily, multiple times per day)
B9: 모집단 완전성을 판단하기 위하여 수행한 절차 Procedures performed to determine the population is complete | I9: 통제 활동의 빈도 및 계획한 감사증거 수준에 따른 테스트 대상 기간 수(추가적인 지침은 US PwC Audit 5400 (US PwC Audit (NP) 5400)을 참조) Number of periods to test based on the frequency of the control activity and the desired level of evidence (Refer to US PwC Audit 5400 (US PwC Audit (NP) 5400) for further guidance)
B11: 3) 각 기간에 대하여 테스트할 통제 활동의 instance 개수 결정 3) Determine the number of instances of the control activity to test for each period | I11: 4a) 경영진이 사용한 정보가 의도된 목적(그러한 절차의 결과를 문서화하는 것을 포함하여) 상 신뢰성이 있는지(즉, 완전하고 정확한지) 확인하기 위해, 이 통제 활동의 운영에 중요하게 사용되는 정보에 대한 통제를 테스트 4a) Test the control(s) over information used in and important to the operation of this control activity used by management to ensure such information is reliable (i.e., is complete and accurate) for its intended purpose, including documenting the results of those procedures
B12: 각 모집단의 각 기간에 수행되는 통제 활동의 instance 개수 Note: 모집단 내에서 각 기간에 통제 활동이 1회를 초과하여 일어나는 경우, 통제 활동이 설계대로 일관성있게 운영되었음을 입증하기 위하여 필요한 감사증거의 범위를 결정하기 위하여 각 기간에 대하여 테스트할 통제 활동의 instance 개수를 결정함. 이러한 결정은 통제 활동과 연관된 위험, 이용가능한 감사증거 및 과거 경험에 근거한 전문가적 판단의 문제이다. 추가적인 지침은 US PwC Audit 5400 (US PwC Audit (NP) 5400)을 참조. Number of instances the control activity operates during each period for each population Note: In situations where a control activity occurs more than once per period within a population, determine the number of instances of the control activity to test for each period to determine the extent of evidence needed to be persuaded the control activity is operating consistently as designed. This determination is a matter of professional judgment and is based on the risk associated with the control activity, available evidence, and prior experience. Refer to US PwC Audit 5400 (US PwC Audit (NP) 5400) for further guidance. | I12: 통제 활동의 운영에 중요하게 사용되는 정보에 대하여, 그러한 정보의 신뢰성(즉, 완전하고 정확함)과 관련한 확신을 제공하기 위하여 경영진이 의존한 통제의 내용 For information determined to be used in and important to the operation of this control activity, describe the control(s) management is relying on to provide assurance regarding the reliability (i.e., it is complete and accurate) of such information.
I13: 경영진의 통제 절차에 대한 통제 테스트의 결과를 기재하거나, 테스트 절차가 수행된 조서에 대한 링크를 첨부 Note: 통합감사의 경우, 이 통제 활동 운영에 사용된 정보의 신뢰성에 대한 우리의 독립적인 테스트와는 별개로 이러한 정보에 대한 경영진의 통제를 테스트하여야 함. Include the results of the control(s) testing over management's control procedures or reference to where the testing procedures are performed. Note: Our own independent testing over the reliability of the information used in the operation of this control activity would not substitute for our requirement to test management's controls over such information in an integrated audit.
B15: 4b) 선택한 통제 활동의 instance를 테스트 4b) Test the control activity instances selected
B16: 해당되는 모든 항목에 체크: Check all that apply:
A18: FALSE | B18: 질문 절차 - (질문만으로는 운영 효과성과 관련된 결론을 뒷받침하기에 충분하지 않음에 유의) Inquiry Procedures - (Reminder - inquiry alone is not sufficient to support conclusion regarding operating effectiveness)
B20: 테스트 계획 Test Plan | I20: 통제 활동에 investigation 기준이나 thresholds가 포함되는 경우, 테스트 계획에 확인할 후속조치의 개수에 대한 고려 뿐만 아니라 경영진이 통제 활동의 설계와 일관성있게 후속조치 및 investigation 항목을 모두 적절히 식별하였는지 여부를 판단하기 위한 절차가 포함되었는지 확인. 'Review' 통제 활동의 설계, 성격 및 빈도에 따라서, "Management Follow-up Items" 및 "Detailed Testing Table" 탭이 필요할 수 있음. In situations where the control activity includes criteria and/or thresholds for items being investigated, ensure the plan includes consideration for the number of follow-ups to corroborate as well as procedures to determine whether management appropriately identified all items for follow up and investigation consistent with the design of the control activity. The tabs “management Follow-up Items” and “Detailed Testing Table” may be needed based upon the design, nature and frequency of the ‘review’ control activity.
B21: 이 통제 활동과 관련된 질문 절차 수행 계획을 세부적으로 기재 (질문만으로는 운영 효과성과 관련된 결론을 뒷받침하기에 충분하지 않음에 유의) Describe in detail the plan to perform inquiry procedures related to this control activity (Reminder - inquiry alone is not sufficient to support conclusion regarding operating effectiveness)
B24: [대상기간 기재]에 대한 테스트 결과 Testing Results for [insert period] | I24: [대상기간 기재]에 대한 테스트 결과 Testing Results for [insert period]
A25: 1 | B25: 문서화 항목 Documentation Prompt | D25: 감사 증거 Evidence | G25: 예외사항 Exception(s) | I25: 문서화 항목 Documentation Prompt | K25: 감사 증거 Evidence | N25: 예외사항 Exception(s)
B26: 누구에게 질문이 수행되었는가? With whom were inquiries performed? | I26: 누구에게 질문이 수행되었는가? With whom were inquiries performed?
B27: 질문 수행 일자 Date inquiries were performed | I27: 질문 수행 일자 Date inquiries were performed
B28: 통제 활동 운영과 관련하여 통제 운영자에게 질문한 내용(보충 질문의 경우, 검토대상 업무의 수행자 또는 기타의 인원) Question asked of the control operator related to the operation of the control activity (or preparer or others if these are corroborative inquiries) | I28: 통제 활동 운영과 관련하여 통제 운영자에게 질문한 내용(보충 질문의 경우, 검토대상 업무의 수행자 또는 기타의 인원) Question asked of the control operator related to the operation of the control activity (or preparer or others if these are corroborative inquiries)
B29: 답변 Response provided | I29: 답변 Response provided
A32: FALSE | B32: 관찰 절차 Observation Procedures
B34: 테스트 계획 Test Plan | I34: 통제 활동에 investigation 기준이나 thresholds가 포함되는 경우, 테스트 계획에 확인할 후속조치의 개수에 대한 고려 뿐만 아니라 경영진이 통제 활동의 설계와 일관성있게 후속조치 및 investigation 항목을 모두 적절히 식별하였는지 여부를 판단하기 위한 절차가 포함되었는지 확인. 'Review' 통제 활동의 설계, 성격 및 빈도에 따라서, "Management Follow-up Items" 및 "Detailed Testing Table" 탭이 필요할 수 있음. In situations where the control activity includes criteria and/or thresholds for items being investigated, ensure the plan includes consideration for the number of follow-ups to corroborate as well as procedures to determine whether management appropriately identified all items for follow up and investigation consistent with the design of the control activity. The tabs “management Follow-up Items” and “Detailed Testing Table” may be needed based upon the design, nature and frequency of the ‘review’ control activity.
B35: 관찰 절차 수행 계획 및 입수할 감사증거의 세부 내역을 기재(각 기간의 테스트 항목 개수, 관련된 선정 기준 포함) Describe in detail the plan to perform observation procedures and the expected evidence to be obtained, including the number of items to be tested for each period and the related basis of selection
B38: [대상기간 기재]에 대한 테스트 결과 Testing Results for [insert period] | I38: [대상기간 기재]에 대한 테스트 결과 Testing Results for [insert period]
B39: 문서화 항목 Documentation Prompt | D39: 감사 증거 Evidence | G39: 예외사항 Exception(s) | I39: 문서화 항목 Documentation Prompt | K39: 감사 증거 Evidence | N39: 예외사항 Exception(s)
B40: 회의 또는 토론 일자 Meeting or discussion date | I40: 회의 또는 토론 일자 Meeting or discussion date
B41: 참석자 및 역할 (감사팀 및 기타 인원) Attendees and roles (Engagement team and others) | I41: 참석자 및 역할 (감사팀 및 기타 인원) Attendees and roles (Engagement team and others)
B42: 통제 운영자가 요청한 특정 조치 또는 통제운영자가 제기한 질문, 회의 또는 토론에서 논의된 사항들 Specific actions requested or questions raised by the control operator(s) and items discussed in the meeting or discussion | I42: 통제 운영자가 요청한 특정 조치 또는 통제운영자가 제기한 질문, 회의 또는 토론에서 논의된 사항들 Specific actions requested or questions raised by the control operator(s) and items discussed in the meeting or discussion
B43: 논의의 완전성에 대한 감사 증거(토론에서 다루어진 특정 내용이 설계평가 상 통제 활동의 정밀함의 수준을 뒷받침하는지의 여부를 포함) Evidence of completeness of the discussions, including whether specific matters addressed supported the designed precision level of the control activity | I43: 논의의 완전성에 대한 감사 증거(토론에서 다루어진 특정 내용이 설계평가 상 통제 활동의 정밀함의 수준을 뒷받침하는지의 여부를 포함) Evidence of completeness of the discussions, including whether specific matters addressed supported the designed precision level of the control activity
B44: Review의 정확성 및 효과성에 대한 증거를 제공하는, 토론의 결과로 도출된 후속조치 항목이나 변동 사항을 설명 Describe any follow-up items or changes resulting from the discussion that provide evidence of the precision and effectiveness of the review | I44: Review의 정확성 및 효과성에 대한 증거를 제공하는, 토론의 결과로 도출된 후속조치 항목이나 변동 사항을 설명 Describe any follow-up items or changes resulting from the discussion that provide evidence of the precision and effectiveness of the review
B45: 통제 운영자가 그에 필요한 지식 및 경험을 보여주는가? 그렇다면, 어떻게? Did the control operator demonstrate the requisite knowledge and experience? If so, how? | I45: 통제 운영자가 그에 필요한 지식 및 경험을 보여주는가? 그렇다면, 어떻게? Did the control operator demonstrate the requisite knowledge and experience? If so, how?
B46: 상기의 고려사항들이 전반적인 review의 범위 및 정확성에 관한 우리의 결론을 뒷받침하는가? 그렇다면, 어떻게? Did the considerations above support our conclusion regarding the overall scope and precision of the review? If so, how? | I46: 상기의 고려사항들이 전반적인 review의 범위 및 정확성에 관한 우리의 결론을 뒷받침하는가? 그렇다면, 어떻게? Did the considerations above support our conclusion regarding the overall scope and precision of the review? If so, how?
A48: FALSE | B48: 문서검사 절차 Inspection Procedures
B50: 테스트 계획 Test Plan | I50: 통제 활동에 investigation 기준이나 thresholds가 포함되는 경우, 테스트 계획에 확인할 후속조치의 개수에 대한 고려 뿐만 아니라 경영진이 통제 활동의 설계와 일관성있게 후속조치 및 investigation 항목을 모두 적절히 식별하였는지 여부를 판단하기 위한 절차가 포함되었는지 확인. 'Review' 통제 활동의 설계, 성격 및 빈도에 따라서, "Management Follow-up Items" 및 "Detailed Testing Table" 탭이 필요할 수 있음. In situations where the control activity includes criteria and/or thresholds for items being investigated, ensure the plan includes consideration for the number of follow-ups to corroborate as well as procedures to determine whether management appropriately identified all items for follow up and investigation consistent with the design of the control activity. The tabs “management Follow-up Items” and “Detailed Testing Table” may be needed based upon the design, nature and frequency of the ‘review’ control activity.
B51: 문서검사 절차 수행 계획 및 입수할 감사증거의 세부 내역을 기재(각 기간의 테스트 항목 개수, 관련된 선정 기준 포함) Describe in detail the plan to perform inspection procedures and the expected evidence to be obtained, including the number of items to be tested for each period and the related basis of selection
B54: [대상기간 기재]에 대한 테스트 결과 Testing Results for [insert period] | I54: [대상기간 기재]에 대한 테스트 결과 Testing Results for [insert period]
B55: 문서화 항목 Documentation Prompt | D55: 감사 증거 Evidence | G55: 예외사항 Exception(s) | I55: 문서화 항목 Documentation Prompt | K55: 감사 증거 Evidence | N55: 예외사항 Exception(s)
B56: 검사한 통제 활동 문서에 대한 감사 증거(해당 항목에 체크): (비고: 아래의 내역이 모두 포함되어야 하거나, 나열된 항목이 모두 요구되는 것은 아님. 추가적인 지침은 PwC Audit 4165.12를 참조.) Evidence of control activity documentation inspected (check those that apply): (Note: the list below is not all-inclusive and not all items listed below are required. Refer to PwC Audit 4165.12 for further guidance.) | I56: 검사한 통제 활동 문서에 대한 감사 증거(해당 항목에 체크): (비고: 아래의 내역이 모두 포함되어야 하거나, 나열된 항목이 모두 요구되는 것은 아님. 추가적인 지침은 PwC Audit 4165.12를 참조.) Evidence of control activity documentation inspected (check those that apply): (Note: the list below is not all-inclusive and not all items listed below are required. Refer to PwC Audit 4165.12 for further guidance.)
A57: FALSE | B57: 서명(승인) Sign-offs | H57: FALSE | I57: 서명(승인) Sign-offs
A58: FALSE | B58: 회의 안건 Meeting agendas | H58: FALSE | I58: 회의 안건 Meeting agendas
A59: FALSE | B59: 고려사항, 근거 및 결론이 기재된 상세한 회의 자료 Detailed memorandum that outline the considerations, rationale and conclusions reached | H59: FALSE | I59: 고려사항, 근거 및 결론이 기재된 상세한 회의 자료 Detailed memorandum that outline the considerations, rationale and conclusions reached
A60: FALSE | B60: 기준/thresholds에 해당하는 사항에 대한 후속조치 이행 및 해결을 입증하는 통제 운영자와의(to/from) 이메일 기록 서신 Email correspondence to/from the control operator demonstrating follow up and resolution of items that meet the criteria/thresholds | H60: FALSE | I60: 기준/thresholds에 해당하는 사항에 대한 후속조치 이행 및 해결을 입증하는 통제 운영자와의(to/from) 이메일 기록 서신 Email correspondence to/from the control operator demonstrating follow up and resolution of items that meet the criteria/thresholds
A61: FALSE | B61: 실질적으로 검토가 실행되었음을 입증하는, 서식/문서 또는 분석에 기재된 표시 Notations on forms, documents or analysis that demonstrate the substance of the execution of the review | H61: FALSE | I61: 실질적으로 검토가 실행되었음을 입증하는, 서식/문서 또는 분석에 기재된 표시 Notations on forms, documents or analysis that demonstrate the substance of the execution of the review
A62: FALSE | B62: 상세한 회의록 (고려사항, 근거, 결론 및 결론이 어떻게 도출되었는지에 대한 내용 포함) Detailed meeting minutes, that include the considerations, rationale, conclusions, as well as how those were arrived | H62: FALSE | I62: 상세한 회의록 (고려사항, 근거, 결론 및 결론이 어떻게 도출되었는지에 대한 내용 포함) Detailed meeting minutes, that include the considerations, rationale, conclusions, as well as how those were arrived
A63: FALSE | B63: 기타. 설명: Other. Describe: | H63: FALSE | I63: 기타. 설명: Other. Describe:
A65: FALSE | B65: 재수행 절차 (비고: 재수행 테스트 절차를 통제 및 실증 테스트 모두를 목적으로 수행하려는 경우, 테스트 계획 및 입수할 감사 증거가 통제 활동의 수행 여부 및 실증 테스트 목적 달성 여부 둘 다에 구체적으로 관련성이 있는지 확인. 통제의 효과성에 대하여 직접적인 증거를 제공하지 않는 감사 증거는 dual purpose test에 대한 증거를 제공하지 않음.) Reperformance Procedures (Note: If reperformance testing procedures are intended to provide both controls and substantive testing evidence, confirm the test plan and evidence obtained is specific with respect to BOTH the control activities performed as well as the achievement of substantive testing objectives. Audit evidence that does not provide direct evidence regarding control effectivness does not provide dual purpose evidence.)
B67: 테스트 계획 Test Plan | I67: 통제 활동에 investigation 기준이나 thresholds가 포함되는 경우, 테스트 계획에 확인할 후속조치의 개수에 대한 고려 뿐만 아니라 경영진이 통제 활동의 설계와 일관성있게 후속조치 및 investigation 항목을 모두 적절히 식별하였는지 여부를 판단하기 위한 절차가 포함되었는지 확인. 'Review' 통제 활동의 설계, 성격 및 빈도에 따라서, "Management Follow-up Items" 및 "Detailed Testing Table" 탭이 필요할 수 있음. In situations where the control activity includes criteria and/or thresholds for items being investigated, ensure the plan includes consideration for the number of follow-ups to corroborate as well as procedures to determine whether management appropriately identified all items for follow up and investigation consistent with the design of the control activity. The tabs “management Follow-up Items” and “Detailed Testing Table” may be needed based upon the design, nature and frequency of the ‘review’ control activity.
B68: 통제활동에 대한 재수행 계획 및 입수할 감사증거의 세부 내역을 기재(각 기간의 테스트 항목 개수, 관련된 선정 기준 포함) Describe in detail the plan to reperform the control activity and the expected evidence to be obtained, including the number of items to be tested for each period and the related basis of selection
B71: [대상기간 기재]에 대한 테스트 결과 Testing Results for [insert period] | I71: [대상기간 기재]에 대한 테스트 결과 Testing Results for [insert period]
A72: 1 | B72: 문서화 항목 Documentation Prompt | C72: 감사 증거 Evidence | D72: 문서화 항목 Documentation Prompt | E72: 감사 증거 Evidence | F72: 예외사항 Exception(s) | I72: 문서화 항목 Documentation Prompt | J72: 감사 증거 Evidence | K72: 문서화 항목 Documentation Prompt | L72: 감사 증거 Evidence | M72: 예외사항 Exception(s)
B73: 통제 운영자의 활동 1 Control Operator(s) Action 1 | D73: 감사팀의 활동 Engagement Team Action | I73: 통제 운영자의 활동 1 Control Operator(s) Action 1 | K73: 감사팀의 활동 Engagement Team Action
B74: 통제 운영자가 정확하게 어떤 일을 수행하였고, 통제 운영자가 명시된 절차를 실제로 수행하였는지를 확인하기 위하여 감사팀이 입수한 증거는 무엇인가? What exactly did the control operator(s) do and what evidence was obtained by the engagement team to ascertain the control operator(s) actually performed the procedures described? Note: 입수한 증거는 질문(보충 질문 포함), 관찰, 조사, 재수행이나 이들의 결합을 통해 수집됨. Note: the evidence obtained is gathered through inquiries (including corroborative inquiries), observation, inspection, reperformance or a combination thereof. (감사팀은 통제 운영자가 정확하게 무엇을 실시하였는지에 대하여 "Review Control Design" 탭 내 I열의 일관성을 검토하여야 함. 감사팀은, 통제 운영자가 기재된 절차를 실제로 수행하였음을 확인하기 위하여, "Review Control Design" 탭 내 O 열 및 상기의 질문, 관찰 및 조사에서 문서화한 감사 증거와의 일관성을 검토하여야 함.) (Engagement team should verify consistency with row I of the "Review Control Design" tab regarding what exactly the control operator(s) did. Engagement teams should verify consistency with row O of the "Review Control Design" tab and/or the evidence gathered as documented above in Inquiry, Observation and/or Inpsection regarding the evidence obtained to ascertain the control operator(s) actually performed the procedures described) | D74: 통제 운영자의 활동을 재수행하기 위하여 감사팀이 무엇을 수행하였는지 세부적으로 기재. What exactly did the engagement team do to reperform the control operator(s)'s action? (Reminder : 감사팀의 절차는 통제 운영자가 수행한 활동과 일관되어야 함에 유의. 감사팀은 통제가 수행되었는지 여부를 테스트하며, 거래나 잔액에 대한 실증테스트에서 통제 효과성을 추론하지 않음.) (Reminder: engagement team procedures should be consistent with the actions performed by the control operator(s)) - it is the performance of the control that we are testing and NOT a substantive test of a transaction or balance from which we can infer control effectiveness | I74: 통제 운영자가 정확하게 어떤 일을 수행하였고, 통제 운영자가 명시된 절차를 실제로 수행하였는지를 확인하기 위하여 감사팀이 입수한 증거는 무엇인가? What exactly did the control operator(s) do and what evidence was obtained by the engagement team to ascertain the control operator(s) actually performed the procedures described? Note: 입수한 증거는 질문(보충 질문 포함), 관찰, 조사, 재수행이나 이들의 결합을 통해 수집됨. Note: the evidence obtained is gathered through inquiries (including corroborative inquiries), observation, inspection, reperformance or a combination thereof. (감사팀은 통제 운영자가 정확하게 무엇을 실시하였는지에 대하여 "Review Control Design" 탭 내 I열의 일관성을 검토하여야 함. 감사팀은, 통제 운영자가 기재된 절차를 실제로 수행하였음을 확인하기 위하여, "Review Control Design" 탭 내 O 열 및 상기의 질문, 관찰 및 조사에서 문서화한 감사 증거와의 일관성을 검토하여야 함.) (Engagement team should verify consistency with row I of the "Review Control Design" tab regarding what exactly the control operator(s) did. Engagement teams should verify consistency with row O of the "Review Control Design" tab and/or the evidence gathered as documented above in Inquiry, Observation and/or Inpsection regarding the evidence obtained to ascertain the control operator(s) actually performed the procedures described) | K74: 통제 운영자의 활동을 재수행하기 위하여 감사팀이 무엇을 수행하였는지 세부적으로 기재. What exactly did the engagement team do to reperform the control operator(s)'s action? (Reminder : 감사팀의 절차는 통제 운영자가 수행한 활동과 일관되어야 함에 유의. 감사팀은 통제가 수행되었는지 여부를 테스트하며, 거래나 잔액에 대한 실증테스트에서 통제 효과성을 추론하지 않음.) (Reminder: engagement team procedures should be consistent with the actions performed by the control operator(s)) - it is the performance of the control that we are testing and NOT a substantive test of a transaction or balance from which we can infer control effectiveness
B77: 5) 통제 활동이 효과적으로 운영되었음을 반영하는 기타의 감사 증거가 있다면, 이를 어떻게 고려하였는지 문서화 (예를 들어, 분기 검토 중 잠재적인 왜곡표시나 예외사항이 통제 활동에 의해 적절히 발견되고 적시에 수정되었다는 증거가 존재하는지?) 5) Document consideration of other evidence, if any, that reflects positively on the operating effectiveness of the control activity (For example, during a quarterly review, is there evidence that potential misstatements or exceptions were appropriately detected by the control activity and timely corrected?)
B80: 6) 통제 활동이 효과적으로 운영되지 않음을 반영되는 기타의 감사 증거가 있다면, 이를 어떻게 고려하였는지 문서화 (예를 들어, 통제 활동에 의하여 적발되고 해결되었어야 하나 그러지 않은 왜곡표시나 예외사항(기간 외 조정 포함)이 존재하는지?) 6) Document consideration of evidence, if any, that reflects negatively on the operating effectiveness of the control activity (For example, have there been misstatements or other exceptions, including out of period adjustments, that should have been detected and resolved by the control activity but were not?)

Sheet DataSheet
B2: 누구에게 질문이 수행되었는가? With whom were inquiries performed? | I2: 누구에게 질문이 수행되었는가? With whom were inquiries performed?
B3: 질문 수행 일자 Date inquiries were performed | I3: 질문 수행 일자 Date inquiries were performed
B4: 통제 활동 운영과 관련하여 통제 운영자에게 질문한 내용(보충 질문의 경우, 검토대상 업무의 수행자 또는 기타의 인원) Question asked of the control operator related to the operation of the control activity (or preparer or others if these are corroborative inquiries) | I4: 통제 활동 운영과 관련하여 통제 운영자에게 질문한 내용(보충 질문의 경우, 검토대상 업무의 수행자 또는 기타의 인원) Question asked of the control operator related to the operation of the control activity (or preparer or others if these are corroborative inquiries)
B5: 답변 Response provided | I5: 답변 Response provided
B9: 통제 운영자의 활동 Control Operator(s) Action | D9: 감사팀의 활동 Engagement Team Action | I9: 통제 운영자의 활동 Control Operator(s) Action | K9: 감사팀의 활동 Engagement Team Action
B10: 통제 운영자가 정확하게 어떤 일을 수행하였고, 통제 운영자가 명시된 절차를 실제로 수행하였는지를 확인하기 위하여 감사팀이 입수한 증거는 무엇인가? What exactly did the control operator(s) do and what evidence was obtained by the engagement team to ascertain the control operator(s) actually performed the procedures described? Note: 입수한 증거는 질문(보충 질문 포함), 관찰, 조사, 재수행이나 이들의 결합을 통해 수집됨. Note: the evidence obtained is gathered through inquiries (including corroborative inquiries), observation, inspection, reperformance or a combination thereof. (감사팀은 통제 운영자가 정확하게 무엇을 실시하였는지에 대하여 "Review Control Design" 탭 내 I열의 일관성을 검토하여야 함. 감사팀은, 통제 운영자가 기재된 절차를 실제로 수행하였음을 확인하기 위하여, "Review Control Design" 탭 내 O 열 및 상기의 질문, 관찰 및 조사에서 문서화한 감사 증거와의 일관성을 검토하여야 함.) (Engagement team should verify consistency with row I of the "Review Control Design" tab regarding what exactly the control operator(s) did. Engagement teams should verify consistency with row O of the "Review Control Design" tab and/or the evidence gathered as documented above in Inquiry, Observation and/or Inpsection regarding the evidence obtained to ascertain the control operator(s) actually performed the procedures described) | D10: 통제 운영자의 활동을 재수행하기 위하여 감사팀이 무엇을 수행하였는지 세부적으로 기재. What exactly did the engagement team do to reperform the control operator(s)'s action? (Reminder: 감사팀의 절차는 통제 운영자가 수행한 활동과 일관되어야 함에 유의. 감사팀은 통제가 수행되었는지 여부를 테스트하며, 거래나 잔액에 대한 실증테스트에서 통제 효과성을 추론하지 않음.) (Reminder: engagement team procedures should be consistent with the actions performed by the control operator(s)) - it is the performance of the control that we are testing and NOT a substantive test of a transaction or balance from which we can infer control effectiveness | I10: 통제 운영자가 정확하게 어떤 일을 수행하였고, 통제 운영자가 명시된 절차를 실제로 수행하였는지를 확인하기 위하여 감사팀이 입수한 증거는 무엇인가? What exactly did the control operator(s) do and what evidence was obtained by the engagement team to ascertain the control operator(s) actually performed the procedures described? Note: 입수한 증거는 질문(보충 질문 포함), 관찰, 조사, 재수행이나 이들의 결합을 통해 수집됨. Note: the evidence obtained is gathered through inquiries (including corroborative inquiries), observation, inspection, reperformance or a combination thereof. (감사팀은 통제 운영자가 정확하게 무엇을 실시하였는지에 대하여 "Review Control Design" 탭 내 I열의 일관성을 검토하여야 함. 감사팀은, 통제 운영자가 기재된 절차를 실제로 수행하였음을 확인하기 위하여, "Review Control Design" 탭 내 O 열 및 상기의 질문, 관찰 및 조사에서 문서화한 감사 증거와의 일관성을 검토하여야 함.) (Engagement team should verify consistency with row I of the "Review Control Design" tab regarding what exactly the control operator(s) did. Engagement teams should verify consistency with row O of the "Review Control Design" tab and/or the evidence gathered as documented above in Inquiry, Observation and/or Inpsection regarding the evidence obtained to ascertain the control operator(s) actually performed the procedures described) | K10: 통제 운영자의 활동을 재수행하기 위하여 감사팀이 무엇을 수행하였는지 세부적으로 기재. What exactly did the engagement team do to reperform the control operator(s)'s action? (Reminder: 감사팀의 절차는 통제 운영자가 수행한 활동과 일관되어야 함에 유의. 감사팀은 통제가 수행되었는지 여부를 테스트하며, 거래나 잔액에 대한 실증테스트에서 통제 효과성을 추론하지 않음.) (Reminder: engagement team procedures should be consistent with the actions performed by the control operator(s)) - it is the performance of the control that we are testing and NOT a substantive test of a transaction or balance from which we can infer control effectiveness

Sheet Master Review Procedures
B1: Prior year control testing documentation rolled forward for reference purposes.
B2: 'Review' 통제를 테스트한다 Test 'Review' control
B3: 2명 이상의 팀원이 동 EGA를 prepare한 경우, 관여한 팀원의 이름과 수행한 절차를 문서화. When more than one preparer was involved in the completion of this EGA, document the names of the team members involved and the procedures performed. | F3: [팀원의 이니셜/이름 및 수행한 절차를 문서화(예를 들어, 홍길동이 하단 a)절차를 수행)] [Document the initials or names of team members and procedures performed (e.g., Jane Doe performed step a) below)]
B6: Procedures | F6: Results | K6: Links
B7: a) | C7: 가장 최근의 평가 이후에 'review' 통제 설계에 변경이 있는지 확인한다. Verify whether there have been changes to the design of the 'review' control since it was last evaluated. | G7: 가장 최근의 'review' 통제에 대한 평가 이후에 통제 설계에 변경이 있는지 확인하고 이를 평가함: Verified if there have been changes to the design of the 'review' control since it was last evaluated and evaluate the design of the 'review' control:
H9: 'Review' 통제 설계에서 변경사항이 파악되지 않음, 또는 No changes were noted in the design of the 'review' control, or
H10: 'Review' 통제 설계에 변경사항이 파악됨. Changes were noted in the design of the 'review' control.
G11: [필요한 경우, 수행한 절차와 변경사항을 문서화] [Document procedures performed and changes, as necessary]
F12: 그리고 AND
G13: 'Review' 통제의 설계를 평가함, 그리고 Evaluated the design of the 'review' control, and
H14: 통제가 효과적으로 설계되었다고 판단함, 또는 Concluded the control is designed effectively, or
H15: 통제가 효과적으로 설계되어 있지 않다고 판단함. 식별된 미비점을 SAD에 기록하고, 해당 업무프로세스의 영향을 받는 FSLI에 대한 감사 계획을 고려함. Concluded the control is not designed effectively, and posted the identified deficiency to the SAD and considered the planned audit procedures for the FSLIs impacted by the business process.
G18: [영향을 받는 FSLI에 대한 감사 계획을 평가한 세부 내용을 문서화] [Document details of evaluation of planned audit procedures for impacted FSLIs]
B21: b) | C21: 'Review' 통제의 운영 효과성을 테스트한다. Test the operating effectiveness of the 'review' control. | G21: Control Activity-x Template에서 각 주요 통제 활동에 대한 테스트 절차를 수행함. Performed testing procedures for each key control activity in the Control Activity-x template.
C24: Note: 질문 만으로는 특정 통제의 효과성 테스트로 충분하지 않음. 수동 통제의 운영 효과성을 평가하는 테스트 방법의 목록은 US PwC Audit 5400 and US PwC Audit (NP) 5400를 참조. Note: Inquiry alone is not sufficient to test the operating effectiveness of a control. Refer to US PwC Audit 5400 and US PwC Audit (NP) 5400 for a listing of testing techniques to evaluate the effective operation of a manual control. Direct entity level control(direct ELC) 및 일부 'review' 통제의 경우, 운영 효과성에 대한 테스트는 경영진의 설명 및 통제 실행의 결론의 합리성과 정확성에 대한 증거를 제공하고, 질문, 회의 참석, 승인(서명)에 대한 검사 및 입수한 설명에 대한 단순한 문서화를 넘어서는 충분한 증거를 포함해야 함. For direct entity level controls and certain 'review' controls, the testing of operating effectiveness should corroborate the reasonableness and accuracy of management's explanations and conclusions resulting from their execution of the control, and should also include sufficient evidence that goes beyond inquiry, attendance at meetings, inspection of sign-offs, and mere documentation that explanations were obtained.
B38: c) | C38: 각 세부 통제 활동에서 식별된 예외사항을 포함한 모든 테스트 결과 및 기타 증거를 고려하여, 'review' 통제가 효과적으로 운영되는지 판단한다. 통제가 효과적으로 운영되지 않는다고 판단될 경우, 통제 미비점을 SAD 또는 CD/W log에 집계하고 감사 전략 및 감사 절차 계획에 대한 통제 미비점의 영향을 평가한다. Consider all test results and other evidence, including exceptions identified in any of the underlying control activities, and determine whether the 'review' control is operating effectively. If the control is determined not to be operating effectively, post the control deficiency to the SAD / CD/W log and evaluate the impact of the control deficiency on the audit strategy and planned audit procedures. | G38: 각 Contol Activity-x Template에서 테스트 결과를 평가함, 그리고 Evaluated testing results within each of the Control Activity-x templates, and
H39: 식별된 예외사항이나 포함된 통제 활동들 간에 상충되는 감사 증거는 없음. 따라서, 'review' 통제 및 그에 포함된 통제 활동들은 효과적으로 운영되었다고 판단함, 또는 There were no exceptions identified or contrary evidence within the underlying control activities. Accordingly, the 'review' control and its underlying control activities were determined to be operating effectively, or
H42: 식별된 예외사항 그리고/또는 포함된 통제 활동들 간에 상충되는 감사 증거가 존재함. 따라서, 'review' 통제가 효과적으로 운영되지 않았다고 판단함. 통제 미비점을 SAD 또는 CD/W log에 집계하고 감사 전략 및 감사 절차 계획에 대한 통제 미비점의 영향을 평가함. There were exceptions identified and/or contrary evidence within the underlying control activities. Accordingly, the 'review' control was determined not to be operating effectively. The control deficiency was posted to the SAD / CD/W log and the impact of the control deficiency on the audit strategy and planned audit procedures was evaluated.
G47: [테스트 결과 및 영향을 문서화] [Document testing results and impact]
B50: 필요한 경우, 감사팀에서 추가한 특정의 감사 절차 Additional engagement specific procedures, if necessary
B51: Procedures | F51: Results
B52: [필요한 경우, 추가적인 특정의 감사 절차를 문서화] [Document engagement specific additional procedures, if necessary] | F52: [추가 절차의 결과를 문서화] [Document results of additional procedures]
B56: Guidance (click + to expand):
B58: AUDIT GUIDE
B59: US PwC Audit 5400 - Determine nature, timing and extent of controls testing to be performed
B60: US PwC Audit (NP) 5400 - Determine nature, timing and extent of controls testing to be performed
B62: SMART GUIDANCE
C63: Testing of Review Controls
B65: GUIDANCE
B66: ● | C66: 질문 만으로는 특정 통제의 효과성에 대한 결론을 뒷받침하기에 충분하지 않을 것이다. 통제의 수행 시 사용되거나 통제 수행으로 인하여 생성된 보고서, 매뉴얼 또는 기타의 문서를 조사하여 추가적인 근거를 얻을 필요성이 있는지 고려한다. Inquiry alone will not provide sufficient evidence to support a conclusion about the effectiveness of a specific control. Consider the need to get further support by examining reports, manuals or other documents used in or generated by the performance of the control.
B68: ● | C68: 감사인이 관찰을 하고 있을 때의 통제는 감사인이 없을 때와 같은 방식으로 수행되지 않을 것이다. 게다가, 관찰은 단지 특정 시점에만 해당된다. 특정 기간 동안의 통제의 운영에 대한 충분한 증거를 입수하기 위해, 통제의 여러 instance에 대해 관찰을 수행하거나 세부적인 질문이나 문서 조사와 같은 추가적인 테스트 방법과 조합하여 관찰을 수행할 것을 고려한다. The control being observed might not be performed in the same manner when the auditors are not present. In addition, observation is pertinent only at a point in time. Consider performing observation of multiple instances of the control, or combining observation with additional testing methods, such as detailed inquiry or inspection of documentation, to gain further evidence about the operation of the control over the period.
B71: ● | C71: 특정 시점의 통제에 대한 검사 또는 재수행을 수행할 때, 감사 기간에 걸쳐 통제가 효과적으로 운영되는지에 대한 충분한 감사 증거를 입수할 방법을 고려한다. (예를 들어, ITGC, 변경이 없다는 기타 증거 등) When inspecting or reperforming the control at a point in time, consider how to obtain sufficient evidence that a control is operating effectively throughout the audit period (e.g., ITGCs, other evidence of no change, etc.).
B73: ● | C73: 'Review' 통제는 특정한 통제 목적을 달성하기 위하여 개인이 정보를 다양한 방식으로 검토하는 통제이다. (예를 들어, 가격 마스터파일에 대한 변경내역 검토, 차이조정에 대한 검토 등) Direct entity level control(direct ELC) 및 일부 'review' 통제의 경우, 운영 효과성에 대한 테스트는 경영진의 설명 및 통제 실행의 결론의 합리성과 정확성에 대한 증거를 제공하고, 질문, 회의 참석, 승인(서명)에 대한 검사 및 입수한 설명에 대한 단순한 문서화를 넘어서는 충분한 증거를 포함해야 한다. 가능한 감사 증거 원천의 예시는 다음을 포함한다: A 'review' control is any control where an individual performs some type of review of information to accomplish a particular control objective (e.g., review of pricing master file changes; review of reconciliations, et al.). For direct entity-level controls and certain 'review' controls, the testing of operating effectiveness should corroborate the reasonableness and accuracy of management's explanations and conclusions resulting from their execution of the control, and/or obtain sufficient evidence that goes beyond inquiry, attendance at meetings, inspection of sign-offs, and mere documentation that explanations were obtained. Examples of potential evidence sources include:
C77: - | D77: 설계된 바와 같이 후속절차가 수행될 항목들이 식별됨 Matters for follow-up are identified, as designed
C78: - | D78: 설계된 바와 같이 후속절차/investigation이 적절하게 수행됨 Foll0w-up / investigation is performed appropriately, as designed
C79: - | D79: 설계된 바와 같이 investigation 대상 항목들이 적절하게 해결됨 Items investigated are appropriately resolved, as designed
C80: - | D80: 경영진이 통제에 사용된 데이터가 목적에 맞게 충분히 신뢰할 만한 것임을 증명할 수 있도록, 이의 신뢰성에 대해 효과적인 통제를 가지고 있음 Management has effective controls over the reliability of data used in the control to verify such data is sufficiently reliable for that purpose
B81: ● | C81: 관련 application이 정확하고 신뢰성있는 정보(즉, standing data)를 이용하는지 여부를 고려한다. 필요한 경우, 데이터의 신뢰성(즉, 완전성, 정확성과 유효성)에 대한 증거를 입수하기 위한 추가적인 절차를 고려한다. Consider whether the application draws upon accurate and reliable data (i.e. standing data). To the extent necessary, consider additional procedures to obtain evidence of the reliability of the data (i.e. completeness, accuracy and validity).
B83: ● | C83: 예외사항이 식별되는 경우, 예외사항의 잠재적 결과를 이해하기 위해 질문하고 다음을 결정한다: When exceptions are identified, make inquiries to understand their potential consequences and determine whether:
C84: - | D84: 수행된 통제 테스트가 통제에 의존하기 위한 적절한 근거를 제공하는지, the tests of controls that have been performed provide an appropriate basis for reliance on the controls,
C85: - | D85: 추가적인 통제 테스트가 필요한지, additional tests of controls are necessary,
C86: - | D86: 왜곡표시 위험에 대응하는 대체적 절차가 요구되는지, risks of misstatement need to be addressed using alternative procedures,
C87: - | D87: 예외사항이 내부통제의 유의한 미비점(US GAAS의 경우에는 material weakness도 포함)에 해당하는지. (이러한 예외사항은 significant matter로 문서화되어야 함) exceptions represent a significant deficiency (as well as material weakness under US GAAS) in internal control (that should be documented as a Significant matter).

Sheet Master Test Plan
B1: Prior year control testing documentation rolled forward for reference purposes.
B2: 'Review' 통제 테스트 Template 'Review' Control Testing Template
B3: 'Review' 통제는 통상적으로 하나가 아닌 여러 개의 활동으로 구성됨. 감사팀의 'Review' 통제 조서는 각각의 중요한 통제 활동을 포함하여야 함. 단순한 서명, 회의가 개최되었다는 증거 그리고/또는 문서에 대한 상위 수준의 조사에 대한 문서검사는, 'review' 통제의 운영 효과성에 대한 감사 증거로 충분하지 않음. ''Review' controls typically are not a single activity but instead comprise multiple activities. Our documentation for a 'review' control should include each key control activity. The mere inspection of sign-offs, evidence of meetings occurring, and/or high level examination of documents is not sufficient audit evidence of the operating effectiveness of a 'review' control.
B4: 통제 번호 Control #
B5: 통제의 내용 Control description
B6: 누가 통제를 수행하는가? Who performs the control
B7: 통제의 위험 (통합감사의 경우 필수) Risk of the control (optional for non-public)
B8: 성격, 시기 및 범위에 대한 계획(최종 LSPM으로부터) Planned nature, timing and extent (from the final LSPM)
B9: 대상 기간 Coverage date
B10: Roll-forward 테스트 전략 Roll-forward testing strategy
B12: 1) 테스트 모집단을 결정 1) Determine the population(s) for testing
B13: 샘플을 선정하고 결론을 도출할 모집단을 식별 Identify the population from which to select the sample and about which to draw conclusions
B15: 모집단 완전성을 판단하기 위하여 수행한 절차 Procedures performed to determine the population is complete
B17: 2) 통제 활동의 빈도 및 계획한 감사증거 수준에 따라 테스트할 기간의 개수 결정 2) Determine the number of periods to test based on the frequency of the control and the desired level of evidence | G17: (US PwC Audit 5400)
B18: 통제의 빈도 Frequency of control
B19: 통제 활동의 빈도 및 계획한 감사증거 수준에 따른 테스트 대상 기간 수 Number of periods to test based on the frequency of the control and the desired level of evidence
B21: 3) 각 기간에 대하여 테스트할 통제 활동의 instance 개수 결정 3) Determine the number of instances of the control to test for each period
B22: 각 모집단의 각 기간에 수행되는 통제 활동의 instance 개수 Number of instances the control operates during each period for each population
B24: 설계 요소 (링크를 포함하지 않아야 함) (A) Design Attributes (this should not include links) (A) | F24: 운영 효과성 테스트 계획 Operating Effectiveness Testing Plan
B25: 세부 통제활동 번호 Detailed Control Activity # | C25: 해당 통제 활동의 목적은 무엇인가? (즉, 통제 운영자가 동 통제 활동을 통해 달성하고자 하는 것이 무엇인가) 하단 "Note 1" 참고. What is the objective of the control activity (i.e., what is reviewer expected to accomplish for this control activity)? See "Note 1" below. | D25: 검토자가 통제 활동의 목적을 어떻게 달성하는가? (즉, 검토자가 정확하게 무엇을, 얼마나 정밀한 수준에서 수행하는가) 하단 "Note 2" 참조 How does the reviewer accomplish the objective of this control activity (i.e, what exactly does the reviewer do and at what level of precision)? See "Note 2" below. | E25: 해당되는 경우, 이 통제의 실행에 사용되는 회사 작성 정보(예를 들어, key report)는 무엇이고 이 정보의 원천는 무엇인가? What company-produced information (e.g., key report), if any, is used in the execution of this control activity and what is the source of this information? | F25: 이 통제 활동의 운영에 사용된 회사 작성 정보에 대하여, 이러한 정보의 완전성과 정확성에 대한 감사 증거를 제공하는 절차 수행 계획을 기재. (B) For company-produced information used in the operation of this control activity, describe the plan to perform procedures that provide evidence of the completeness and accuracy of that information. (B) | G25: 질문 (해당되는 경우) Inquiry (if applicable) | H25: 문서 검사 (해당되는 경우) Inspection (if applicable) | I25: 관찰 (해당되는 경우) Observation (if applicable) | J25: 재수행 (해당되는 경우) Reperformance (if applicable)
G26: 이 통제 활동과 관련한 질문 절차 수행 계획을 기재(질문만으로는 운영 효과성과 관련된 결론을 뒷받침하기에 충분하지 않음에 유의)(C) Describe the plan to perform inquiry procedures related to this control activity (Reminder - inquiry alone is not sufficient to support conclusion regarding operating effectiveness)(C) | H26: 문서검사 절차 수행 계획 및 입수할 감사증거의 세부 내역을 기재(각 기간의 테스트 항목 개수, 관련된 선정 기준 포함)(C) Describe the plan to perform inspection procedures and the expected evidence to be obtained, including the number of items to be tested for each period and the related basis of selection (C) | I26: 관찰 절차 수행 계획 및 입수할 감사증거의 세부 내역을 기재(각 기간의 테스트 항목 개수, 관련된 선정 기준 포함)(C) Describe the plan to perform observation procedures and the expected evidence to be obtained, including the number of items to be tested for each period and the related basis of selection (C) | J26: 통제활동에 대한 재수행 계획 및 입수할 감사증거의 세부 내역을 기재(각 기간의 테스트 항목 개수, 관련된 선정 기준 포함)(C) Describe the plan to reperform the control activity and the expected evidence to be obtained, including the number of items to be tested for each period and the related basis of selection(C) | K26: 실증 테스트와 함께 dual purpose test 감사 증거를 입수하기 위한 절차인가? (예/아니오)(D) Procedures intended for substantive testing dual purpose evidence (Yes / No)(D) | L26: 해당되는 경우, dual purpose test 조서에 대한 링크를 첨부 Link to dual purpose testing (if applicable)
B27: 1
B30: 2
B33: 3 (E)
B38: Note 1 | C38: 왜곡표시를 예방하거나 적발하는 절차는 일반적으로 단순히 차이점을 파악하고 설명하는 절차보다 더 정밀함. 통제 목적 및 개별 통제 활동의 설계에 대한 세부 이해를 바탕으로 이 review 통제의 설계 평가에 대한 결론을 내릴 때, 감사팀은 이 통제가 관련된 LSPM(EGA 'Identify risk and understand controls in the business process' 또는 'Identify risks and understand controls in the period-end financial reporting process'의 LSPM template에 문서화된)에 대응하는지 재확인하여야 함. A procedure that functions to prevent or detect misstatements generally is more precise than a procedure that merely identifies and explains differences. In finalizing the assessment of the design of this review control (based on a detailed understanding of the objective and design of individual control activities), we should reconfirm that the control is responsive to the LSPMs to which is it linked (in the LSPM template(s) within the EGA Identify risk and understand controls in the business process or Identify risks and understand controls in the period-end financial reporting process).
B42: Note 2 | C42: 이 질문에 대하여, 다음에 대한 고려사항을 문서화: - 세분화 수준: 보다 세분화된 수준에서 수행되는 통제가 상위 수준에서 수행되는 통제보다 일반적으로 더 정교함; - 수행의 일관성: 정기적으로 일관성있게 수행되는 통제는 산발적으로 수행되는 통제보다 일반적으로 더 정교함; - Investigation 기준: 언제 후속조치/조사가 수행되는지에 대한 지침을 제공하는 세부적인 기준/thresholds는 통제의 설계 및 정교함과 관련된 중요한 요소임; - 기대치의 예측가능성: 통제의 효과성이 잠재적인 중요한 왜곡표시를 드러낼 수 있는 충분히 정확한 예측치 도출에 의존하는 정도. When responding \to this question, document consideration of the following: - Level of aggregation: A control that is performed at a more granular level generally is more precise than one performed at a higher level; - Consistency of performance: A control that is performed routinely and consistently generally is more precise than one performed sporadically; - Criteria for investigation: The specifics of the criteria and/or thresholds used to guide when follow-up/investigation is to be performed are an important element of the design and precision of controls; - Predictability of expectations: The extent to which effectiveness of the control depends on development of sufficiently precise expectations to highlight potential material misstatements.
B49: (A) | C49: 일부 설계에 대한 정보가 EGA 'Identify risk and understand controls in the business process' 또는 'Identify risks and understand controls in the period-end financial reporting process'에서 이미 파악될 수 있지만, 이 설계 평가에서는 개별 통제활동과 테스트 절차 계획을 명확하게 연결하는 것이 중요함. 따라서 이 양식을 작성할 때, DB의 다른 영역에 링크하기 보다는 다양한 부분에 대한 설명을 기재. While some of the design information may have already been captured in the EGA Identify risks and understand controls in the business process or Identify risks and understand controls in the period-end financial reporting process, it is important for this design assessment to clearly document the link between the individual control activities and the planned testing procedures. Accordingly, when completing this template provide descriptions within the various sections instead of creating links to other areas in the database.
B52: (B) | C52: 통합감사에서, 이 테스트는 경영진이 통제의 운영에 사용된 데이터가 의도된 목적과 관련하여 신뢰할 수 있는지(즉, 완전하고 정확한지)에 대하여 어떻게 확신을 얻는지에 초점을 맞춰야 함. 재무제표에 대한 감사 만을 수행하는 경우, 회사 작성 정보의 완전성과 정확성과 관련된 감사 증거는 적합한 실증 절차 수행에 의하여 입수될 수도 있음. In an integrated audit, this testing should be focused on testing how management ensures the data used in the operation of the control is reliable (i.e., it is complete and accurate) for the intended purpose. In a financial statement-only audit, evidence regarding the completeness and accuracy of company-produced information can also be obtained by performing appropriate substantive procedures.
B55: (C) | C55: 만약 통제 활동에 대하여 상기 열이 추가/삭제되는 경우, 해당 통제활동 탭에 대해서 수동으로 추가/삭제되어야 함. If rows are added/deleted above for control activities they will need to be manually added/deleted to the corresponding control activity tab.
B56: (D) | C56: Dual purpose test 감사 증거를 제공하기 위한 실증 절차를 계획하는 경우, 특정 실증 절차가 어떻게 관련 통제 목적에 대응하고 통제 활동의 효과적인 실행을 뒷받침하는 증거를 제공하는지에 대한 테스트 계획을 명확하게 확인함. If substantive procedures are intended to provide dual purpose evidence, confirm that the test plan is clear as to how specific substantive procedures address the applicable control objective and provide evidence supporting effective execution of the control activity.
B58: (E) | C58: Detailed Control Activity를 추가하기 위하여 이 행을 복사하여 추가할 수 있음. 탭을 추가하려면 "Add Control Activity tab" 버튼을 사용. 추가된 탭에는 이 탭의 정보가 채워져있지 않으며, 수동으로 링크하여야 함. This line can be copied to add additional Detailed Control Activities. Use the button "Add Control Activity tab" to add additional tabs. Additional tabs will not be prepopulated with the information on this tab and will need to be linked manually.

Sheet First Test Plan
B1: Prior year control testing documentation rolled forward for reference purposes.
B2: 'Review' 통제 테스트 Template 'Review' Control Testing Template
B3: 'Review' 통제는 통상적으로 하나가 아닌 여러 개의 활동으로 구성됨. 감사팀의 'Review' 통제 조서는 각각의 중요한 통제 활동을 포함하여야 함. 단순한 서명, 회의가 개최되었다는 증거 그리고/또는 문서에 대한 상위 수준의 조사에 대한 문서검사는, 'review' 통제의 운영 효과성에 대한 감사 증거로 충분하지 않음. 'Review' controls typically are not a single activity but instead comprise multiple activities. Our documentation for a 'review' control should include each key control activity. The mere inspection of sign-offs, evidence of meetings occurring, and/or high level examination of documents is not sufficient audit evidence of the operating effectiveness of a 'review' control.
B4: 통제 번호 Control #
B5: 통제의 내용 Control description
B6: 누가 통제를 수행하는가? Who performs the control
B7: 통제의 위험 (통합감사의 경우 필수) Risk of the control (optional for non-public)
B8: 성격, 시기 및 범위에 대한 계획(최종 LSPM으로부터) Planned nature, timing and extent (from the final LSPM)
B9: 대상 기간 Coverage date
B10: Roll-forward 테스트 전략 Roll-forward testing strategy
B12: 1) 테스트 모집단을 결정 1) Determine the population(s) for testing
B13: 샘플을 선정하고 결론을 도출할 모집단을 식별 Identify the population from which to select the sample and about which to draw conclusions
B15: 모집단 완전성을 판단하기 위하여 수행한 절차 Procedures performed to determine the population is complete
B17: 2) 통제 활동의 빈도 및 계획한 감사증거 수준에 따라 테스트할 기간의 개수 결정 2) Determine the number of periods to test based on the frequency of the control and the desired level of evidence | G17: (US PwC Audit 5400)
B18: 통제의 빈도 Frequency of control
B19: 통제 활동의 빈도 및 계획한 감사증거 수준에 따른 테스트 대상 기간 수 Number of periods to test based on the frequency of the control and the desired level of evidence
B21: 3) 각 기간에 대하여 테스트할 통제 활동의 instance 개수 결정 3) Determine the number of instances of the control to test for each period
B22: 각 모집단의 각 기간에 수행되는 통제 활동의 instance 개수 Number of instances the control operates during each period for each population
B24: 설계 요소 (링크를 포함하지 않아야 함) (A) Design Attributes (this should not include links) (A) | F24: 운영 효과성 테스트 계획 Operating Effectiveness Testing Plan
B25: 세부 통제활동 번호 Detailed Control Activity # | C25: 해당 통제 활동의 목적은 무엇인가? (즉, 통제 운영자가 동 통제 활동을 통해 달성하고자 하는 것이 무엇인가) 하단 "Note 1" 참고. What is the objective of the control activity (i.e., what is reviewer expected to accomplish for this control activity)? See "Note 1" below. | D25: 검토자가 통제 활동의 목적을 어떻게 달성하는가? (즉, 검토자가 정확하게 무엇을, 얼마나 정밀한 수준에서 수행하는가) 하단 "Note 2" 참조 How does the reviewer accomplish the objective of this control activity (i.e, what exactly does the reviewer do and at what level of precision)? See "Note 2" below. | E25: 해당되는 경우, 이 통제의 실행에 사용되는 회사 작성 정보(예를 들어, key report)는 무엇이고 이 정보의 원천는 무엇인가? What company-produced information (e.g., key report), if any, is used in the execution of this control activity and what is the source of this information? | F25: 이 통제활동의 운영에 사용된 회사제공정보에 대하여 해당 정보의 완전성과 정확성을 증명할 절차 수행 계획을 설명한다. (B) For company-produced information used in the operation of this control activity, describe the plan to perform procedures that provide evidence of the completeness and accuracy of that information. (B) | G25: 질문 (해당되는 경우) Inquiry (if applicable) | H25: 문서 검사 (해당되는 경우) Inspection (if applicable) | I25: 관찰 (해당되는 경우) Observation (if applicable) | J25: 재수행 (해당되는 경우) Reperformance (if applicable)
G26: 이 통제 활동과 관련한 질문 절차 수행 계획을 기재(질문만으로는 운영 효과성과 관련된 결론을 뒷받침하기에 충분하지 않음에 유의)(C) Describe the plan to perform inquiry procedures related to this control activity (Reminder - inquiry alone is not sufficient to support conclusion regarding operating effectiveness)(C) | H26: 문서검사 절차 수행 계획 및 입수할 감사증거의 세부 내역을 기재(각 기간의 테스트 항목 개수, 관련된 선정 기준 포함)(C) Describe the plan to perform inspection procedures and the expected evidence to be obtained, including the number of items to be tested for each period and the related basis of selection (C) | I26: 관찰 절차 수행 계획 및 입수할 감사증거의 세부 내역을 기재(각 기간의 테스트 항목 개수, 관련된 선정 기준 포함)(C) Describe the plan to perform observation procedures and the expected evidence to be obtained, including the number of items to be tested for each period and the related basis of selection (C) | J26: 통제활동에 대한 재수행 계획 및 입수할 감사증거의 세부 내역을 기재(각 기간의 테스트 항목 개수, 관련된 선정 기준 포함)(C) Describe the plan to reperform the control activity and the expected evidence to be obtained, including the number of items to be tested for each period and the related basis of selection(C) | K26: 실증 테스트와 함께 dual purpose test 감사 증거를 입수하기 위한 절차인가? (예/아니오)(D) Procedures intended for substantive testing dual purpose evidence (Yes / No)(D) | L26: 해당되는 경우, dual purpose test 조서에 대한 링크를 첨부 Link to dual purpose testing (if applicable)
B27: 1
B30: 2
B33: 3 (E)
B38: Note 1 | C38: 왜곡표시를 예방하거나 적발하는 절차는 일반적으로 단순히 차이점을 파악하고 설명하는 절차보다 더 정밀함. 통제 목적 및 개별 통제 활동의 설계에 대한 세부 이해를 바탕으로 이 review 통제의 설계 평가에 대한 결론을 내릴 때, 감사팀은 이 통제가 관련된 LSPM(EGA 'Identify risk and understand controls in the business process' 또는 'Identify risks and understand controls in the period-end financial reporting process'의 LSPM template에 문서화된)에 대응하는지 재확인하여야 함. A procedure that functions to prevent or detect misstatements generally is more precise than a procedure that merely identifies and explains differences. In finalizing the assessment of the design of this review control (based on a detailed understanding of the objective and design of individual control activities), we should reconfirm that the control is responsive to the LSPMs to which is it linked (in the LSPM template(s) within the EGA Identify risk and understand controls in the business process or Identify risks and understand controls in the period-end financial reporting process).
B42: Note 2 | C42: 이 질문에 대하여, 다음에 대한 고려사항을 문서화: - 세분화 수준: 보다 세분화된 수준에서 수행되는 통제가 상위 수준에서 수행되는 통제보다 일반적으로 더 정교함; - 수행의 일관성: 정기적으로 일관성있게 수행되는 통제는 산발적으로 수행되는 통제보다 일반적으로 더 정교함; - Investigation 기준: 언제 후속조치/조사가 수행되는지에 대한 지침을 제공하는 세부적인 기준/thresholds는 통제의 설계 및 정교함과 관련된 중요한 요소임; - 기대치의 예측가능성: 통제의 효과성이 잠재적인 중요한 왜곡표시를 드러낼 수 있는 충분히 정확한 예측치 도출에 의존하는 정도. When responding \to this question, document consideration of the following: - Level of aggregation: A control that is performed at a more granular level generally is more precise than one performed at a higher level; - Consistency of performance: A control that is performed routinely and consistently generally is more precise than one performed sporadically; - Criteria for investigation: The specifics of the criteria and/or thresholds used to guide when follow-up/investigation is to be performed are an important element of the design and precision of controls; - Predictability of expectations: The extent to which effectiveness of the control depends on development of sufficiently precise expectations to highlight potential material misstatements.
B49: (A) | C49: 일부 설계에 대한 정보가 EGA 'Identify risk and understand controls in the business process' 또는 'Identify risks and understand controls in the period-end financial reporting process'에서 이미 파악될 수 있지만, 이 설계 평가에서는 개별 통제활동과 테스트 절차 계획을 명확하게 연결하는 것이 중요함. 따라서 이 양식을 작성할 때, DB의 다른 영역에 링크하기 보다는 다양한 부분에 대한 설명을 기재. While some of the design information may have already been captured in the EGA Identify risks and understand controls in the business process or Identify risks and understand controls in the period-end financial reporting process, it is important for this design assessment to clearly document the link between the individual control activities and the planned testing procedures. Accordingly, when completing this template provide descriptions within the various sections instead of creating links to other areas in the database.
B52: (B) | C52: 통합감사에서, 이 테스트는 경영진이 통제의 운영에 사용된 데이터가 의도된 목적과 관련하여 신뢰할 수 있는지(즉, 완전하고 정확한지)에 대하여 어떻게 확신을 얻는지에 초점을 맞춰야 함. 재무제표에 대한 감사 만을 수행하는 경우, 회사 작성 정보의 완전성과 정확성과 관련된 감사 증거는 적합한 실증 절차 수행에 의하여 입수될 수도 있음. In an integrated audit, this testing should be focused on testing how management ensures the data used in the operation of the control is reliable (i.e., it is complete and accurate) for the intended purpose. In a financial statement-only audit, evidence regarding the completeness and accuracy of company-produced information can also be obtained by performing appropriate substantive procedures.
B55: (C) | C55: 만약 통제 활동에 대하여 상기 행이 추가/삭제되는 경우, 해당 통제활동 탭에 대해서 수동으로 추가/삭제되어야 함. If rows are added/deleted above for control activities they will need to be manually added/deleted to the corresponding control activity tab.
B56: (D) | C56: Dual purpose test 감사 증거를 제공하기 위한 실증 절차를 계획하는 경우, 특정 실증 절차가 어떻게 관련 통제 목적에 대응하고 통제 활동의 효과적인 실행을 뒷받침하는 증거를 제공하는지에 대한 테스트 계획을 명확하게 확인함. If substantive procedures are intended to provide dual purpose evidence, confirm that the test plan is clear as to how specific substantive procedures address the applicable control objective and provide evidence supporting effective execution of the control activity.
B58: (E) | C58: Detailed Control Activity를 추가하기 위하여 이 행을 복사하여 추가할 수 있음. 탭을 추가하려면 "Add Control Activity tab" 버튼을 사용. 추가된 탭에는 이 탭의 정보가 채워져있지 않으며, 수동으로 링크하여야 함. This line can be copied to add additional Detailed Control Activities. Use the button "Add Control Activity tab" to add additional tabs. Additional tabs will not be prepopulated with the information on this tab and will need to be linked manually.

Sheet Control Activity-1 - v2013
B1: Prior year control testing documentation rolled forward for reference purposes.
B2: 운영효과성에 대한 테스트 - 통제활동 1 Operating Effectiveness Testing - Control Activity-1
B3: Note: 각 통제 활동에 대하여 별도의 테스트 탭을 생성하여야 함 Note: A separate testing tab should be created for each control activity
B4: 통제 활동의 내용 [검토자가 통제 활동의 목적을 어떻게 달성하는가? (즉, 검토자가 정확하게 무엇을, 얼마나 정밀한 수준에서 수행하는가)] Control Activity Description [How does the reviewer accomplish the objective of this control activity (i.e, what exactly does the reviewer do and at what level of precision)?] | F4: ='First Test Plan'!D27 -> 0
B6: 4) 선택한 통제 활동의 instance를 테스트 4) Test the control instances selected
B7: 회사 작성 정보(예를 들어, key report)에 대한 테스트 절차 및 그러한 절차의 결과에 대해 문서화 비고: 통합감사에서, 이 테스트는 경영진이 통제의 운영에 사용된 데이터가 의도된 목적과 관련하여 신뢰할 수 있는지(즉, 완전하고 정확한지)에 대하여 어떻게 확신을 얻는지에 초점을 맞춰야 함. 재무제표에 대한 감사 만을 수행하는 경우, 회사 작성 정보의 완전성과 정확성과 관련된 감사 증거는 적합한 실증 절차 수행에 의하여 입수될 수도 있음. Document testing procedures performed over company-produced information (e.g., key report) and results of those procedures Note: In an integrated audit, this testing should be focused on testing how management ensures the data used in the operation of the control is reliable (i.e., it is complete and accurate) for the intended purpose. In a financial statement-only audit, evidence regarding the completeness and accuracy of company-produced information can also be obtained by performing appropriate substantive procedures.
D8: 운영효과성에 대한 테스트 계획 Operating Effectiveness Testing Plan | E8: [대상기간 기재]에 대한 테스트 결과 (A) Testing Results for [insert period] (A) | F8: 예외사항 Exception(s) | G8: [대상기간 기재]에 대한 테스트 결과 (A)(B) Testing Results for [insert period] (A)(B) | H8: 예외사항 Exception(s)
B9: 질문 절차 Inquiry Procedure(s) | D9: ='First Test Plan'!G27 -> 0
D10: ='First Test Plan'!G28 -> 0
D11: ='First Test Plan'!G29 -> 0
B12: 문서검사 절차 Inspection Procedure(s) | D12: ='First Test Plan'!H27 -> 0
D13: ='First Test Plan'!H28 -> 0
D14: ='First Test Plan'!H29 -> 0
B15: 관찰 절차 Observation Procedures(s) | D15: ='First Test Plan'!I27 -> 0
D16: ='First Test Plan'!I28 -> 0
D17: ='First Test Plan'!I29 -> 0
B18: 재수행 절차 Reperformance Procedure(s) | D18: ='First Test Plan'!J27 -> 0
D19: ='First Test Plan'!J28 -> 0
D20: ='First Test Plan'!J29 -> 0
B22: 5) 통제 활동이 효과적으로 운영되었음을 반영하는 기타의 감사 증거가 있다면, 이를 어떻게 고려하였는지 문서화 (예를 들어, 분기 검토 중 잠재적인 왜곡표시나 예외사항이 통제 활동에 의해 적절히 발견되고 적시에 수정되었다는 증거가 존재하는지?) 5) Document consideration of other evidence, if any, that reflects positively on the operating effectiveness of the control activity (For example, during a quarterly review, is there evidence that potential misstatements or exceptions were appropriately detected by the control and timely corrected?)
B25: 6) 통제 활동이 효과적으로 운영되지 않음을 반영되는 기타의 감사 증거가 있다면, 이를 어떻게 고려하였는지 문서화 (예를 들어, 통제 활동에 의하여 적발되고 해결되었어야 하나 그러지 않은 왜곡표시나 예외사항(기간 외 조정 포함)이 존재하는지?) 6) Document consideration of evidence, if any, that reflects negatively on the operating effectiveness of the control activity (For example, have there been misstatements or other exceptions, including out of period adjustments, that should have been detected and resolved by the control but were not?)
B28: (A) | C28: 통제 활동에 investigation 기준이나 thresholds가 포함되는 경우, 테스트 계획에 확인할 후속조치의 개수에 대한 고려 뿐만 아니라 경영진이 통제 활동의 설계와 일관성있게 후속조치 및 investigation 항목을 모두 적절히 식별하였는지 여부를 판단하기 위한 절차가 포함되었는지 확인. 'Review' 통제의 설계, 성격 및 빈도에 따라서, "Management Follow-up Items" 및 "Detailed Testing Table" 탭이 필요할 수 있음. In situations where the control includes criteria and/or thresholds for items being investigated, ensure the plan includes consideration for the number of follow-ups to corroborate as well as procedures to determine whether management appropriately identified all items for follow up and investigation consistent with the design of the control. The tabs “Mgmt Follow-up Items” and “Detailed Testing Table” may be needed based upon the design, nature and frequency of the ‘review’ control.
B32: (B) | C32: 테스트 대상 기간을 추가하려면, "Testing Results" 및 "Exception(s)" 열을 추가함. Add "Testing Results" and "Exception(s)" columns for additional periods tested.

Sheet Control Activity-2 - v2013
B1: Prior year control testing documentation rolled forward for reference purposes.
B2: 운영효과성에 대한 테스트 - 통제활동 2 Operating Effectiveness Testing - Control Activity-2
B3: Note: 각 통제 활동에 대하여 별도의 테스트 탭을 생성하여야 함 Note: A separate testing tab should be created for each control activity
B4: 통제 활동의 내용 [검토자가 통제 활동의 목적을 어떻게 달성하는가? (즉, 검토자가 정확하게 무엇을, 얼마나 정밀한 수준에서 수행하는가)] Control Activity Description [How does the reviewer accomplish the objective of this control activity (i.e, what exactly does the reviewer do and at what level of precision)?] | F4: ='First Test Plan'!D30 -> 0
B6: 4) 선택한 통제 활동의 instance를 테스트 4) Test the control instances selected
B7: 회사 작성 정보(예를 들어, key report)에 대한 테스트 절차 및 그러한 절차의 결과에 대해 문서화 비고: 통합감사에서, 이 테스트는 경영진이 통제의 운영에 사용된 데이터가 의도된 목적과 관련하여 신뢰할 수 있는지(즉, 완전하고 정확한지)에 대하여 어떻게 확신을 얻는지에 초점을 맞춰야 함. 재무제표에 대한 감사 만을 수행하는 경우, 회사 작성 정보의 완전성과 정확성과 관련된 감사 증거는 적합한 실증 절차 수행에 의하여 입수될 수도 있음. Document testing procedures performed over company-produced information (e.g., key report) and results of those procedures Note: In an integrated audit, this testing should be focused on testing how management ensures the data used in the operation of the control is reliable (i.e., it is complete and accurate) for the intended purpose. In a financial statement-only audit, evidence regarding the completeness and accuracy of company-produced information can also be obtained by performing appropriate substantive procedures.
D8: 운영효과성에 대한 테스트 계획 Operating Effectiveness Testing Plan | E8: [대상기간 기재]에 대한 테스트 결과 (A) Testing Results for [insert period] (A) | F8: 예외사항 Exception(s) | G8: [대상기간 기재]에 대한 테스트 결과 (A)(B) Testing Results for [insert period] (A)(B) | H8: 예외사항 Exception(s)
B9: 질문 절차 Inquiry Procedure(s) | D9: ='First Test Plan'!G30 -> 0
D10: ='First Test Plan'!G31 -> 0
D11: ='First Test Plan'!G32 -> 0
B12: 문서검사 절차 Inspection Procedure(s) | D12: ='First Test Plan'!H30 -> 0
D13: ='First Test Plan'!H31 -> 0
D14: ='First Test Plan'!H32 -> 0
B15: 관찰 절차 Observation Procedures(s) | D15: ='First Test Plan'!I30 -> 0
D16: ='First Test Plan'!I31 -> 0
D17: ='First Test Plan'!I32 -> 0
B18: 재수행 절차 Reperformance Procedure(s) | D18: ='First Test Plan'!J30 -> 0
D19: ='First Test Plan'!J31 -> 0
D20: ='First Test Plan'!J32 -> 0
B22: 5) 통제 활동이 효과적으로 운영되었음을 반영하는 기타의 감사 증거가 있다면, 이를 어떻게 고려하였는지 문서화 (예를 들어, 분기 검토 중 잠재적인 왜곡표시나 예외사항이 통제 활동에 의해 적절히 발견되고 적시에 수정되었다는 증거가 존재하는지?) 5) Document consideration of other evidence, if any, that reflects positively on the operating effectiveness of the control activity (For example, during a quarterly review, is there evidence that potential misstatements or exceptions were appropriately detected by the control and timely corrected?)
B25: 6) 통제 활동이 효과적으로 운영되지 않음을 반영되는 기타의 감사 증거가 있다면, 이를 어떻게 고려하였는지 문서화 (예를 들어, 통제 활동에 의하여 적발되고 해결되었어야 하나 그러지 않은 왜곡표시나 예외사항(기간 외 조정 포함)이 존재하는지?) 6) Document consideration of evidence, if any, that reflects negatively on the operating effectiveness of the control activity (For example, have there been misstatements or other exceptions, including out of period adjustments, that should have been detected and resolved by the control but were not?)
B28: (A) | C28: 통제 활동에 investigation 기준이나 thresholds가 포함되는 경우, 테스트 계획에 확인할 후속조치의 개수에 대한 고려 뿐만 아니라 경영진이 통제 활동의 설계와 일관성있게 후속조치 및 investigation 항목을 모두 적절히 식별하였는지 여부를 판단하기 위한 절차가 포함되었는지 확인. 'Review' 통제의 설계, 성격 및 빈도에 따라서, "Management Follow-up Items" 및 "Detailed Testing Table" 탭이 필요할 수 있음. In situations where the control includes criteria and/or thresholds for items being investigated, ensure the plan includes consideration for the number of follow-ups to corroborate as well as procedures to determine whether management appropriately identified all items for follow up and investigation consistent with the design of the control. The tabs “Mgmt Follow-up Items” and “Detailed Testing Table” may be needed based upon the design, nature and frequency of the ‘review’ control.
B32: (B) | C32: 테스트 대상 기간을 추가하려면, "Testing Results" 및 "Exception(s)" 열을 추가함. Add "Testing Results" and "Exception(s)" columns for additional periods tested.

Sheet Master Control Activity v2013
B1: Prior year control testing documentation rolled forward for reference purposes.
B2: 운영효과성에 대한 테스트 - 통제활동-[x] Operating Effectiveness Testing - Control Activity-[x]
B3: Note: 각 통제 활동에 대하여 별도의 테스트 탭을 생성하여야 함 Note: A separate testing tab should be created for each control activity
B4: 통제 활동의 내용 [검토자가 통제 활동의 목적을 어떻게 달성하는가? (즉, 검토자가 정확하게 무엇을, 얼마나 정밀한 수준에서 수행하는가)] Control Activity Description [How does the reviewer accomplish the objective of this control activity (i.e, what exactly does the reviewer do and at what level of precision)?] | F4: [Summary Test Plan 탭의 링크를 삽입한다] [insert link from Summary Test Plan tab]
B6: 4) 선택한 통제 활동의 instance를 테스트 4) Test the control instances selected
B7: 회사 작성 정보(예를 들어, key report)에 대한 테스트 절차 및 그러한 절차의 결과에 대해 문서화 비고: 통합감사에서, 이 테스트는 경영진이 통제의 운영에 사용된 데이터가 의도된 목적과 관련하여 신뢰할 수 있는지(즉, 완전하고 정확한지)에 대하여 어떻게 확신을 얻는지에 초점을 맞춰야 함. 재무제표에 대한 감사 만을 수행하는 경우, 회사 작성 정보의 완전성과 정확성과 관련된 감사 증거는 적합한 실증 절차 수행에 의하여 입수될 수도 있음. Document testing procedures performed over company-produced information (e.g., key report) and results of those procedures Note: In an integrated audit, this testing should be focused on testing how management ensures the data used in the operation of the control is reliable (i.e., it is complete and accurate) for the intended purpose. In a financial statement-only audit, evidence regarding the completeness and accuracy of company-produced information can also be obtained by performing appropriate substantive procedures.
D8: 운영효과성에 대한 테스트 계획 Operating Effectiveness Testing Plan | E8: [대상기간 기재]에 대한 테스트 결과 (A) Testing Results for [insert period] (A) | F8: 예외사항 Exception(s) | G8: [대상기간 기재]에 대한 테스트 결과 (A)(B) Testing Results for [insert period] (A)(B) | H8: 예외사항 Exception(s)
B9: 질문 절차 Inquiry Procedure(s) | D9: [Summary Test Plan 탭의 링크를 삽입한다] [insert link from Summary Test Plan tab]
D10: [Summary Test Plan 탭의 링크를 삽입한다] [insert link from Summary Test Plan tab]
D11: [Summary Test Plan 탭의 링크를 삽입한다] [insert link from Summary Test Plan tab]
B12: 문서검사 절차 Inspection Procedure(s) | D12: [Summary Test Plan 탭의 링크를 삽입한다] [insert link from Summary Test Plan tab]
D13: [Summary Test Plan 탭의 링크를 삽입한다] [insert link from Summary Test Plan tab]
D14: [Summary Test Plan 탭의 링크를 삽입한다] [insert link from Summary Test Plan tab]
B15: 관찰 절차 Observation Procedures(s) | D15: [Summary Test Plan 탭의 링크를 삽입한다] [insert link from Summary Test Plan tab]
D16: [Summary Test Plan 탭의 링크를 삽입한다] [insert link from Summary Test Plan tab]
D17: [Summary Test Plan 탭의 링크를 삽입한다] [insert link from Summary Test Plan tab]
B18: 재수행 절차 Reperformance Procedure(s) | D18: [Summary Test Plan 탭의 링크를 삽입한다] [insert link from Summary Test Plan tab]
D19: [Summary Test Plan 탭의 링크를 삽입한다] [insert link from Summary Test Plan tab]
D20: [Summary Test Plan 탭의 링크를 삽입한다] [insert link from Summary Test Plan tab]
B22: 5) 통제 활동이 효과적으로 운영되었음을 반영하는 기타의 감사 증거가 있다면, 이를 어떻게 고려하였는지 문서화 (예를 들어, 분기 검토 중 잠재적인 왜곡표시나 예외사항이 통제 활동에 의해 적절히 발견되고 적시에 수정되었다는 증거가 존재하는지?) 5) Document consideration of other evidence, if any, that reflects positively on the operating effectiveness of the control activity (For example, during a quarterly review, is there evidence that potential misstatements or exceptions were appropriately detected by the control and timely corrected?)
B25: 6) 통제 활동이 효과적으로 운영되지 않음을 반영되는 기타의 감사 증거가 있다면, 이를 어떻게 고려하였는지 문서화 (예를 들어, 통제 활동에 의하여 적발되고 해결되었어야 하나 그러지 않은 왜곡표시나 예외사항(기간 외 조정 포함)이 존재하는지?) 6) Document consideration of evidence, if any, that reflects negatively on the operating effectiveness of the control activity (For example, have there been misstatements or other exceptions, including out of period adjustments, that should have been detected and resolved by the control but were not?)
B28: (A) | C28: 통제 활동에 investigation 기준이나 thresholds가 포함되는 경우, 테스트 계획에 확인할 후속조치의 개수에 대한 고려 뿐만 아니라 경영진이 통제 활동의 설계와 일관성있게 후속조치 및 investigation 항목을 모두 적절히 식별하였는지 여부를 판단하기 위한 절차가 포함되었는지 확인. 'Review' 통제의 설계, 성격 및 빈도에 따라서, "Management Follow-up Items" 및 "Detailed Testing Table" 탭이 필요할 수 있음. In situations where the control includes criteria and/or thresholds for items being investigated, ensure the plan includes consideration for the number of follow-ups to corroborate as well as procedures to determine whether management appropriately identified all items for follow up and investigation consistent with the design of the control. The tabs “Mgmt Follow-up Items” and “Detailed Testing Table” may be needed based upon the design, nature and frequency of the ‘review’ control.
B32: (B) | C32: 테스트 대상 기간을 추가하려면, "Testing Results" 및 "Exception(s)" 열을 추가함. Add "Testing Results" and "Exception(s)" columns for additional periods tested.

Sheet Master Follow-Up Items
B1: Prior year control testing documentation rolled forward for reference purposes.
B3: 테스트 대상으로 선정한 경영진의 후속조치 항목에 대한 테스트 - 통제 활동 [x] Testing of Management Follow-up Items Selected for Testing - Control Activity-[x]
B4: 이 탭은 통제의 운영 중 식별된 경영진의 후속조치가 요구되는 사항에 대한 감사팀의 테스트 절차 문서화에 사용되며, 'review' 통제의 설계, 성격 및 빈도에 따라서 이 탭의 사용이 필요할 수도 있고 필요하지 않을 수도 있음. 경영진이 통제 설계 상 정의된 investigation 기준에 해당하는 문제에 대하여 적절히 후속조치를 수행하고 이를 해결하였음을 확인하기 위하여 필요한 감사 증거의 범위에 대한 감사팀의 판단이 요구됨. Use of this tab may or may not be needed based upon the design, nature and frequency of the 'review' control and is used to document our testing procedures regarding items identified during the operation of the control requiring management follow-up. The engagement team will need to make judgments about the extent of evidence necessary to be satisfied that management appropriately followed-up and resolved matters meeting the criteria for investigation established in the design of the control.
B5: No. | C5: 경영진의 후속조치와 관련된 instance (예, 20xx년 2분기) Instance that management follow-up relates to (e.g., Q2 20xx) | D5: 테스트 대상으로 선정한 경영진의 후속조치 항목 Management follow-up items selected for testing | E5: 경영진의 후속조치가 통제활동의 설계 내용과 일관성이 있는지 확인하기 위하여 수행한 절차 Procedures performed to validate that management's follow-up was consistent with design of control activity | F5: 예외사항 Exceptions
B6: 1
B7: 2
B8: 3
B9: 4
B10: 5
B11: 6
B12: 7
B13: 8
B14: 9
B15: 10
B16: 11
B17: 12
... B35: 30

Sheet Master Review Procedures (4)
B1: Prior year control testing documentation rolled forward for reference purposes.
B2: 'Review' 통제를 테스트한다 Test 'Review' control
B3: 접근권한 (검토) - 접근권한 모니터링 - 애플리케이션, 데이터베이스/데이터 파일, 운영 시스템/네트워크에 대한 접근권한의 적정성은 주기적으로 모니터링된다 Access (Review) - Access monitoring - access rights to applications, database/data files, operating system/network are periodically monitored for appropriateness
B5: 2명 이상의 팀원이 동 EGA를 prepare한 경우, 관여한 팀원의 이름과 수행한 절차를 문서화. When more than one preparer was involved in the completion of this EGA, document the names of the team members involved and the procedures performed. | F5: [팀원의 이니셜/이름 및 수행한 절차를 문서화(예를 들어, 홍길동이 하단 a)절차를 수행)] [Document the initials or names of team members and procedures performed (e.g., Jane Doe performed step a) below)]
B8: Procedures | F8: Results | K8: Links
B9: a) | C9: 'Review' 통제 설계에 변경이 있는지 확인한다. Verify whether there have been changes to the design of the 'review' control. | G9: 'Review' 통제의 설계에 변경이 있는지 확인함, 그리고 Verified if there have been changes to the design of the 'review' control, and
H10: 'Review' 통제 설계에서 변경사항이 파악되지 않음, 또는 No changes were noted in the design of the 'review' control, or
H11: 'Review' 통제 설계에 변경사항이 파악됨. Changes were noted in the design of the 'review' control.
G12: [필요한 경우, 수행한 절차와 변경사항을 문서화] [Document procedures performed and changes, as necessary]
F13: 그리고 AND
G14: 'Review' 통제의 설계를 평가함, 그리고 Evaluated the design of the 'review' control, and
H15: 통제가 효과적으로 설계되었다고 판단함, 또는 Concluded the control is designed effectively, or
H16: 통제가 효과적으로 설계되어 있지 않다고 판단하여, 식별된 미비점을 SAD에 기록하고 해당 업무프로세스의 영향을 받는 FSLI에 대한 감사 계획을 고려함. Concluded the control is not designed effectively, and posted the identified deficiency to the SAD and considered the planned audit procedures for the FSLIs impacted by the business process.
G19: [영향을 받는 FSLI에 대한 감사 계획을 평가한 세부 내용을 문서화] [Document details of evaluation of planned audit procedures for impacted FSLIs]
B22: b) | C22: 'Review' 통제를 테스트하기 위한 계획을 수립한다. Develop the plan for testing the 'review' control. | G22: Summary Test Plan tab에서 'review' 통제를 테스트하기 위한 계획을 수립하였음. Developed the plan for testing the 'review' control in the tab Summary Test Plan.
F23: 그리고 AND
G24: 'Review' 통제의 일부로서 실행된 각각의 핵심 통제활동에 대해, 운영 효과성을 테스트하기 위해 Control Activity-x라는 별도의 tab을 생성함. For each key control activity executed as part of the 'review' control, create a separate tab Control Activity-x for operating effectiveness testing.
B27: c) | C27: 다음의 사항을 조사하여, 'review' 통제의 운영 효과성을 테스트한다: Test the operating effectiveness of the 'review' control by testing the following: | G27: 해당 기간동안 경영진이 접근권한을 재검증하기 위해 활용하는 접근권한 목록을 조사하여 다음의 각각을 확인. 'Control Activity-x' tab 또는 별도 링크에서 테스트함. Tested the access listing which is used by management to execute the revalidation of access rights during the relevant period to verify each of the following. Testing in tab 'Control Activity-x' or provided link.
C29: i) | D29: 해당 기간동안 접근권한(super user, administrative access 및 generic IDs를 포함)의 재검증을 위해 경영진이 사용한 접근권한 목록. The access listing which is used by management to execute the revalidation of access rights (including super user, administrative access and/or generic IDs) during the relevant period.
G30: - | H30: 통제운영자가 생성되는 정보의 완전성과 정확성을 확인하였는지에 대한 적절한 근거 증빙의 존재, 그리고 The existence of appropriate supporting evidence that the control operator verified completeness and accuracy of the information being generated, and
G32: - | H32: 해당 기간동안, 적절한 환경에서 보고서를 생성하기 위해 실행된 변수 쿼리 (parameters of query)나 자동 스크립트 (automated script), 그리고 The parameters of the query or automated script used to generate the report being run in the appropriate environment, in the relevant period, and
C34: ii) | D34: 해당 기간동안 경영진의 접근권한(super user, administrative access 및 generic IDs를 포함) 재검증 검토내역 샘플. A sample of management access revalidation reviews (including super user, administrative access and/or generic IDs) during the relevant period. | G34: - | H34: 관련 정책 및 절차에 따라 접근권한의 재검증을 수행하는 담당자 (예, 매니저, role owners, data owners 등)에게 접근권한 목록이 모두 배포됨 (예, 자동화, 이메일 공지 등). The access list was fully distributed (e.g. automation, email notification, etc.) to the relevant personnel responsible for executing the revalidation of access rights (e.g. managers, role owners, data owners, etc.) in accordance with the relevant policies and/or procedures.
C38: iii) | D38: 해당 기간동안 완료되고 승인된 접근권한 재검증 검토내역. The completed and approved access revalidation review during the relevant period. | F38: 그리고 AND
G39: 해당 기간동안 경영진의 접근권한 재검증에 대한 검토내역 중 샘플을 테스트하여 다음의 각각을 확인. 'Control Activity-x' tab 또는 별도 링크에서 테스트함. Tested a sample of management access revalidation reviews during the relevant period to verify each of the following. Testing in tab 'Control Activity-x' or provided link.
G41: - | H41: 경영진이 시스템 또는 신뢰할 만한 출처에서 입수한 완전하고 정확한 데이터를 근거로 하여 시스템상 부여된 접근권한을 승인된 직무책임(job responsibilities)과 비교하는지에 대한 적절한 근거 증빙의 존재, 그리고 The existence of appropriate supporting evidence that management compared the user access rights within the system to the approved job responsibilities based on complete and accurate data from the system or trusted source, and
C42: Note: 질문만으로는 특정 통제의 효과성 테스트로 충분하지 않음. 수동 통제의 운영 효과성을 평가하는 테스트 방법의 목록은 US PwC Audit 5400 and US PwC Audit (NP) 5400를 참조. Note: Inquiry alone is not sufficient to test the operating effectiveness of a control. Refer to US PwC Audit 5400 and/or US PwC Audit (NP) 5400 for a listing of testing techniques to evaluate the effective operation of a manual control. Direct entity level control(direct ELC) 및 특정 'review' 통제의 경우, 운영 효과성에 대한 테스트는 경영진의 설명 및 통제 실행의 결론의 합리성과 정확성에 대한 증거를 제공하고, 질문, 회의 참석, 승인(서명)에 대한 검사 및 입수한 설명에 대한 단순한 문서화를 넘어서는 충분한 증거를 포함해야 함. For direct entity level controls and certain 'review' controls, the testing of operating effectiveness should corroborate the reasonableness and accuracy of management's explanations and conclusions resulting from their execution of the control, and should also include sufficient evidence that goes beyond inquiry, attendance at meetings, inspection of sign-offs, and mere documentation that explanations were obtained.
G44: - | H44: 관련된 정책 및 절차에 따라 변경(modification)에 대한 지속적인 접근/요청을 경영진이 적시에 승인하였는지에 대한 적절한 근거 증빙의 존재, 그리고 The existence of appropriate supporting evidence that management approval for continued access/request for modification was processed in a timely manner in accordance with the relevant policies and/or procedures, and
G47: - | H47: 요청된 경우, 관련 정책 및 절차에 따라 적시에 접근권한이 삭제됨. The access, when requested, was removed in a timely manner in accordance with the relevant polices and/or procedures.
F49: 그리고 AND
G50: 해당 기간 동안 완료되고 승인된 접근권한 재검증 검토내역을 테스트하여 다음의 각각을 확인. 'Control Activity-x' tab 또는 별도 링크에서 테스트함. Tested the completed and approved access revalidation review during the relevant period to verify each of the following. Testing in tab 'Control Activity-x' or provided link.
G53: - | H53: 검토자들로부터 요청된 접근권한 수정사항이 시스템 내에서 완전하고 정확하게 처리되었는지에 대하여 경영진이 검증한 적절한 근거 증빙의 존재, 그리고 The existence of appropriate supporting evidence of management verification that requested access modifications from reviewers were processed in the system completely and accurately, and
G56: - | H56: 검토되지 않은 접근권한이 관련된 정책 및 절차에 따라 해결되었는지 경영진이 확인하였다는 적절한 근거 증빙의 존재, 그리고 The existence of appropriate supporting evidence of management confirmation that any access not reviewed was addressed in accordance with the relevant policies and/or procedures, and
G59: - | H59: 관련된 정책 및 절차에 따라 전반적인 검토가 수행되었음을 나타내는 경영진 최종 승인(Sign-off) 혹은 기타 검증 (예, 이메일, tickmarks)의 적절한 근거 증빙의 존재. The existence of appropriate supporting evidence of management final sign-off or other validation (e.g. emails, tickmarks) that the overall access review had been executed in accordance with the relevant policies and/or procedures.
B63: d) | C63: 각 세부 통제 활동에서 식별된 예외사항을 포함한 모든 테스트 결과 및 기타 증거를 고려하여, 'review' 통제가 효과적으로 운영되는지 판단한다. 통제가 효과적으로 운영되지 않는다고 판단될 경우, 통제 미비점을 SAD 또는 CD/W log에 집계하고 감사 전략 및 감사 절차 계획에 대한 통제 미비점의 영향을 평가한다. Consider all test results and other evidence, including exceptions identified in any of the underlying control activities, and determine whether the 'review' control is operating effectively. If the control is determined not to be operating effectively, post the control deficiency to the SAD / CD/W log and evaluate the impact of the control deficiency on the audit strategy and planned audit procedures. | G63: 각 Contol Activity-x Template에서 테스트 결과를 평가함, 그리고 Evaluated testing results within each of the Control Activity-x templates, and
H64: 식별된 예외사항이나 포함된 통제 활동들 간에 상충되는 감사 증거는 없음. 따라서, 'review' 통제 및 그에 포함된 통제 활동들은 효과적으로 운영되었다고 판단함, 또는 There were no exceptions identified or contrary evidence within the underlying control activities. Accordingly, the 'review' control and its underlying control activities were determined to be operating effectively, or
H67: 식별된 예외사항 그리고/또는 포함된 통제 활동들 간에 상충되는 감사 증거가 존재함. 따라서, 'review' 통제가 효과적으로 운영되지 않았다고 판단함. 통제 미비점을 SAD 또는 CD/W log에 집계하고 감사 전략 및 감사 절차 계획에 대한 통제 미비점의 영향을 평가함. There were exceptions identified and/or contrary evidence within the underlying control activities. Accordingly, the 'review' control was determined not to be operating effectively. The control deficiency was posted to the SAD / CD/W log and the impact of the control deficiency on the audit strategy and planned audit procedures was evaluated.
G72: [테스트 결과 및 영향을 문서화] [Document testing results and impact]
B75: 필요한 경우, 감사팀에서 추가한 특정의 감사 절차 Additional engagement specific procedures, if necessary
B76: Procedures | F76: Results
B77: [필요한 경우, 추가적인 특정의 감사 절차를 문서화] [Document engagement specific additional procedures, if necessary] | F77: [추가 절차의 결과를 문서화] [Document results of additional procedures]
B81: Guidance (click + to expand):
B83: AUDIT GUIDE
B84: US PwC Audit 1206 - Audit evidence
C85: US PwC Audit (NP) 1206 - Audit evidence
B86: US PwC Audit 5400 - Determine nature, timing and extent of controls testing to be performed
C87: US PwC Audit (NP) 5400 - Determine nature, timing and extent of controls testing to be performed
B89: SMART GUIDANCE
C90: Testing of Review Controls
B92: GUIDANCE
B93:  | C93: 질문 만으로는 특정 통제의 효과성에 대한 결론을 뒷받침하기에 충분하지 않을 것이다. 통제의 수행 시 사용되거나 통제 수행으로 인하여 생성된 보고서, 매뉴얼 또는 기타의 문서를 조사하여 추가적인 근거를 얻을 필요성이 있는지 고려한다. Inquiry alone will not provide sufficient evidence to support a conclusion about the effectiveness of a specific control. Consider the need to get further support by examining reports, manuals or other documents used in or generated by the performance of the control.
B95:  | C95: 감사인이 관찰을 하고 있을 때의 통제는 감사인이 없을 때와 같은 방식으로 수행되지 않을 것이다. 게다가, 관찰은 단지 특정 시점에만 해당된다. 특정 기간 동안의 통제의 운영에 대한 충분한 증거를 입수하기 위해, 통제의 여러 instance에 대해 관찰을 수행하거나 세부적인 질문이나 문서 조사와 같은 추가적인 테스트 방법과 조합하여 관찰을 수행할 것을 고려한다. The control being observed might not be performed in the same manner when the auditors are not present. In addition, observation is pertinent only at a point in time. Consider performing observation of multiple instances of the control, or combining observation with additional testing methods, such as detailed inquiry or inspection of documentation, to gain further evidence about the operation of the control over the period.
B98:  | C98: 특정 시점의 통제에 대한 검사 또는 재수행을 수행할 때, 감사 기간에 걸쳐 통제가 효과적으로 운영되는지에 대한 충분한 감사 증거를 입수할 방법을 고려한다. (예를 들어, ITGC, 변경이 없다는 기타 증거 등) When inspecting or reperforming the control at a point in time, consider how to obtain sufficient evidence that a control is operating effectively throughout the audit period (e.g., ITGCs, other evidence of no change, etc.).
B100:  | C100: 'Review' 통제는 특정한 통제 목적을 달성하기 위하여 개인이 정보를 다양한 방식으로 검토하는 통제이다. (예를 들어, 가격 마스터파일에 대한 변경내역 검토, 차이조정에 대한 검토 등) Direct entity level control(direct ELC) 및 일부 'review' 통제의 경우, 운영 효과성에 대한 테스트는 경영진의 설명 및 통제 실행의 결론의 합리성과 정확성에 대한 증거를 제공하고, 질문, 회의 참석, 승인(서명)에 대한 검사 및 입수한 설명에 대한 단순한 문서화를 넘어서는 충분한 증거를 포함해야 한다. 가능한 감사 증거 원천의 예시는 다음을 포함한다: A 'review' control is any control where an individual performs some type of review of information to accomplish a particular control objective (e.g., review of pricing master file changes; review of reconciliations, et al.). For direct entity-level controls and certain 'review' controls, the testing of operating effectiveness should corroborate the reasonableness and accuracy of management's explanations and conclusions resulting from their execution of the control, and/or obtain sufficient evidence that goes beyond inquiry, attendance at meetings, inspection of sign-offs, and mere documentation that explanations were obtained. Examples of potential evidence sources include:
C104: - | D104: 설계된 바와 같이 후속절차가 수행될 항목들이 식별됨 Matters for follow-up are identified, as designed
C105: - | D105: 설계된 바와 같이 후속절차/investigation이 적절하게 수행됨 Foll0w-up / investigation is performed appropriately, as designed
C106: - | D106: 통제에 사용된 데이터는 그 목적에 맞추어 충분히 신뢰할 수 있음. Data used in the control is sufficiently reliable for that purpose
C107: - | D107: 해당 통제는 과거에 실패하지 않았음 (예, SUM 또는 조정사항 없이 통제를 수행) The control has not failed in the past (e.g., no SUMs or adjustments got past the control that should not have)
C108: - | D108: 해당 통제가 과거에 수행된 것으로 보임 (예, 통제로 인해 threshold 이상의 잠재적 왜곡표시가 적시에 적발됨) The control has been shown to work in the past (e.g., potential misstatements above the threshold have been timely detected by the control)
B109:  | C109: 관련 application이 정확하고 신뢰성있는 정보(즉, standing data)를 이용하는지 여부를 고려한다. 필요한 경우, 데이터의 신뢰성(즉, 완전성, 정확성과 유효성)에 대한 증거를 입수하기 위한 추가적인 절차를 고려한다. Consider whether the application draws upon accurate and reliable data (i.e. standing data). To the extent necessary, consider additional procedures to obtain evidence of the reliability of the data (i.e. completeness, accuracy and validity).
B111:  | C111: 예외사항이 식별되는 경우, 예외사항의 잠재적 결과를 이해하기 위해 질문하고 다음을 결정한다: When exceptions are identified, make inquiries to understand their potential consequences and determine whether:
C112: - | D112: 수행된 통제 테스트가 통제에 의존하기 위한 적절한 근거를 제공하는지, the tests of controls that have been performed provide an appropriate basis for reliance on the controls,
C113: - | D113: 추가적인 통제 테스트가 필요한지, additional tests of controls are necessary,
C114: - | D114: 왜곡표시 위험에 대응하는 대체적 절차가 요구되는지, risks of misstatement need to be addressed using alternative procedures,
C115: - | D115: 예외사항이 내부통제의 유의한 미비점(US GAAS의 경우에는 material weakness도 포함)에 해당하는지. (이러한 예외사항은 significant matter로 문서화되어야 함) exceptions represent a significant deficiency (as well as material weakness under US GAAS) in internal control (that should be documented as a Significant matter).

Sheet Master Review Procedures (7)
B1: Prior year control testing documentation rolled forward for reference purposes.
B2: 'Review' 통제를 테스트한다 Test 'Review' control
B3: 프로그램 변경(검토) - 프로그램 변경의 적정성을 모니터링한다 Prog. change (Review) - Changes are monitored for appropriateness
B4: 2명 이상의 팀원이 동 EGA를 prepare한 경우, 관여한 팀원의 이름과 수행한 절차를 문서화. When more than one preparer was involved in the completion of this EGA, document the names of the team members involved and the procedures performed. | F4: [팀원의 이니셜/이름 및 수행한 절차를 문서화(예를 들어, 홍길동이 하단 a)절차를 수행)] [Document the initials or names of team members and procedures performed (e.g., Jane Doe performed step a) below)]
B7: Procedures | F7: Results | K7: Links
B8: a) | C8: 'Review' 통제 설계에 변경이 있는지 확인한다. Verify whether there have been changes to the design of the 'review' control. | G8: 'Review' 통제의 설계에 변경이 있는지 확인함, 그리고 Verified if there have been changes to the design of the 'review' control, and
H9: 'Review' 통제 설계에서 변경사항이 파악되지 않음, 또는 No changes were noted in the design of the 'review' control, or
H10: 'Review' 통제 설계에 변경사항이 파악됨. Changes were noted in the design of the 'review' control.
G11: [필요한 경우, 수행한 절차와 변경사항을 문서화] [Document procedures performed and changes, as necessary]
F12: 그리고 AND
G13: 'Review' 통제의 설계를 평가함, 그리고 Evaluated the design of the 'review' control, and
H14: 통제가 효과적으로 설계되었다고 판단함, 또는 Concluded the control is designed effectively, or
H15: 통제가 효과적으로 설계되어 있지 않다고 판단하여, 식별된 미비점을 SAD에 기록하고 해당 업무프로세스의 영향을 받는 FSLI에 대한 감사 계획을 고려함. Concluded the control is not designed effectively, and posted the identified deficiency to the SAD and considered the planned audit procedures for the FSLIs impacted by the business process.
G18: [영향을 받는 FSLI에 대한 감사 계획을 평가한 세부 내용을 문서화] [Document details of evaluation of planned audit procedures for impacted FSLIs]
B21: b) | C21: 'Review' 통제를 테스트하기 위한 계획을 수립한다. Develop the plan for testing the 'review' control. | G21: Summary Test Plan tab에서 'review' 통제를 테스트하기 위한 계획을 수립하였음. Developed the plan for testing the 'review' control in the tab Summary Test Plan.
F22: 그리고 AND
G23: 'Review' 통제의 일부로서 실행된 각각의 핵심 통제활동에 대해, 운영 효과성을 테스트하기 위해 Control Activity-x라는 별도의 tab을 생성함. For each key control activity executed as part of the 'review' control, create a separate tab Control Activity-x for operating effectiveness testing.
B26: c) | C26: 다음의 사항을 조사하여, 'review' 통제의 운영 효과성을 테스트한다: Test the operating effectiveness of the 'review' control by testing the following: | G26: 해당 기간동안 검토 샘플의 증빙을 조사하고 다음의 각각을 확인. 'Control Activity-x' tab 또는 별도 링크에서 테스트함. Tested evidence for a sample of reviews during the relevant period to verify each of the following. Testing in tab 'Control Activity-x' or provided link.
C28: - | D28: 해당 기간동안 수행된 프로그램 변경내역의 검토 샘플과 변경내역 검토의 적정성을 평가한다. A sample of reviews of changes performed during the relevant period and assess the appropriateness of the review of changes. | G28: - | H28: 검토를 위해 시스템에서 처리된 변경내역 모집단의 완전성, 그리고 The completeness of the population of changes processed in the system for review, and
G30: - | H30: 검토 및 승인에 대한 적절한 근거 증빙의 존재 (예, 문서상 서명/이니셜, 문서화된 설명, 체크마크 또는 이메일 등 기타 후속절차의 표시 등), 그리고 The existence of appropriate supporting evidence (e.g., a signature or initials on the document, written explanations, checkmarks, or other indications of follow up, such as an email, etc.) of review and approval, and
C32: Note: 질문만으로는 특정 통제의 효과성 테스트로 충분하지 않음. 수동 통제의 운영 효과성을 평가하는 테스트 방법의 목록은 US PwC Audit 5400 and US PwC Audit (NP) 5400를 참조. Note: Inquiry alone is not sufficient to test the operating effectiveness of a control. Refer to US PwC Audit 5400 and/or US PwC Audit (NP) 5400 for a listing of testing techniques to evaluate the effective operation of a manual control. Direct entity level control(direct ELC) 및 특정 'review' 통제의 경우, 운영 효과성에 대한 테스트는 경영진의 설명 및 통제 실행의 결론의 합리성과 정확성에 대한 증거를 제공하고, 질문, 회의 참석, 승인(서명)에 대한 검사 및 입수한 설명에 대한 단순한 문서화를 넘어서는 충분한 증거를 포함해야 함. For direct entity level controls and certain 'review' controls, the testing of operating effectiveness should corroborate the reasonableness and accuracy of management's explanations and conclusions resulting from their execution of the control, and should also include sufficient evidence that goes beyond inquiry, attendance at meetings, inspection of sign-offs, and mere documentation that explanations were obtained.
G33: - | H33: 합의된 정책 및 절차에 따른 검토 및 승인의 수행, 그리고 The performance of the review and approval in accordance with agreed upon working policies and/or procedures, and
G35: - | H35: 변경내역 검토 중 발견된 차이나 예외사항에 대해 적시에 통제운영자가 후속조치를 취하였는지에 대한 적절한 근거 증빙의 존재, 그리고 The existence of appropriate supporting evidence for any control operator follow-up on differences or exceptions noted in a timely manner during review of changes made, and
G38: - | H38: 승인권자의 적정성 (예, 가능한 경우 승인내역과 승인권한자 목록을 비교하거나, 역할과 책임 (roles & responsibilities)에 대한 평가를 통하여) The appropriateness of the approver (e.g., through comparing the approval to a listing of authorized individuals, if available or through evaluation of roles & responsibilities).
B47: d) | C47: 각 세부 통제 활동에서 식별된 예외사항을 포함한 모든 테스트 결과 및 기타 증거를 고려하여, 'review' 통제가 효과적으로 운영되는지 판단한다. 통제가 효과적으로 운영되지 않는다고 판단될 경우, 통제 미비점을 SAD 또는 CD/W log에 집계하고 감사 전략 및 감사 절차 계획에 대한 통제 미비점의 영향을 평가한다. Consider all test results and other evidence, including exceptions identified in any of the underlying control activities, and determine whether the 'review' control is operating effectively. If the control is determined not to be operating effectively, post the control deficiency to the SAD / CD/W log and evaluate the impact of the control deficiency on the audit strategy and planned audit procedures. | G47: 각 Contol Activity-x Template에서 테스트 결과를 평가함, 그리고 Evaluated testing results within each of the Control Activity-x templates, and
H48: 식별된 예외사항이나 포함된 통제 활동들 간에 상충되는 감사 증거는 없음. 따라서, 'review' 통제 및 그에 포함된 통제 활동들은 효과적으로 운영되었다고 판단함, 또는 There were no exceptions identified or contrary evidence within the underlying control activities. Accordingly, the 'review' control and its underlying control activities were determined to be operating effectively, or
H51: 식별된 예외사항 그리고/또는 포함된 통제 활동들 간에 상충되는 감사 증거가 존재함. 따라서, 'review' 통제가 효과적으로 운영되지 않았다고 판단함. 통제 미비점을 SAD 또는 CD/W log에 집계하고 감사 전략 및 감사 절차 계획에 대한 통제 미비점의 영향을 평가함. There were exceptions identified and/or contrary evidence within the underlying control activities. Accordingly, the 'review' control was determined not to be operating effectively. The control deficiency was posted to the SAD / CD/W log and the impact of the control deficiency on the audit strategy and planned audit procedures was evaluated.
G56: [테스트 결과 및 영향을 문서화] [Document testing results and impact]
B59: 필요한 경우, 감사팀에서 추가한 특정의 감사 절차 Additional engagement specific procedures, if necessary
B60: Procedures | F60: Results
B61: [필요한 경우, 추가적인 특정의 감사 절차를 문서화] [Document engagement specific additional procedures, if necessary] | F61: [추가 절차의 결과를 문서화] [Document results of additional procedures]
B65: Guidance (click + to expand):
B67: AUDIT GUIDE
B68: US PwC Audit 1206 - Audit evidence
C69: US PwC Audit (NP) 1206 - Audit evidence
B70: US PwC Audit 5400 - Determine nature, timing and extent of controls testing to be performed
C71: US PwC Audit (NP) 5400 - Determine nature, timing and extent of controls testing to be performed
B73: SMART GUIDANCE
C74: Testing of Review Controls
B76: GUIDANCE
B77:  | C77: 질문 만으로는 특정 통제의 효과성에 대한 결론을 뒷받침하기에 충분하지 않을 것이다. 통제의 수행 시 사용되거나 통제 수행으로 인하여 생성된 보고서, 매뉴얼 또는 기타의 문서를 조사하여 추가적인 근거를 얻을 필요성이 있는지 고려한다. Inquiry alone will not provide sufficient evidence to support a conclusion about the effectiveness of a specific control. Consider the need to get further support by examining reports, manuals or other documents used in or generated by the performance of the control.
B79:  | C79: 감사인이 관찰을 하고 있을 때의 통제는 감사인이 없을 때와 같은 방식으로 수행되지 않을 것이다. 게다가, 관찰은 단지 특정 시점에만 해당된다. 특정 기간 동안의 통제의 운영에 대한 충분한 증거를 입수하기 위해, 통제의 여러 instance에 대해 관찰을 수행하거나 세부적인 질문이나 문서 조사와 같은 추가적인 테스트 방법과 조합하여 관찰을 수행할 것을 고려한다. The control being observed might not be performed in the same manner when the auditors are not present. In addition, observation is pertinent only at a point in time. Consider performing observation of multiple instances of the control, or combining observation with additional testing methods, such as detailed inquiry or inspection of documentation, to gain further evidence about the operation of the control over the period.
B82:  | C82: 특정 시점의 통제에 대한 검사 또는 재수행을 수행할 때, 감사 기간에 걸쳐 통제가 효과적으로 운영되는지에 대한 충분한 감사 증거를 입수할 방법을 고려한다. (예를 들어, ITGC, 변경이 없다는 기타 증거 등) When inspecting or reperforming the control at a point in time, consider how to obtain sufficient evidence that a control is operating effectively throughout the audit period (e.g., ITGCs, other evidence of no change, etc.).
B84:  | C84: 'Review' 통제는 특정한 통제 목적을 달성하기 위하여 개인이 정보를 다양한 방식으로 검토하는 통제이다. (예를 들어, 가격 마스터파일에 대한 변경내역 검토, 차이조정에 대한 검토 등) Direct entity level control(direct ELC) 및 일부 'review' 통제의 경우, 운영 효과성에 대한 테스트는 경영진의 설명 및 통제 실행의 결론의 합리성과 정확성에 대한 증거를 제공하고, 질문, 회의 참석, 승인(서명)에 대한 검사 및 입수한 설명에 대한 단순한 문서화를 넘어서는 충분한 증거를 포함해야 한다. 가능한 감사 증거 원천의 예시는 다음을 포함한다: A 'review' control is any control where an individual performs some type of review of information to accomplish a particular control objective (e.g., review of pricing master file changes; review of reconciliations, et al.). For direct entity-level controls and certain 'review' controls, the testing of operating effectiveness should corroborate the reasonableness and accuracy of management's explanations and conclusions resulting from their execution of the control, and/or obtain sufficient evidence that goes beyond inquiry, attendance at meetings, inspection of sign-offs, and mere documentation that explanations were obtained. Examples of potential evidence sources include:
C88: - | D88: 설계된 바와 같이 후속절차가 수행될 항목들이 식별됨 Matters for follow-up are identified, as designed
C89: - | D89: 설계된 바와 같이 후속절차/investigation이 적절하게 수행됨 Foll0w-up / investigation is performed appropriately, as designed
C90: - | D90: 통제에 사용된 데이터는 그 목적에 맞추어 충분히 신뢰할 수 있음. Data used in the control is sufficiently reliable for that purpose
C91: - | D91: 해당 통제는 과거에 실패하지 않았음 (예, SUM 또는 조정사항 없이 통제를 수행) The control has not failed in the past (e.g., no SUMs or adjustments got past the control that should not have)
C92: - | D92: 해당 통제가 과거에 수행된 것으로 보임 (예, 통제로 인해 threshold 이상의 잠재적 왜곡표시가 적시에 적발됨) The control has been shown to work in the past (e.g., potential misstatements above the threshold have been timely detected by the control)
B93:  | C93: 관련 application이 정확하고 신뢰성있는 정보(즉, standing data)를 이용하는지 여부를 고려한다. 필요한 경우, 데이터의 신뢰성(즉, 완전성, 정확성과 유효성)에 대한 증거를 입수하기 위한 추가적인 절차를 고려한다. Consider whether the application draws upon accurate and reliable data (i.e. standing data). To the extent necessary, consider additional procedures to obtain evidence of the reliability of the data (i.e. completeness, accuracy and validity).
B95:  | C95: 예외사항이 식별되는 경우, 예외사항의 잠재적 결과를 이해하기 위해 질문하고 다음을 결정한다: When exceptions are identified, make inquiries to understand their potential consequences and determine whether:
C96: - | D96: 수행된 통제 테스트가 통제에 의존하기 위한 적절한 근거를 제공하는지, the tests of controls that have been performed provide an appropriate basis for reliance on the controls,
C97: - | D97: 추가적인 통제 테스트가 필요한지, additional tests of controls are necessary,
C98: - | D98: 왜곡표시 위험에 대응하는 대체적 절차가 요구되는지, risks of misstatement need to be addressed using alternative procedures,
C99: - | D99: 예외사항이 내부통제의 유의한 미비점(US GAAS의 경우에는 material weakness도 포함)에 해당하는지. (이러한 예외사항은 significant matter로 문서화되어야 함) exceptions represent a significant deficiency (as well as material weakness under US GAAS) in internal control (that should be documented as a Significant matter).

Sheet Master Review Procedures (16)
B1: Prior year control testing documentation rolled forward for reference purposes.
B2: 'Review' 통제를 테스트한다 Test 'Review' control
B3: Process-wide (검토) - IT 내의 업무분장을 위한 정책이 존재한다 Process-wide (Review) - Segregation of duties policies are maintained for segregation of duties within IT
B4: 2명 이상의 팀원이 동 EGA를 prepare한 경우, 관여한 팀원의 이름과 수행한 절차를 문서화. When more than one preparer was involved in the completion of this EGA, document the names of the team members involved and the procedures performed. | F4: [팀원의 이니셜/이름 및 수행한 절차를 문서화(예를 들어, 홍길동이 하단 a)절차를 수행)] [Document the initials or names of team members and procedures performed (e.g., Jane Doe performed step a) below)]
B7: Procedures | F7: Results | K7: Links
B8: a) | C8: 'Review' 통제 설계에 변경이 있는지 확인한다. Verify whether there have been changes to the design of the 'review' control. | G8: 'Review' 통제의 설계에 변경이 있는지 확인함, 그리고 Verified if there have been changes to the design of the 'review' control, and
H9: 'Review' 통제 설계에서 변경사항이 파악되지 않음, 또는 No changes were noted in the design of the 'review' control, or
H10: 'Review' 통제 설계에 변경사항이 파악됨. Changes were noted in the design of the 'review' control.
G11: [필요한 경우, 수행한 절차와 변경사항을 문서화] [Document procedures performed and changes, as necessary]
F12: 그리고 AND
G13: 'Review' 통제의 설계를 평가함, 그리고 Evaluated the design of the 'review' control, and
H14: 통제가 효과적으로 설계되었다고 판단함, 또는 Concluded the control is designed effectively, or
H15: 통제가 효과적으로 설계되어 있지 않다고 판단하여, 식별된 미비점을 SAD에 기록하고 해당 업무프로세스의 영향을 받는 FSLI에 대한 감사 계획을 고려함. Concluded the control is not designed effectively, and posted the identified deficiency to the SAD and considered the planned audit procedures for the FSLIs impacted by the business process.
G18: [영향을 받는 FSLI에 대한 감사 계획을 평가한 세부 내용을 문서화] [Document details of evaluation of planned audit procedures for impacted FSLIs]
B21: b) | C21: 'Review' 통제를 테스트하기 위한 계획을 수립한다. Develop the plan for testing the 'review' control. | G21: Summary Test Plan tab에서 'review' 통제를 테스트하기 위한 계획을 수립하였음. Developed the plan for testing the 'review' control in the tab Summary Test Plan.
F22: 그리고 AND
G23: 'Review' 통제의 일부로서 실행된 각각의 핵심 통제활동에 대해, 운영 효과성을 테스트하기 위해 Control Activity-x라는 별도의 tab을 생성함. For each key control activity executed as part of the 'review' control, create a separate tab Control Activity-x for operating effectiveness testing.
B26: c) | C26: 다음의 사항을 조사하여, 'review' 통제의 운영 효과성을 테스트한다: Test the operating effectiveness of the 'review' control by testing the following: | G26: 업무분장과 관련된 경영진의 통제활동 별로, 통제가 해당 기간 동안 효과적으로 운영된 사례의 샘플에 대한 증거를 조사함. 'Control Activity-x' tab또는 별도 링크에서 테스트함. For each management's control around the SOD, tested evidence for a sample of instances that the control was operating effectively during the relevant period. Testing in tab 'Control Activity-x' or provided link.
C28: i) | D28: a) 질문에서 결정된 업무분장과 관련된 경영진의 통제활동 별로, 각 통제가 해당 기간동안 효과적으로 운영된 사례의 샘플에 대한 증거 For each management's control around the SOD (as determined in a) Inquiry), evidence for a sample of instances that the control was operating effectively during the relevant period.
F29: 그리고 AND
G30: 업무분장이 충돌한 모든 관련 업무에 대해 해당 기간 동안 개인별로 할당된 역할과 책임(roles and responsibilities)에 따라 실제로 업무가 수행되었는지 확인하기 위해 업무분장 충돌내역에 대해 조사함. 'Control Activity-x' tab또는 별도 링크에서 테스트함. For all relevant SOD conflicts, tested the SOD conflicts to verify that they are actually being carried out in accordance with individuals' assigned roles and responsibilities during the relevant period. Testing in tab 'Control Activity-x' or provided link.
C33: ii) | D33: 업무분장이 충돌한 모든 관련 업무에 대해, 해당 기간동안 개인별로 할당된 역할과 책임 (roles and responsibilities)에 따라 실제로 업무가 수행되었는지 확인한다. For all relevant SOD conflicts verify that they are actually being carried out in accordance with individuals' assigned roles and responsibilities during the relevant period.
C38: Note: 질문만으로는 특정 통제의 효과성 테스트로 충분하지 않음. 수동 통제의 운영 효과성을 평가하는 테스트 방법의 목록은 US PwC Audit 5400 and US PwC Audit (NP) 5400를 참조. Note: Inquiry alone is not sufficient to test the operating effectiveness of a control. Refer to US PwC Audit 5400 and/or US PwC Audit (NP) 5400 for a listing of testing techniques to evaluate the effective operation of a manual control. Direct entity level control(direct ELC) 및 특정 'review' 통제의 경우, 운영 효과성에 대한 테스트는 경영진의 설명 및 통제 실행의 결론의 합리성과 정확성에 대한 증거를 제공하고, 질문, 회의 참석, 승인(서명)에 대한 검사 및 입수한 설명에 대한 단순한 문서화를 넘어서는 충분한 증거를 포함해야 함. For direct entity level controls and certain 'review' controls, the testing of operating effectiveness should corroborate the reasonableness and accuracy of management's explanations and conclusions resulting from their execution of the control, and should also include sufficient evidence that goes beyond inquiry, attendance at meetings, inspection of sign-offs, and mere documentation that explanations were obtained.
B52: d) | C52: 각 세부 통제 활동에서 식별된 예외사항을 포함한 모든 테스트 결과 및 기타 증거를 고려하여, 'review' 통제가 효과적으로 운영되는지 판단한다. 통제가 효과적으로 운영되지 않는다고 판단될 경우, 통제 미비점을 SAD 또는 CD/W log에 집계하고 감사 전략 및 감사 절차 계획에 대한 통제 미비점의 영향을 평가한다. Consider all test results and other evidence, including exceptions identified in any of the underlying control activities, and determine whether the 'review' control is operating effectively. If the control is determined not to be operating effectively, post the control deficiency to the SAD / CD/W log and evaluate the impact of the control deficiency on the audit strategy and planned audit procedures. | G52: 각 Contol Activity-x Template에서 테스트 결과를 평가함, 그리고 Evaluated testing results within each of the Control Activity-x templates, and
H53: 식별된 예외사항이나 포함된 통제 활동들 간에 상충되는 감사 증거는 없음. 따라서, 'review' 통제 및 그에 포함된 통제 활동들은 효과적으로 운영되었다고 판단함, 또는 There were no exceptions identified or contrary evidence within the underlying control activities. Accordingly, the 'review' control and its underlying control activities were determined to be operating effectively, or
H56: 식별된 예외사항 그리고/또는 포함된 통제 활동들 간에 상충되는 감사 증거가 존재함. 따라서, 'review' 통제가 효과적으로 운영되지 않았다고 판단함. 통제 미비점을 SAD 또는 CD/W log에 집계하고 감사 전략 및 감사 절차 계획에 대한 통제 미비점의 영향을 평가함. There were exceptions identified and/or contrary evidence within the underlying control activities. Accordingly, the 'review' control was determined not to be operating effectively. The control deficiency was posted to the SAD / CD/W log and the impact of the control deficiency on the audit strategy and planned audit procedures was evaluated.
G61: [테스트 결과 및 영향을 문서화] [Document testing results and impact]
B64: 필요한 경우, 감사팀에서 추가한 특정의 감사 절차 Additional engagement specific procedures, if necessary
B65: Procedures | F65: Results
B66: [필요한 경우, 추가적인 특정의 감사 절차를 문서화] [Document engagement specific additional procedures, if necessary] | F66: [추가 절차의 결과를 문서화] [Document results of additional procedures]
B70: Guidance (click + to expand):
B72: AUDIT GUIDE
B73: US PwC Audit 1206 - Audit evidence
C74: US PwC Audit (NP) 1206 - Audit evidence
B75: US PwC Audit 5400 - Determine nature, timing and extent of controls testing to be performed
C76: US PwC Audit (NP) 5400 - Determine nature, timing and extent of controls testing to be performed
B78: SMART GUIDANCE
C79: Testing of Review Controls
B81: GUIDANCE
B82:  | C82: 질문 만으로는 특정 통제의 효과성에 대한 결론을 뒷받침하기에 충분하지 않을 것이다. 통제의 수행 시 사용되거나 통제 수행으로 인하여 생성된 보고서, 매뉴얼 또는 기타의 문서를 조사하여 추가적인 근거를 얻을 필요성이 있는지 고려한다. Inquiry alone will not provide sufficient evidence to support a conclusion about the effectiveness of a specific control. Consider the need to get further support by examining reports, manuals or other documents used in or generated by the performance of the control.
B84:  | C84: 감사인이 관찰을 하고 있을 때의 통제는 감사인이 없을 때와 같은 방식으로 수행되지 않을 것이다. 게다가, 관찰은 단지 특정 시점에만 해당된다. 특정 기간 동안의 통제의 운영에 대한 충분한 증거를 입수하기 위해, 통제의 여러 instance에 대해 관찰을 수행하거나 세부적인 질문이나 문서 조사와 같은 추가적인 테스트 방법과 조합하여 관찰을 수행할 것을 고려한다. The control being observed might not be performed in the same manner when the auditors are not present. In addition, observation is pertinent only at a point in time. Consider performing observation of multiple instances of the control, or combining observation with additional testing methods, such as detailed inquiry or inspection of documentation, to gain further evidence about the operation of the control over the period.
B87:  | C87: 특정 시점의 통제에 대한 검사 또는 재수행을 수행할 때, 감사 기간에 걸쳐 통제가 효과적으로 운영되는지에 대한 충분한 감사 증거를 입수할 방법을 고려한다. (예를 들어, ITGC, 변경이 없다는 기타 증거 등) When inspecting or reperforming the control at a point in time, consider how to obtain sufficient evidence that a control is operating effectively throughout the audit period (e.g., ITGCs, other evidence of no change, etc.).
B89:  | C89: 'Review' 통제는 특정한 통제 목적을 달성하기 위하여 개인이 정보를 다양한 방식으로 검토하는 통제이다. (예를 들어, 가격 마스터파일에 대한 변경내역 검토, 차이조정에 대한 검토 등) Direct entity level control(direct ELC) 및 일부 'review' 통제의 경우, 운영 효과성에 대한 테스트는 경영진의 설명 및 통제 실행의 결론의 합리성과 정확성에 대한 증거를 제공하고, 질문, 회의 참석, 승인(서명)에 대한 검사 및 입수한 설명에 대한 단순한 문서화를 넘어서는 충분한 증거를 포함해야 한다. 가능한 감사 증거 원천의 예시는 다음을 포함한다: A 'review' control is any control where an individual performs some type of review of information to accomplish a particular control objective (e.g., review of pricing master file changes; review of reconciliations, et al.). For direct entity-level controls and certain 'review' controls, the testing of operating effectiveness should corroborate the reasonableness and accuracy of management's explanations and conclusions resulting from their execution of the control, and/or obtain sufficient evidence that goes beyond inquiry, attendance at meetings, inspection of sign-offs, and mere documentation that explanations were obtained. Examples of potential evidence sources include:
C93: - | D93: 설계된 바와 같이 후속절차가 수행될 항목들이 식별됨 Matters for follow-up are identified, as designed
C94: - | D94: 설계된 바와 같이 후속절차/investigation이 적절하게 수행됨 Foll0w-up / investigation is performed appropriately, as designed
C95: - | D95: 통제에 사용된 데이터는 그 목적에 맞추어 충분히 신뢰할 수 있음. Data used in the control is sufficiently reliable for that purpose
C96: - | D96: 해당 통제는 과거에 실패하지 않았음 (예, SUM 또는 조정사항 없이 통제를 수행) The control has not failed in the past (e.g., no SUMs or adjustments got past the control that should not have)
C97: - | D97: 해당 통제가 과거에 수행된 것으로 보임 (예, 통제로 인해 threshold 이상의 잠재적 왜곡표시가 적시에 적발됨) The control has been shown to work in the past (e.g., potential misstatements above the threshold have been timely detected by the control)
B98:  | C98: 관련 application이 정확하고 신뢰성있는 정보(즉, standing data)를 이용하는지 여부를 고려한다. 필요한 경우, 데이터의 신뢰성(즉, 완전성, 정확성과 유효성)에 대한 증거를 입수하기 위한 추가적인 절차를 고려한다. Consider whether the application draws upon accurate and reliable data (i.e. standing data). To the extent necessary, consider additional procedures to obtain evidence of the reliability of the data (i.e. completeness, accuracy and validity).
B100:  | C100: 예외사항이 식별되는 경우, 예외사항의 잠재적 결과를 이해하기 위해 질문하고 다음을 결정한다: When exceptions are identified, make inquiries to understand their potential consequences and determine whether:
C101: - | D101: 수행된 통제 테스트가 통제에 의존하기 위한 적절한 근거를 제공하는지, the tests of controls that have been performed provide an appropriate basis for reliance on the controls,
C102: - | D102: 추가적인 통제 테스트가 필요한지, additional tests of controls are necessary,
C103: - | D103: 왜곡표시 위험에 대응하는 대체적 절차가 요구되는지, risks of misstatement need to be addressed using alternative procedures,
C104: - | D104: 예외사항이 내부통제의 유의한 미비점(US GAAS의 경우에는 material weakness도 포함)에 해당하는지. (이러한 예외사항은 significant matter로 문서화되어야 함) exceptions represent a significant deficiency (as well as material weakness under US GAAS) in internal control (that should be documented as a Significant matter).

Sheet Master Testing Table Review
B1: Prior year control testing documentation rolled forward for reference purposes.
B3: 세부 테스트 내역 - 통제 활동 [x] Detailed Testing Table - Control Activity-[x]
B4: 'Review' 통제의 설계, 성격 및 빈도에 따라서 이 탭의 사용이 필요할 수도 있고 필요하지 않을 수도 있음. 특정 기간에 여러개의 통제 instance를 테스트하여야 하는 경우에는 이 탭을 사용할 필요가 있음. Use of this tab may or may not be needed based upon the design, nature and frequency of the 'review' control and may be necessary in situations where multiple instances of a control in a given period need to be tested.
B5: No. | C5: 샘플 통제의 세부내역 (예, 청구서 번호) Control Sample Detail (e.g., invoice #) | D5: 일자 Date | E5: [통제 특성 1] [Control Characteristic 1] | F5: [통제 특성 2] [Control Characteristic 2] | G5: [통제 특성 3] [Control Characteristic 3] | H5: [통제 특성 4] [Control Characteristic 4] | I5: [통제 특성 5] [Control Characteristic 5] | J5: 비고 Comments/Notes
B6: 1
B7: 2
B8: 3
B9: 4
B10: 5
B11: 6
B12: 7
B13: 8
B14: 9
B15: 10
B16: 11
B17: 12
... B35: 30

Sheet Master Procedures (1)
B1: Prior year control testing documentation rolled forward for reference purposes.
B2: 테스트를 수행한다 - 질문, 관찰, 검사 및 재수행 Perform testing using inquiry, observation, inspection and reperformance
B3: 시스템에 대한 접근권한 - 시스템에 대한 접근권한 요청은 경영진에 의해 적절히 검토되고 승인된다 Access - Access requests are properly reviewed and authorized by management
B4: Procedures | G4: Results | L4: Links
B5: a) | C5: 질문 Inquiry | H5: 해당 사항 없음. 추가적인 질문이 수행되지 아니함. Not applicable. Additional inquiry not performed. | N5: TRUE
C6: 통제의 다양한 측면을 테스트하기 위하여 해당 통제(자동 통제 부문을 포함하여)를 잘 알고 있는 담당자에게 질문한다. Inquire of personnel knowledgeable of the control (including any automated components) to test the various aspects of the control. | G6: 또는 OR
H7: 질문을 수행하고, 회사의 ITGC에 대한 이해 및 평가 내역을 기술하는 관련 EGA 또는 회사의 내부통제에 대한 이해 및 평가 내역을 기술하는 관련 EGA에 문서화함. Inquired and documented in a related EGA addressing the understanding and evaluation of entity's ITGCs or in a related EGA addressing the understanding and evaluation of entity's internal control.
H10: [링크 첨부] [provide link]
G11: 또는 OR
H12: 통제의 다양한 측면을 고려하여 해당 통제 (자동통제 부문을 포함하여)를 잘 알고 있는 담당자에게 질문: Inquired of personnel knowledgeable of the control considering the various aspects of the control (including any automated control components):
H14: - | I14: 검토를 수행하기위해 활용되는 정보 (예, 정책 및 절차). Information (e.g., policies and/or procedures) that is utilized to perform the review.
H15: - | I15: 통제운영자가 승인권자의 적정성을 확인하는 방법 (예, 가능한 경우 승인내역과 승인권자 목록을 비교하거나, 역할과 책임 (roles & responsibilities)에 대한 평가를 통하여) How the control operator confirms the appropriateness of the approver (e.g., through comparing the approval to a listing of authorized individuals, if available or through evaluation of roles & responsibilities).
H18: - | I18: 통제운영자가 해당 요청이 유효한(valid) 임직원/협력업체에 대한 것인지 확인하는 방법. How the control operator confirms that the request is for a valid employee/contractor.
H20: - | I20: 통제운영자가 시스템에 대한 접근권한 요청 과정에서 발견된 차이 혹은 예외사항에 대해 후속조치를 취하는 방법. How the control operator follows up on differences or exceptions noted during the processing of the access request.
H22: - | I22: 통제운영자가 요청된 시스템에 대한 접근권한이 직무책임(job responsibilities)과 상응한다는 것을 확인하는 방법. How the control operator confirms that access is commensurate with job responsibilities.
H24: - | I24: 통제운영자가 시스템에 대한 접근권한 요청이 시스템 내에서 정확하게 승인되었는지를 확인하는 방법. How the control operator confirms the access request was accurately granted within the system.
H26: - | I26: 해당 통제가 운영된 기간 및 운영 빈도. The period for which the control has been in operation and the frequency of its operation.
H28: - | I28: 해당 통제를 수행하는 사람(들)의 적합성. The appropriateness of the person(s) performing the control(s).
H29: [상세 내역, 질문 대상자 및 날짜를 문서화] [document details, name and date of inquiry]
B31: b) | C31: 관찰 Observation 프로세스 상 자동 처리되는 부문을 포함하여 통제운영자가 정상적인 처리 과정에서 합의된 정책/또는 절차에 따라 통제를 수행하는 것을 관찰한다. During the normal course of processing, observe the control operator performing the control in accordance with agreed upon policies and/or procedures, including any considerations for automated components in the process. | H31: 해당 사항 없음. 관찰이 수행되지 아니함. Not applicable. Observation not performed. | N31: TRUE
G32: 또는 OR
H33: 관찰을 수행하고, 회사의 ITGC에 대한 이해 및 평가 내역을 기술하는 관련 EGA 또는 회사의 내부통제에 대한 이해 및 평가 내역을 기술하는 관련EGA에 문서화함. Observed and documented in a related EGA addressing the understanding and evaluation of entity's ITGCs or in a related EGA addressing the understanding and evaluation of entity's internal control.
H36: [링크 첨부] [provide link]
G37: 또는 OR
H38: 다음의 각각을 포함하여, 통제운영자의 통제수행을 관찰: Observed the control operator performing the control, including each of the following:
